Workbook
Name Slicer_Category: #N/A
Name Slicer_Customer_Segment: #N/A
Name Slicer_Region: #N/A
Name Slicer_Sales_Channel: #N/A

Sheet Raw_Data
A1: Order_ID | B1: Order_Date | C1: Customer_ID | D1: Customer_Name | E1: Customer_Segment | F1: City | G1: State | H1: Region | I1: Category | J1: Product | K1: Quantity | L1: Unit_Price | M1: Discount | N1: Sales | O1: Cost | P1: Profit | Q1: Profit_Margin_% | R1: Payment_Method | S1: Sales_Channel | T1: Salesperson | U1: Month | V1: Year | W1: Day_Name | X1: Delivery_Days | Y1: Delivery_Date | Z1: Order_Status | AA1: Customer_Type | AB1: Priority | AC1: Return_Requested | AD1: Rating | AE1: Column1
A2: ORD10002 | B2: 14-04-2024 | C2: CUST1017 | D2: Aarav Verma | E2: Consumer | F2: Mumbai | G2: Maharashtra | H2: South | I2: Electronics | J2: Tablet | K2: 4 | L2: 12000 | M2: 0.05 | N2: 45600 | O2: 32350.14 | P2: 13249.86 | Q2: 29.06 | R2: Net Banking | S2: Marketplace | T2: Amit | U2: April | V2: 2024 | W2: Sunday | X2: 9 | Y2: 23-04-2024 | Z2: Completed | AA2: VIP | AB2: Low | AC2: No | AD2: 2
A3: ORD10003 | B3: 14-12-2024 | C3: CUST1173 | D3: Arjun Verma | E3: Corporate | F3: Jaipur | G3: Rajasthan | H3: North | I3: Accessories | J3: Wallet | K3: 1 | L3: 800 | M3: 0.15 | N3: 680 | O3: 413.53 | P3: 266.47 | Q3: 39.19 | R3: UPI | S3: Retail Store | T3: Manish | U3: December | V3: 2024 | W3: Saturday | X3: 5 | Y3: 19-12-2024 | Z3: Completed | AA3: Returning | AB3: Low | AC3: No | AD3: 5
A4: ORD10004 | B4: 45778 | C4: CUST1024 | D4: Vikram Agarwal | E4: Corporate | F4: Mumbai | G4: Maharashtra | H4: North | I4: Clothing | J4: Shirt | K4: 9 | L4: 1800 | M4: 0.2 | N4: 12960 | O4: 9593.44 | P4: 3366.56 | Q4: 25.98 | R4: Debit Card | S4: Online | T4: Kavita | U4: January | V4: 2025 | W4: Sunday | X4: 10 | Y4: 15-01-2025 | Z4: Completed | AA4: Returning | AB4: Medium | AC4: No | AD4: 2
A5: ORD10005 | B5: 46001 | C5: CUST1084 | D5: Riya Mehta | E5: Corporate | F5: Chennai | G5: Tamil Nadu | H5: South | I5: Office Supplies | J5: Printer Paper | K5: 5 | L5: 100 | M5: 0.2 | N5: 400 | O5: 298.75 | P5: 101.25 | Q5: 25.31 | R5: UPI | S5: Online | T5: Rahul | U5: October | V5: 2025 | W5: Sunday | X5: 3 | Y5: 15-10-2025 | Z5: Cancelled | AA5: New | AB5: Medium | AC5: No | AD5: 3
A6: ORD10006 | B6: 45902 | C6: CUST1127 | D6: Aditi Kapoor | E6: Corporate | F6: Mumbai | G6: Maharashtra | H6: West | I6: Furniture | J6: Table | K6: 6 | L6: 4000 | M6: 0.15 | N6: 20400 | O6: 12678.96 | P6: 7721.04 | Q6: 37.85 | R6: Net Banking | S6: Retail Store | T6: Vikas | U6: February | V6: 2025 | W6: Sunday | X6: 8 | Y6: 17-02-2025 | Z6: Completed | AA6: New | AB6: Low | AC6: No | AD6: 1
A7: ORD10007 | B7: 45697 | C7: CUST1240 | D7: Meera Kumar | E7: Small Business | F7: Delhi | G7: Delhi | H7: North | I7: Electronics | J7: Smartphone | K7: 3 | L7: 50000 | M7: 0.15 | N7: 127500 | O7: 83262.24 | P7: 44237.76 | Q7: 34.7 | R7: Credit Card | S7: Marketplace | T7: Anjali | U7: September | V7: 2025 | W7: Tuesday | X7: 2 | Y7: 45756 | Z7: Pending | AA7: Returning | AB7: High | AC7: No | AD7: 1
A8: ORD10008 | B8: 27-05-2025 | C8: CUST1321 | D8: Priya Chopra | E8: Small Business | F8: Pune | G8: Maharashtra | H8: South | I8: Clothing | J8: Jeans | K8: 8 | L8: 700 | M8: 0.1 | N8: 5040 | O8: 4013.9 | P8: 1026.1 | Q8: 20.36 | R8: Debit Card | S8: Retail Store | T8: Pooja | U8: May | V8: 2025 | W8: Tuesday | X8: 3 | Y8: 30-05-2025 | Z8: Cancelled | AA8: VIP | AB8: High | AC8: Yes | AD8: 5 | AE8: a
A9: ORD10009 | B9: 45331 | C9: CUST1041 | D9: Aditya Yadav | E9: Corporate | F9: Chennai | G9: Tamil Nadu | H9: North | I9: Clothing | J9: Shirt | K9: 2 | L9: 1800 | M9: 0.1 | N9: 3240 | O9: 2550.08 | P9: 689.92 | Q9: 21.29 | R9: Net Banking | S9: Online | T9: Pooja | U9: September | V9: 2024 | W9: Monday | X9: 1 | Y9: 45360 | Z9: Completed | AA9: VIP | AB9: Medium | AC9: Yes | AD9: 3
A10: ORD10010 | B10: 31-12-2025 | C10: CUST1333 | D10: Sneha Malhotra | E10: Small Business | F10: Ahmedabad | G10: Gujarat | H10: West | I10: Accessories | J10: Sunglasses | K10: 4 | L10: 3000 | M10: 0.05 | N10: 11400 | O10: 9333.07 | P10: 2066.93 | Q10: 18.13 | R10: Credit Card | S10: Online | T10: Rahul | U10: December | V10: 2025 | W10: Wednesday | X10: 5 | Y10: 46143 | Z10: Pending | AA10: New | AB10: Medium | AC10: Yes | AD10: 5
A11: ORD10011 | B11: 25-12-2025 | C11: CUST1017 | D11: Neha Verma | E11: Small Business | F11: Ahmedabad | G11: Gujarat | H11: South | I11: Furniture | J11: Table | K11: 4 | L11: 2500 | M11: 0 | N11: 10000 | O11: 5681.98 | P11: 4318.02 | Q11: 43.18 | R11: UPI | S11: Marketplace | T11: Rohit | U11: December | V11: 2025 | W11: Thursday | X11: 1 | Y11: 26-12-2025 | Z11: Completed | AA11: New | AB11: High | AC11: Yes | AD11: 5
A12: ORD10012 | B12: 45447 | C12: CUST1211 | D12: Riya Chopra | E12: Small Business | F12: Lucknow | G12: Uttar Pradesh | H12: North | I12: Clothing | J12: Jeans | K12: 8 | L12: 2500 | M12: 0.05 | N12: 19000 | O12: 12267.55 | P12: 6732.45 | Q12: 35.43 | R12: Credit Card | S12: Online | T12: Kavita | U12: April | V12: 2024 | W12: Saturday | X12: 2 | Y12: 45508 | Z12: Pending | AA12: VIP | AB12: Medium | AC12: Yes | AD12: 2
A13: ORD10013 | B13: 45450 | C13: CUST1039 | D13: Riya Agarwal | E13: Small Business | F13: Hyderabad | G13: Telangana | H13: North | I13: Furniture | J13: Table | K13: 8 | L13: 4000 | M13: 0.15 | N13: 27200 | O13: 16794.58 | P13: 10405.42 | Q13: 38.26 | R13: Credit Card | S13: Marketplace | T13: Anjali | U13: July | V13: 2024 | W13: Saturday | X13: 5 | Y13: 45603 | Z13: Pending | AA13: New | AB13: Low | AC13: Yes | AD13: 2
A14: ORD10014 | B14: 17-06-2024 | C14: CUST1136 | D14: Riya Kumar | E14: Corporate | F14: Kolkata | G14: West Bengal | H14: West | I14: Clothing | J14: Shoes | K14: 4 | L14: 2500 | M14: 0 | N14: 10000 | O14: 8160.33 | P14: 1839.67 | Q14: 18.4 | R14: Debit Card | S14: Online | T14: Sneha | U14: June | V14: 2024 | W14: Monday | X14: 7 | Y14: 24-06-2024 | Z14: Completed | AA14: New | AB14: Low | AC14: Yes | AD14: 3
A15: ORD10015 | B15: 45571 | C15: CUST1096 | D15: Aditya Bansal | E15: Consumer | F15: Delhi | G15: Delhi | H15: South | I15: Electronics | J15: Monitor | K15: 8 | L15: 35000 | M15: 0.2 | N15: 224000 | O15: 128045.14 | P15: 95954.86 | Q15: 42.84 | R15: Cash | S15: Online | T15: Manish | U15: June | V15: 2024 | W15: Monday | X15: 1 | Y15: 45602 | Z15: Cancelled | AA15: New | AB15: High | AC15: Yes | AD15: 5
A16: ORD10016 | B16: 24-09-2024 | C16: CUST1203 | D16: Rohan Mishra | E16: Small Business | F16: Mumbai | G16: Maharashtra | H16: East | I16: Clothing | J16: T-Shirt | K16: 10 | L16: 3500 | M16: 0.1 | N16: 31500 | O16: 19355.02 | P16: 12144.98 | Q16: 38.56 | R16: Cash | S16: Retail Store | T16: Neeraj | U16: September | V16: 2024 | W16: Tuesday | X16: 4 | Y16: 28-09-2024 | Z16: Completed | AA16: New | AB16: Medium | AC16: Yes | AD16: 1
A17: ORD10017 | B17: 45599 | C17: CUST1225 | D17: Aditi Yadav | E17: Corporate | F17: Ahmedabad | G17: Gujarat | H17: North | I17: Furniture | J17: Table | K17: 5 | L17: 4000 | M17: 0.1 | N17: 18000 | O17: 11285.04 | P17: 6714.96 | Q17: 37.31 | R17: Net Banking | S17: Retail Store | T17: Neeraj | U17: March | V17: 2024 | W17: Monday | X17: 4 | Y17: 15-03-2024 | Z17: Completed | AA17: New | AB17: Medium | AC17: Yes | AD17: 1
A18: ORD10018 | B18: 17-12-2024 | C18: CUST1129 | D18: Vivaan Verma | E18: Small Business | F18: Ahmedabad | G18: Gujarat | H18: West | I18: Furniture | J18: Bookshelf | K18: 5 | L18: 15000 | M18: 0.05 | N18: 71250 | O18: 48910.31 | P18: 22339.69 | Q18: 31.35 | R18: UPI | S18: Online | T18: Amit | U18: December | V18: 2024 | W18: Tuesday | X18: 4 | Y18: 21-12-2024 | Z18: Completed | AA18: Returning | AB18: Low | AC18: No | AD18: 2
A19: ORD10019 | B19: 18-03-2024 | C19: CUST1190 | D19: Nisha Kapoor | E19: Consumer | F19: Jaipur | G19: Rajasthan | H19: West | I19: Accessories | J19: Sunglasses | K19: 9 | L19: 500 | M19: 0 | N19: 4500 | O19: 2518.77 | P19: 1981.23 | Q19: 44.03 | R19: Debit Card | S19: Online | T19: Sneha | U19: March | V19: 2024 | W19: Monday | X19: 3 | Y19: 21-03-2024 | Z19: Cancelled | AA19: Returning | AB19: Low | AC19: No | AD19: 2
A20: ORD10020 | B20: 45479 | C20: CUST1091 | D20: Ishita Sharma | E20: Consumer | F20: Hyderabad | G20: Telangana | H20: East | I20: Electronics | J20: Tablet | K20: 9 | L20: 22000 | M20: 0.2 | N20: 158400 | O20: 128870.38 | P20: 29529.62 | Q20: 18.64 | R20: Cash | S20: Marketplace | T20: Rahul | U20: June | V20: 2024 | W20: Friday | X20: 4 | Y20: 45602 | Z20: Completed | AA20: Returning | AB20: Low | AC20: Yes | AD20: 4
A21: ORD10021 | B21: 45515 | C21: CUST1099 | D21: Pooja Jain | E21: Corporate | F21: Delhi | G21: Delhi | H21: North | I21: Clothing | J21: Jeans | K21: 4 | L21: 2500 | M21: 0.1 | N21: 9000 | O21: 5007.5 | P21: 3992.5 | Q21: 44.36 | R21: UPI | S21: Retail Store | T21: Anjali | U21: November | V21: 2024 | W21: Friday | X21: 4 | Y21: 45637 | Z21: Completed | AA21: Returning | AB21: High | AC21: No | AD21: 1
A22: ORD10022 | B22: 21-04-2024 | C22: CUST1161 | D22: Ishita Bansal | E22: Small Business | F22: Mumbai | G22: Maharashtra | H22: North | I22: Office Supplies | J22: Printer Paper | K22: 10 | L22: 350 | M22: 0 | N22: 3500 | O22: 2251.67 | P22: 1248.33 | Q22: 35.67 | R22: Cash | S22: Marketplace | T22: Rahul | U22: April | V22: 2024 | W22: Sunday | X22: 10 | Y22: 45296 | Z22: Pending | AA22: Returning | AB22: Low | AC22: No | AD22: 1
A23: ORD10023 | B23: 45972 | C23: CUST1064 | D23: Priya Kapoor | E23: Corporate | F23: Ahmedabad | G23: Gujarat | H23: West | I23: Accessories | J23: Watch | K23: 6 | L23: 2000 | M23: 0 | N23: 12000 | O23: 7617.09 | P23: 4382.91 | Q23: 36.52 | R23: UPI | S23: Retail Store | T23: Sneha | U23: November | V23: 2025 | W23: Tuesday | X23: 6 | Y23: 17-11-2025 | Z23: Cancelled | AA23: VIP | AB23: Low | AC23: Yes | AD23: 4
A24: ORD10024 | B24: 15-07-2025 | C24: CUST1221 | D24: Nisha Bansal | E24: Small Business | F24: Kolkata | G24: West Bengal | H24: East | I24: Furniture | J24: Table | K24: 10 | L24: 6000 | M24: 0.15 | N24: 51000 | O24: 32000.8 | P24: 18999.2 | Q24: 37.25 | R24: Cash | S24: Retail Store | T24: Rohit | U24: July | V24: 2025 | W24: Tuesday | X24: 1 | Y24: 16-07-2025 | Z24: Completed | AA24: VIP | AB24: Low | AC24: No | AD24: 2
A25: ORD10025 | B25: 28-08-2024 | C25: CUST1076 | D25: Aarav Sharma | E25: Consumer | F25: Mumbai | G25: Maharashtra | H25: West | I25: Office Supplies | J25: Stapler | K25: 10 | L25: 350 | M25: 0 | N25: 3500 | O25: 2687.2 | P25: 812.8 | Q25: 23.22 | R25: Net Banking | S25: Online | T25: Rohit | U25: August | V25: 2024 | W25: Wednesday | X25: 5 | Y25: 45331 | Z25: Completed | AA25: Returning | AB25: High | AC25: Yes | AD25: 4
A26: ORD10026 | B26: 45964 | C26: CUST1266 | D26: Riya Sharma | E26: Small Business | F26: Jaipur | G26: Rajasthan | H26: South | I26: Clothing | J26: Jeans | K26: 3 | L26: 700 | M26: 0 | N26: 2100 | O26: 1610.93 | P26: 489.07 | Q26: 23.29 | R26: Credit Card | S26: Retail Store | T26: Pooja | U26: March | V26: 2025 | W26: Tuesday | X26: 4 | Y26: 15-03-2025 | Z26: Completed | AA26: Returning | AB26: High | AC26: No | AD26: 4
A27: ORD10027 | B27: 45662 | C27: CUST1327 | D27: Ananya Agarwal | E27: Small Business | F27: Lucknow | G27: Uttar Pradesh | H27: West | I27: Accessories | J27: Sunglasses | K27: 9 | L27: 2000 | M27: 0.05 | N27: 17100 | O27: 12875.95 | P27: 4224.05 | Q27: 24.7 | R27: Debit Card | S27: Retail Store | T27: Rohit | U27: May | V27: 2025 | W27: Thursday | X27: 8 | Y27: 45905 | Z27: Completed | AA27: New | AB27: High | AC27: No | AD27: 2
A28: ORD10028 | B28: 45357 | C28: CUST1110 | D28: Aditya Mehta | E28: Corporate | F28: Pune | G28: Maharashtra | H28: East | I28: Office Supplies | J28: Pen Set | K28: 9 | L28: 100 | M28: 0.05 | N28: 855 | O28: 630.45 | P28: 224.55 | Q28: 26.26 | R28: Net Banking | S28: Retail Store | T28: Kavita | U28: June | V28: 2024 | W28: Monday | X28: 4 | Y28: 45479 | Z28: Pending | AA28: New | AB28: Low | AC28: No | AD28: 4
A29: ORD10029 | B29: 26-12-2024 | C29: CUST1215 | D29: Aditi Yadav | E29: Small Business | F29: Lucknow | G29: Uttar Pradesh | H29: South | I29: Electronics | J29: Monitor | K29: 7 | L29: 22000 | M29: 0 | N29: 154000 | O29: 120186.37 | P29: 33813.63 | Q29: 21.96 | R29: Cash | S29: Online | T29: Sneha | U29: December | V29: 2024 | W29: Thursday | X29: 5 | Y29: 31-12-2024 | Z29: Pending | AA29: Returning | AB29: Medium | AC29: Yes | AD29: 4
A30: ORD10030 | B30: 30-06-2025 | C30: CUST1340 | D30: Aarav Verma | E30: Small Business | F30: Chennai | G30: Tamil Nadu | H30: West | I30: Clothing | J30: Jeans | K30: 8 | L30: 1200 | M30: 0.2 | N30: 7680 | O30: 5451.35 | P30: 2228.65 | Q30: 29.02 | R30: Debit Card | S30: Retail Store | T30: Pooja | U30: June | V30: 2025 | W30: Monday | X30: 1 | Y30: 45664 | Z30: Pending | AA30: New | AB30: Medium | AC30: No | AD30: 3
A31: ORD10031 | B31: 45841 | C31: CUST1277 | D31: Vivaan Jain | E31: Consumer | F31: Hyderabad | G31: Telangana | H31: North | I31: Clothing | J31: Jacket | K31: 6 | L31: 2500 | M31: 0.1 | N31: 13500 | O31: 9139.27 | P31: 4360.73 | Q31: 32.3 | R31: Credit Card | S31: Online | T31: Rahul | U31: March | V31: 2025 | W31: Friday | X31: 5 | Y31: 45994 | Z31: Completed | AA31: New | AB31: Low | AC31: Yes | AD31: 2
A32: ORD10032 | B32: 17-12-2025 | C32: CUST1311 | D32: Arjun Agarwal | E32: Consumer | F32: Bengaluru | G32: Karnataka | H32: East | I32: Clothing | J32: Shirt | K32: 10 | L32: 1200 | M32: 0.15 | N32: 10200 | O32: 6072.09 | P32: 4127.91 | Q32: 40.47 | R32: Credit Card | S32: Marketplace | T32: Amit | U32: December | V32: 2025 | W32: Wednesday | X32: 5 | Y32: 22-12-2025 | Z32: Completed | AA32: Returning | AB32: High | AC32: No | AD32: 4
A33: ORD10033 | B33: 45669 | C33: CUST1290 | D33: Vivaan Jain | E33: Small Business | F33: Hyderabad | G33: Telangana | H33: West | I33: Electronics | J33: Monitor | K33: 4 | L33: 8000 | M33: 0.1 | N33: 28800 | O33: 22031.46 | P33: 6768.54 | Q33: 23.5 | R33: UPI | S33: Online | T33: Anjali | U33: December | V33: 2025 | W33: Monday | X33: 10 | Y33: 45973 | Z33: Completed | AA33: VIP | AB33: Medium | AC33: Yes | AD33: 4
A34: ORD10034 | B34: 25-12-2025 | C34: CUST1268 | D34: Ananya Bansal | E34: Small Business | F34: Jaipur | G34: Rajasthan | H34: West | I34: Electronics | J34: Headphones | K34: 6 | L34: 50000 | M34: 0.15 | N34: 255000 | O34: 152377.03 | P34: 102622.97 | Q34: 40.24 | R34: Cash | S34: Retail Store | T34: Manish | U34: December | V34: 2025 | W34: Thursday | X34: 3 | Y34: 28-12-2025 | Z34: Pending | AA34: Returning | AB34: Medium | AC34: Yes | AD34: 1
A35: ORD10035 | B35: 15-11-2025 | C35: CUST1167 | D35: Karan Malhotra | E35: Consumer | F35: Pune | G35: Maharashtra | H35: East | I35: Clothing | J35: Jeans | K35: 8 | L35: 3500 | M35: 0.2 | N35: 22400 | O35: 12493.58 | P35: 9906.42 | Q35: 44.23 | R35: UPI | S35: Retail Store | T35: Sneha | U35: November | V35: 2025 | W35: Saturday | X35: 7 | Y35: 22-11-2025 | Z35: Completed | AA35: VIP | AB35: High | AC35: No | AD35: 5
A36: ORD10036 | B36: 15-05-2025 | C36: CUST1331 | D36: Kavya Malhotra | E36: Consumer | F36: Delhi | G36: Delhi | H36: North | I36: Accessories | J36: Watch | K36: 2 | L36: 800 | M36: 0.15 | N36: 1360 | O36: 1001.59 | P36: 358.41 | Q36: 26.35 | R36: UPI | S36: Online | T36: Kavita | U36: May | V36: 2025 | W36: Thursday | X36: 9 | Y36: 24-05-2025 | Z36: Completed | AA36: VIP | AB36: Low | AC36: No | AD36: 5
A37: ORD10037 | B37: 17-07-2025 | C37: CUST1139 | D37: Priya Kumar | E37: Consumer | F37: Chennai | G37: Tamil Nadu | H37: North | I37: Clothing | J37: T-Shirt | K37: 9 | L37: 1800 | M37: 0.15 | N37: 13770 | O37: 10186.64 | P37: 3583.36 | Q37: 26.02 | R37: Debit Card | S37: Retail Store | T37: Neeraj | U37: July | V37: 2025 | W37: Thursday | X37: 6 | Y37: 23-07-2025 | Z37: Completed | AA37: VIP | AB37: High | AC37: Yes | AD37: 2
A38: ORD10038 | B38: 16-10-2024 | C38: CUST1185 | D38: Karan Kumar | E38: Consumer | F38: Hyderabad | G38: Telangana | H38: South | I38: Clothing | J38: Jacket | K38: 10 | L38: 3500 | M38: 0.2 | N38: 28000 | O38: 17639.62 | P38: 10360.38 | Q38: 37 | R38: UPI | S38: Online | T38: Amit | U38: October | V38: 2024 | W38: Wednesday | X38: 2 | Y38: 18-10-2024 | Z38: Completed | AA38: VIP | AB38: Medium | AC38: Yes | AD38: 4
A39: ORD10039 | B39: 27-03-2025 | C39: CUST1130 | D39: Kavya Verma | E39: Consumer | F39: Mumbai | G39: Maharashtra | H39: West | I39: Electronics | J39: Monitor | K39: 5 | L39: 22000 | M39: 0.15 | N39: 93500 | O39: 75798.99 | P39: 17701.01 | Q39: 18.93 | R39: Cash | S39: Online | T39: Manish | U39: March | V39: 2025 | W39: Thursday | X39: 6 | Y39: 45692 | Z39: Completed | AA39: VIP | AB39: High | AC39: Yes | AD39: 2
A40: ORD10040 | B40: 25-07-2025 | C40: CUST1317 | D40: Vikram Agarwal | E40: Small Business | F40: Bengaluru | G40: Karnataka | H40: West | I40: Accessories | J40: Wallet | K40: 2 | L40: 800 | M40: 0 | N40: 1600 | O40: 1137.53 | P40: 462.47 | Q40: 28.9 | R40: Cash | S40: Retail Store | T40: Sneha | U40: July | V40: 2025 | W40: Friday | X40: 7 | Y40: 45665 | Z40: Cancelled | AA40: VIP | AB40: Medium | AC40: No | AD40: 5
A41: ORD10041 | B41: 27-09-2024 | C41: CUST1283 | D41: Aditya Gupta | E41: Consumer | F41: Lucknow | G41: Uttar Pradesh | H41: West | I41: Electronics | J41: Monitor | K41: 2 | L41: 12000 | M41: 0.05 | N41: 22800 | O41: 14016.61 | P41: 8783.39 | Q41: 38.52 | R41: Cash | S41: Marketplace | T41: Manish | U41: September | V41: 2024 | W41: Friday | X41: 2 | Y41: 29-09-2024 | Z41: Completed | AA41: Returning | AB41: Medium | AC41: Yes | AD41: 2
A42: ORD10042 | B42: 45698 | C42: CUST1279 | D42: Vikram Mishra | E42: Consumer | F42: Pune | G42: Maharashtra | H42: East | I42: Office Supplies | J42: File Folder | K42: 2 | L42: 200 | M42: 0.1 | N42: 360 | O42: 239.32 | P42: 120.68 | Q42: 33.52 | R42: Debit Card | S42: Online | T42: Amit | U42: October | V42: 2025 | W42: Thursday | X42: 10 | Y42: 46001 | Z42: Completed | AA42: New | AB42: Medium | AC42: No | AD42: 4
A43: ORD10043 | B43: 45815 | C43: CUST1021 | D43: Ishita Yadav | E43: Corporate | F43: Mumbai | G43: Maharashtra | H43: East | I43: Clothing | J43: Jacket | K43: 7 | L43: 1800 | M43: 0.2 | N43: 10080 | O43: 5762.93 | P43: 4317.07 | Q43: 42.83 | R43: Credit Card | S43: Online | T43: Rahul | U43: July | V43: 2025 | W43: Sunday | X43: 8 | Y43: 14-07-2025 | Z43: Pending | AA43: VIP | AB43: High | AC43: Yes | AD43: 3
A44: ORD10044 | B44: 45606 | C44: CUST1252 | D44: Aditya Malhotra | E44: Corporate | F44: Lucknow | G44: Uttar Pradesh | H44: West | I44: Electronics | J44: Smartphone | K44: 8 | L44: 35000 | M44: 0.15 | N44: 238000 | O44: 158909.97 | P44: 79090.03 | Q44: 33.23 | R44: UPI | S44: Retail Store | T44: Neeraj | U44: October | V44: 2024 | W44: Friday | X44: 3 | Y44: 14-10-2024 | Z44: Cancelled | AA44: New | AB44: Medium | AC44: No | AD44: 4
A45: ORD10045 | B45: 18-11-2024 | C45: CUST1207 | D45: Meera Chopra | E45: Consumer | F45: Pune | G45: Maharashtra | H45: West | I45: Clothing | J45: T-Shirt | K45: 1 | L45: 2500 | M45: 0 | N45: 2500 | O45: 1453.25 | P45: 1046.75 | Q45: 41.87 | R45: Cash | S45: Online | T45: Rahul | U45: November | V45: 2024 | W45: Monday | X45: 5 | Y45: 23-11-2024 | Z45: Completed | AA45: VIP | AB45: Medium | AC45: No | AD45: 4
A46: ORD10046 | B46: 24-03-2025 | C46: CUST1323 | D46: Simran Agarwal | E46: Consumer | F46: Delhi | G46: Delhi | H46: South | I46: Furniture | J46: Bookshelf | K46: 9 | L46: 4000 | M46: 0.1 | N46: 32400 | O46: 18072.55 | P46: 14327.45 | Q46: 44.22 | R46: UPI | S46: Marketplace | T46: Amit | U46: March | V46: 2025 | W46: Monday | X46: 8 | Y46: 45661 | Z46: Completed | AA46: VIP | AB46: Medium | AC46: Yes | AD46: 2
A47: ORD10047 | B47: 45783 | C47: CUST1242 | D47: Vikram Malhotra | E47: Small Business | F47: Mumbai | G47: Maharashtra | H47: South | I47: Clothing | J47: Shirt | K47: 3 | L47: 2500 | M47: 0.1 | N47: 6750 | O47: 5233.78 | P47: 1516.22 | Q47: 22.46 | R47: Cash | S47: Online | T47: Manish | U47: June | V47: 2025 | W47: Thursday | X47: 5 | Y47: 45936 | Z47: Pending | AA47: VIP | AB47: High | AC47: Yes | AD47: 1
A48: ORD10048 | B48: 16-10-2024 | C48: CUST1338 | D48: Kavya Chopra | E48: Consumer | F48: Pune | G48: Maharashtra | H48: West | I48: Clothing | J48: Jacket | K48: 9 | L48: 1800 | M48: 0 | N48: 16200 | O48: 11446.58 | P48: 4753.42 | Q48: 29.34 | R48: Net Banking | S48: Retail Store | T48: Vikas | U48: October | V48: 2024 | W48: Wednesday | X48: 5 | Y48: 21-10-2024 | Z48: Cancelled | AA48: Returning | AB48: High | AC48: No | AD48: 4
A49: ORD10049 | B49: 24-02-2025 | C49: CUST1196 | D49: Pooja Mishra | E49: Small Business | F49: Chennai | G49: Tamil Nadu | H49: South | I49: Furniture | J49: Desk | K49: 10 | L49: 9000 | M49: 0.05 | N49: 85500 | O49: 64216.52 | P49: 21283.48 | Q49: 24.89 | R49: Cash | S49: Online | T49: Pooja | U49: February | V49: 2025 | W49: Monday | X49: 1 | Y49: 25-02-2025 | Z49: Completed | AA49: VIP | AB49: High | AC49: No | AD49: 1
A50: ORD10050 | B50: 23-02-2025 | C50: CUST1136 | D50: Neha Bansal | E50: Small Business | F50: Jaipur | G50: Rajasthan | H50: West | I50: Electronics | J50: Monitor | K50: 8 | L50: 8000 | M50: 0.05 | N50: 60800 | O50: 41147.16 | P50: 19652.84 | Q50: 32.32 | R50: Credit Card | S50: Retail Store | T50: Anjali | U50: February | V50: 2025 | W50: Sunday | X50: 3 | Y50: 26-02-2025 | Z50: Completed | AA50: Returning | AB50: Medium | AC50: No | AD50: 5
A51: ORD10051 | B51: 45326 | C51: CUST1052 | D51: Riya Gupta | E51: Small Business | F51: Delhi | G51: Delhi | H51: East | I51: Accessories | J51: Backpack | K51: 4 | L51: 1200 | M51: 0.05 | N51: 4560 | O51: 3444.17 | P51: 1115.83 | Q51: 24.47 | R51: Credit Card | S51: Online | T51: Vikas | U51: April | V51: 2024 | W51: Tuesday | X51: 7 | Y51: 45539 | Z51: Completed | AA51: New | AB51: Medium | AC51: No | AD51: 3
A52: ORD10052 | B52: 29-11-2025 | C52: CUST1313 | D52: Pooja Bansal | E52: Small Business | F52: Kolkata | G52: West Bengal | H52: South | I52: Furniture | J52: Desk | K52: 9 | L52: 9000 | M52: 0.2 | N52: 64800 | O52: 38703.01 | P52: 26096.99 | Q52: 40.27 | R52: Cash | S52: Marketplace | T52: Pooja | U52: November | V52: 2025 | W52: Saturday | X52: 3 | Y52: 45700 | Z52: Completed | AA52: New | AB52: Medium | AC52: No | AD52: 4
A53: ORD10053 | B53: 45571 | C53: CUST1301 | D53: Priya Mishra | E53: Corporate | F53: Pune | G53: Maharashtra | H53: East | I53: Electronics | J53: Headphones | K53: 5 | L53: 50000 | M53: 0.2 | N53: 200000 | O53: 161042.72 | P53: 38957.28 | Q53: 19.48 | R53: Cash | S53: Retail Store | T53: Rahul | U53: June | V53: 2024 | W53: Monday | X53: 2 | Y53: 45632 | Z53: Pending | AA53: Returning | AB53: Medium | AC53: Yes | AD53: 2
A54: ORD10054 | B54: 23-01-2024 | C54: CUST1026 | D54: Simran Yadav | E54: Corporate | F54: Kolkata | G54: West Bengal | H54: East | I54: Accessories | J54: Wallet | K54: 10 | L54: 1200 | M54: 0.1 | N54: 10800 | O54: 5963.61 | P54: 4836.39 | Q54: 44.78 | R54: Debit Card | S54: Marketplace | T54: Vikas | U54: January | V54: 2024 | W54: Tuesday | X54: 7 | Y54: 30-01-2024 | Z54: Completed | AA54: New | AB54: High | AC54: Yes | AD54: 5
A55: ORD10055 | B55: 45384 | C55: CUST1047 | D55: Priya Jain | E55: Small Business | F55: Pune | G55: Maharashtra | H55: West | I55: Furniture | J55: Office Chair | K55: 1 | L55: 6000 | M55: 0.15 | N55: 5100 | O55: 3813.46 | P55: 1286.54 | Q55: 25.23 | R55: Debit Card | S55: Online | T55: Pooja | U55: February | V55: 2024 | W55: Sunday | X55: 10 | Y55: 14-02-2024 | Z55: Completed | AA55: VIP | AB55: Medium | AC55: No | AD55: 2
A56: ORD10056 | B56: 18-03-2024 | C56: CUST1346 | D56: Pooja Chopra | E56: Small Business | F56: Pune | G56: Maharashtra | H56: East | I56: Clothing | J56: Jacket | K56: 6 | L56: 700 | M56: 0.15 | N56: 3570 | O56: 2792.59 | P56: 777.41 | Q56: 21.78 | R56: Credit Card | S56: Retail Store | T56: Amit | U56: March | V56: 2024 | W56: Monday | X56: 3 | Y56: 21-03-2024 | Z56: Completed | AA56: Returning | AB56: High | AC56: Yes | AD56: 4
A57: ORD10057 | B57: 22-11-2025 | C57: CUST1288 | D57: Neha Saxena | E57: Small Business | F57: Chennai | G57: Tamil Nadu | H57: South | I57: Office Supplies | J57: Stapler | K57: 7 | L57: 350 | M57: 0 | N57: 2450 | O57: 1364.05 | P57: 1085.95 | Q57: 44.32 | R57: Credit Card | S57: Marketplace | T57: Rohit | U57: November | V57: 2025 | W57: Saturday | X57: 4 | Y57: 26-11-2025 | Z57: Pending | AA57: VIP | AB57: Medium | AC57: No | AD57: 1
A58: ORD10058 | B58: 45539 | C58: CUST1233 | D58: Sneha Mishra | E58: Small Business | F58: Bengaluru | G58: Karnataka | H58: West | I58: Electronics | J58: Laptop | K58: 5 | L58: 22000 | M58: 0 | N58: 110000 | O58: 64529.22 | P58: 45470.78 | Q58: 41.34 | R58: Net Banking | S58: Marketplace | T58: Pooja | U58: April | V58: 2024 | W58: Tuesday | X58: 4 | Y58: 13-04-2024 | Z58: Cancelled | AA58: Returning | AB58: High | AC58: Yes | AD58: 4
A59: ORD10059 | B59: 30-03-2025 | C59: CUST1051 | D59: Sneha Kapoor | E59: Small Business | F59: Lucknow | G59: Uttar Pradesh | H59: East | I59: Clothing | J59: Jacket | K59: 1 | L59: 1800 | M59: 0.05 | N59: 1710 | O59: 1335.46 | P59: 374.54 | Q59: 21.9 | R59: Credit Card | S59: Retail Store | T59: Sneha | U59: March | V59: 2025 | W59: Sunday | X59: 8 | Y59: 45842 | Z59: Completed | AA59: New | AB59: Low | AC59: No | AD59: 1
A60: ORD10060 | B60: 45509 | C60: CUST1284 | D60: Rahul Bansal | E60: Consumer | F60: Hyderabad | G60: Telangana | H60: South | I60: Accessories | J60: Backpack | K60: 1 | L60: 1200 | M60: 0.05 | N60: 1140 | O60: 648.12 | P60: 491.88 | Q60: 43.15 | R60: UPI | S60: Online | T60: Manish | U60: May | V60: 2024 | W60: Wednesday | X60: 10 | Y60: 18-05-2024 | Z60: Completed | AA60: New | AB60: Medium | AC60: Yes | AD60: 2
A61: ORD10061 | B61: 16-01-2024 | C61: CUST1009 | D61: Karan Kumar | E61: Consumer | F61: Ahmedabad | G61: Gujarat | H61: South | I61: Office Supplies | J61: Printer Paper | K61: 2 | L61: 100 | M61: 0.05 | N61: 190 | O61: 134.71 | P61: 55.29 | Q61: 29.1 | R61: Cash | S61: Marketplace | T61: Neeraj | U61: January | V61: 2024 | W61: Tuesday | X61: 6 | Y61: 22-01-2024 | Z61: Completed | AA61: VIP | AB61: Low | AC61: No | AD61: 4
A62: ORD10062 | B62: 14-08-2024 | C62: CUST1338 | D62: Meera Kumar | E62: Corporate | F62: Chennai | G62: Tamil Nadu | H62: North | I62: Accessories | J62: Belt | K62: 2 | L62: 2000 | M62: 0.2 | N62: 3200 | O62: 2388.34 | P62: 811.66 | Q62: 25.36 | R62: Credit Card | S62: Retail Store | T62: Kavita | U62: August | V62: 2024 | W62: Wednesday | X62: 10 | Y62: 24-08-2024 | Z62: Completed | AA62: Returning | AB62: High | AC62: Yes | AD62: 4
A63: ORD10063 | B63: 45507 | C63: CUST1300 | D63: Aditi Yadav | E63: Corporate | F63: Jaipur | G63: Rajasthan | H63: West | I63: Electronics | J63: Laptop | K63: 6 | L63: 35000 | M63: 0.05 | N63: 199500 | O63: 143353.86 | P63: 56146.14 | Q63: 28.14 | R63: Net Banking | S63: Marketplace | T63: Sneha | U63: March | V63: 2024 | W63: Friday | X63: 3 | Y63: 45599 | Z63: Completed | AA63: Returning | AB63: High | AC63: No | AD63: 1
A64: ORD10064 | B64: 27-02-2025 | C64: CUST1049 | D64: Neha Mehta | E64: Corporate | F64: Mumbai | G64: Maharashtra | H64: East | I64: Accessories | J64: Watch | K64: 7 | L64: 2000 | M64: 0.05 | N64: 13300 | O64: 8746.84 | P64: 4553.16 | Q64: 34.23 | R64: UPI | S64: Online | T64: Rohit | U64: February | V64: 2025 | W64: Thursday | X64: 6 | Y64: 45780 | Z64: Pending | AA64: New | AB64: Low | AC64: Yes | AD64: 1
A65: ORD10065 | B65: 23-08-2025 | C65: CUST1063 | D65: Ishita Jain | E65: Small Business | F65: Kolkata | G65: West Bengal | H65: West | I65: Electronics | J65: Tablet | K65: 3 | L65: 35000 | M65: 0 | N65: 105000 | O65: 67095.46 | P65: 37904.54 | Q65: 36.1 | R65: Credit Card | S65: Retail Store | T65: Manish | U65: August | V65: 2025 | W65: Saturday | X65: 9 | Y65: 45666 | Z65: Cancelled | AA65: Returning | AB65: Medium | AC65: Yes | AD65: 5
A66: ORD10066 | B66: 24-12-2024 | C66: CUST1143 | D66: Nisha Singh | E66: Corporate | F66: Ahmedabad | G66: Gujarat | H66: North | I66: Furniture | J66: Desk | K66: 8 | L66: 4000 | M66: 0 | N66: 32000 | O66: 18592.61 | P66: 13407.39 | Q66: 41.9 | R66: Net Banking | S66: Marketplace | T66: Sneha | U66: December | V66: 2024 | W66: Tuesday | X66: 9 | Y66: 45689 | Z66: Completed | AA66: New | AB66: Low | AC66: No | AD66: 3
A67: ORD10067 | B67: 45758 | C67: CUST1325 | D67: Aarav Verma | E67: Small Business | F67: Chennai | G67: Tamil Nadu | H67: South | I67: Office Supplies | J67: Notebook | K67: 3 | L67: 200 | M67: 0.2 | N67: 480 | O67: 282.39 | P67: 197.61 | Q67: 41.17 | R67: Cash | S67: Retail Store | T67: Rohit | U67: November | V67: 2025 | W67: Tuesday | X67: 7 | Y67: 45972 | Z67: Completed | AA67: Returning | AB67: Low | AC67: No | AD67: 3
A68: ORD10068 | B68: 45571 | C68: CUST1140 | D68: Riya Mishra | E68: Corporate | F68: Chennai | G68: Tamil Nadu | H68: West | I68: Accessories | J68: Belt | K68: 2 | L68: 500 | M68: 0.05 | N68: 950 | O68: 695.37 | P68: 254.63 | Q68: 26.8 | R68: Net Banking | S68: Retail Store | T68: Kavita | U68: June | V68: 2024 | W68: Monday | X68: 10 | Y68: 20-06-2024 | Z68: Completed | AA68: Returning | AB68: Low | AC68: Yes | AD68: 3
A69: ORD10069 | B69: 14-11-2025 | C69: CUST1307 | D69: Vivaan Sharma | E69: Consumer | F69: Kolkata | G69: West Bengal | H69: East | I69: Electronics | J69: Tablet | K69: 10 | L69: 22000 | M69: 0.2 | N69: 176000 | O69: 107279.04 | P69: 68720.96 | Q69: 39.05 | R69: Debit Card | S69: Online | T69: Sneha | U69: November | V69: 2025 | W69: Friday | X69: 5 | Y69: 19-11-2025 | Z69: Completed | AA69: Returning | AB69: Medium | AC69: Yes | AD69: 1
A70: ORD10070 | B70: 21-12-2025 | C70: CUST1343 | D70: Sneha Verma | E70: Corporate | F70: Jaipur | G70: Rajasthan | H70: North | I70: Clothing | J70: Jeans | K70: 3 | L70: 2500 | M70: 0.2 | N70: 6000 | O70: 4205.13 | P70: 1794.87 | Q70: 29.91 | R70: Cash | S70: Online | T70: Rohit | U70: December | V70: 2025 | W70: Sunday | X70: 4 | Y70: 25-12-2025 | Z70: Cancelled | AA70: New | AB70: Medium | AC70: No | AD70: 5
A71: ORD10071 | B71: 28-11-2024 | C71: CUST1186 | D71: Aditya Mehta | E71: Consumer | F71: Kolkata | G71: West Bengal | H71: South | I71: Clothing | J71: Jacket | K71: 2 | L71: 2500 | M71: 0 | N71: 5000 | O71: 3371.13 | P71: 1628.87 | Q71: 32.58 | R71: Cash | S71: Marketplace | T71: Kavita | U71: November | V71: 2024 | W71: Thursday | X71: 3 | Y71: 45303 | Z71: Cancelled | AA71: VIP | AB71: Low | AC71: No | AD71: 3
A72: ORD10072 | B72: 45940 | C72: CUST1179 | D72: Sneha Yadav | E72: Small Business | F72: Chennai | G72: Tamil Nadu | H72: South | I72: Furniture | J72: Bookshelf | K72: 3 | L72: 2500 | M72: 0.2 | N72: 6000 | O72: 4126.12 | P72: 1873.88 | Q72: 31.23 | R72: Debit Card | S72: Online | T72: Pooja | U72: October | V72: 2025 | W72: Friday | X72: 2 | Y72: 46001 | Z72: Cancelled | AA72: Returning | AB72: Low | AC72: Yes | AD72: 5
A73: ORD10073 | B73: 16-08-2025 | C73: CUST1320 | D73: Neha Chopra | E73: Small Business | F73: Bengaluru | G73: Karnataka | H73: East | I73: Electronics | J73: Smartphone | K73: 8 | L73: 22000 | M73: 0.2 | N73: 140800 | O73: 101883.98 | P73: 38916.02 | Q73: 27.64 | R73: Debit Card | S73: Retail Store | T73: Neeraj | U73: August | V73: 2025 | W73: Saturday | X73: 8 | Y73: 24-08-2025 | Z73: Cancelled | AA73: Returning | AB73: Medium | AC73: No | AD73: 3
A74: ORD10074 | B74: 17-04-2025 | C74: CUST1147 | D74: Aditya Mishra | E74: Consumer | F74: Lucknow | G74: Uttar Pradesh | H74: West | I74: Electronics | J74: Tablet | K74: 9 | L74: 8000 | M74: 0.1 | N74: 64800 | O74: 36635.35 | P74: 28164.65 | Q74: 43.46 | R74: Cash | S74: Marketplace | T74: Anjali | U74: April | V74: 2025 | W74: Thursday | X74: 8 | Y74: 25-04-2025 | Z74: Completed | AA74: VIP | AB74: Low | AC74: No | AD74: 5
A75: ORD10075 | B75: 45385 | C75: CUST1176 | D75: Aditya Kapoor | E75: Small Business | F75: Hyderabad | G75: Telangana | H75: South | I75: Office Supplies | J75: Stapler | K75: 8 | L75: 800 | M75: 0.05 | N75: 6080 | O75: 4675.28 | P75: 1404.72 | Q75: 23.1 | R75: Credit Card | S75: Online | T75: Rohit | U75: March | V75: 2024 | W75: Monday | X75: 8 | Y75: 45629 | Z75: Completed | AA75: Returning | AB75: High | AC75: Yes | AD75: 3
A76: ORD10076 | B76: 23-02-2024 | C76: CUST1286 | D76: Pooja Kumar | E76: Corporate | F76: Chennai | G76: Tamil Nadu | H76: South | I76: Office Supplies | J76: File Folder | K76: 7 | L76: 350 | M76: 0.2 | N76: 1960 | O76: 1252.47 | P76: 707.53 | Q76: 36.1 | R76: UPI | S76: Online | T76: Manish | U76: February | V76: 2024 | W76: Friday | X76: 6 | Y76: 29-02-2024 | Z76: Completed | AA76: VIP | AB76: Low | AC76: No | AD76: 3
A77: ORD10077 | B77: 20-01-2025 | C77: CUST1270 | D77: Aditya Mishra | E77: Small Business | F77: Kolkata | G77: West Bengal | H77: West | I77: Furniture | J77: Table | K77: 2 | L77: 6000 | M77: 0.2 | N77: 9600 | O77: 7016.94 | P77: 2583.06 | Q77: 26.91 | R77: Net Banking | S77: Retail Store | T77: Amit | U77: January | V77: 2025 | W77: Monday | X77: 6 | Y77: 26-01-2025 | Z77: Completed | AA77: Returning | AB77: Medium | AC77: Yes | AD77: 2
A78: ORD10078 | B78: 20-03-2024 | C78: CUST1277 | D78: Meera Sharma | E78: Small Business | F78: Chennai | G78: Tamil Nadu | H78: East | I78: Clothing | J78: Jeans | K78: 4 | L78: 1200 | M78: 0.05 | N78: 4560 | O78: 3133.07 | P78: 1426.93 | Q78: 31.29 | R78: Net Banking | S78: Online | T78: Manish | U78: March | V78: 2024 | W78: Wednesday | X78: 5 | Y78: 25-03-2024 | Z78: Completed | AA78: Returning | AB78: Low | AC78: Yes | AD78: 2
A79: ORD10079 | B79: 23-11-2025 | C79: CUST1230 | D79: Vikram Kapoor | E79: Consumer | F79: Lucknow | G79: Uttar Pradesh | H79: East | I79: Furniture | J79: Sofa | K79: 1 | L79: 9000 | M79: 0.1 | N79: 8100 | O79: 5790.37 | P79: 2309.63 | Q79: 28.51 | R79: Cash | S79: Online | T79: Vikas | U79: November | V79: 2025 | W79: Sunday | X79: 4 | Y79: 27-11-2025 | Z79: Pending | AA79: VIP | AB79: High | AC79: No | AD79: 4
A80: ORD10080 | B80: 23-07-2024 | C80: CUST1027 | D80: Kavya Chopra | E80: Corporate | F80: Pune | G80: Maharashtra | H80: North | I80: Clothing | J80: T-Shirt | K80: 9 | L80: 2500 | M80: 0.05 | N80: 21375 | O80: 16794.56 | P80: 4580.44 | Q80: 21.43 | R80: Net Banking | S80: Online | T80: Sneha | U80: July | V80: 2024 | W80: Tuesday | X80: 10 | Y80: 45330 | Z80: Completed | AA80: New | AB80: Low | AC80: No | AD80: 4
A81: ORD10081 | B81: 23-12-2024 | C81: CUST1258 | D81: Sneha Singh | E81: Corporate | F81: Ahmedabad | G81: Gujarat | H81: North | I81: Furniture | J81: Sofa | K81: 2 | L81: 4000 | M81: 0.15 | N81: 6800 | O81: 3837.78 | P81: 2962.22 | Q81: 43.56 | R81: UPI | S81: Online | T81: Amit | U81: December | V81: 2024 | W81: Monday | X81: 1 | Y81: 24-12-2024 | Z81: Pending | AA81: Returning | AB81: Low | AC81: No | AD81: 2
A82: ORD10082 | B82: 23-12-2025 | C82: CUST1041 | D82: Aarav Kumar | E82: Consumer | F82: Bengaluru | G82: Karnataka | H82: South | I82: Electronics | J82: Tablet | K82: 8 | L82: 50000 | M82: 0.05 | N82: 380000 | O82: 272134.73 | P82: 107865.27 | Q82: 28.39 | R82: Net Banking | S82: Marketplace | T82: Manish | U82: December | V82: 2025 | W82: Tuesday | X82: 8 | Y82: 31-12-2025 | Z82: Pending | AA82: VIP | AB82: Medium | AC82: Yes | AD82: 3
A83: ORD10083 | B83: 16-10-2025 | C83: CUST1256 | D83: Simran Kapoor | E83: Consumer | F83: Hyderabad | G83: Telangana | H83: South | I83: Office Supplies | J83: Notebook | K83: 1 | L83: 200 | M83: 0.15 | N83: 170 | O83: 96.38 | P83: 73.62 | Q83: 43.31 | R83: Debit Card | S83: Retail Store | T83: Kavita | U83: October | V83: 2025 | W83: Thursday | X83: 10 | Y83: 26-10-2025 | Z83: Pending | AA83: New | AB83: High | AC83: No | AD83: 2
A84: ORD10084 | B84: 45568 | C84: CUST1260 | D84: Aditi Sharma | E84: Corporate | F84: Lucknow | G84: Uttar Pradesh | H84: West | I84: Clothing | J84: Jeans | K84: 2 | L84: 3500 | M84: 0.1 | N84: 6300 | O84: 4327.96 | P84: 1972.04 | Q84: 31.3 | R84: Credit Card | S84: Marketplace | T84: Kavita | U84: March | V84: 2024 | W84: Sunday | X84: 9 | Y84: 19-03-2024 | Z84: Cancelled | AA84: Returning | AB84: Medium | AC84: Yes | AD84: 3
A85: ORD10085 | B85: 16-05-2024 | C85: CUST1330 | D85: Karan Chopra | E85: Small Business | F85: Mumbai | G85: Maharashtra | H85: West | I85: Office Supplies | J85: Printer Paper | K85: 2 | L85: 800 | M85: 0.1 | N85: 1440 | O85: 1004.29 | P85: 435.71 | Q85: 30.26 | R85: Cash | S85: Marketplace | T85: Pooja | U85: May | V85: 2024 | W85: Thursday | X85: 1 | Y85: 17-05-2024 | Z85: Completed | AA85: New | AB85: Low | AC85: No | AD85: 1
A86: ORD10086 | B86: 13-11-2024 | C86: CUST1279 | D86: Kavya Kumar | E86: Consumer | F86: Pune | G86: Maharashtra | H86: South | I86: Furniture | J86: Office Chair | K86: 4 | L86: 2500 | M86: 0.1 | N86: 9000 | O86: 7353.57 | P86: 1646.43 | Q86: 18.29 | R86: UPI | S86: Retail Store | T86: Amit | U86: November | V86: 2024 | W86: Wednesday | X86: 9 | Y86: 22-11-2024 | Z86: Pending | AA86: VIP | AB86: Medium | AC86: No | AD86: 1
A87: ORD10087 | B87: 45572 | C87: CUST1266 | D87: Ananya Agarwal | E87: Consumer | F87: Chennai | G87: Tamil Nadu | H87: West | I87: Clothing | J87: Shoes | K87: 8 | L87: 2500 | M87: 0.1 | N87: 18000 | O87: 11685.31 | P87: 6314.69 | Q87: 35.08 | R87: Credit Card | S87: Retail Store | T87: Manish | U87: July | V87: 2024 | W87: Wednesday | X87: 8 | Y87: 18-07-2024 | Z87: Pending | AA87: New | AB87: High | AC87: No | AD87: 3
A88: ORD10088 | B88: 45909 | C88: CUST1180 | D88: Riya Sharma | E88: Small Business | F88: Mumbai | G88: Maharashtra | H88: East | I88: Electronics | J88: Tablet | K88: 5 | L88: 15000 | M88: 0.15 | N88: 63750 | O88: 46935.08 | P88: 16814.92 | Q88: 26.38 | R88: Net Banking | S88: Retail Store | T88: Sneha | U88: September | V88: 2025 | W88: Tuesday | X88: 7 | Y88: 16-09-2025 | Z88: Completed | AA88: VIP | AB88: Low | AC88: Yes | AD88: 4
A89: ORD10089 | B89: 25-11-2025 | C89: CUST1121 | D89: Sneha Jain | E89: Corporate | F89: Chennai | G89: Tamil Nadu | H89: North | I89: Accessories | J89: Watch | K89: 1 | L89: 800 | M89: 0.2 | N89: 640 | O89: 373.81 | P89: 266.19 | Q89: 41.59 | R89: Net Banking | S89: Online | T89: Rohit | U89: November | V89: 2025 | W89: Tuesday | X89: 8 | Y89: 45728 | Z89: Completed | AA89: Returning | AB89: Medium | AC89: No | AD89: 1
A90: ORD10090 | B90: 27-10-2025 | C90: CUST1014 | D90: Karan Malhotra | E90: Small Business | F90: Lucknow | G90: Uttar Pradesh | H90: West | I90: Furniture | J90: Table | K90: 6 | L90: 9000 | M90: 0.1 | N90: 48600 | O90: 39333.94 | P90: 9266.06 | Q90: 19.07 | R90: Net Banking | S90: Online | T90: Sneha | U90: October | V90: 2025 | W90: Monday | X90: 5 | Y90: 45668 | Z90: Completed | AA90: Returning | AB90: High | AC90: No | AD90: 2
A91: ORD10091 | B91: 16-03-2024 | C91: CUST1228 | D91: Aditya Agarwal | E91: Small Business | F91: Lucknow | G91: Uttar Pradesh | H91: East | I91: Office Supplies | J91: File Folder | K91: 4 | L91: 100 | M91: 0.05 | N91: 380 | O91: 301.2 | P91: 78.8 | Q91: 20.74 | R91: UPI | S91: Marketplace | T91: Neeraj | U91: March | V91: 2024 | W91: Saturday | X91: 8 | Y91: 24-03-2024 | Z91: Completed | AA91: VIP | AB91: High | AC91: No | AD91: 3
A92: ORD10092 | B92: 24-07-2024 | C92: CUST1014 | D92: Sneha Kapoor | E92: Small Business | F92: Bengaluru | G92: Karnataka | H92: East | I92: Furniture | J92: Bookshelf | K92: 9 | L92: 4000 | M92: 0 | N92: 36000 | O92: 27482.43 | P92: 8517.57 | Q92: 23.66 | R92: Cash | S92: Marketplace | T92: Pooja | U92: July | V92: 2024 | W92: Wednesday | X92: 3 | Y92: 27-07-2024 | Z92: Completed | AA92: VIP | AB92: Low | AC92: Yes | AD92: 3
A93: ORD10093 | B93: 16-03-2024 | C93: CUST1231 | D93: Riya Mishra | E93: Small Business | F93: Kolkata | G93: West Bengal | H93: East | I93: Clothing | J93: T-Shirt | K93: 7 | L93: 2500 | M93: 0.2 | N93: 14000 | O93: 10128.04 | P93: 3871.96 | Q93: 27.66 | R93: Debit Card | S93: Marketplace | T93: Manish | U93: March | V93: 2024 | W93: Saturday | X93: 3 | Y93: 19-03-2024 | Z93: Completed | AA93: New | AB93: Low | AC93: No | AD93: 5
A94: ORD10094 | B94: 14-06-2024 | C94: CUST1266 | D94: Priya Chopra | E94: Consumer | F94: Delhi | G94: Delhi | H94: East | I94: Electronics | J94: Monitor | K94: 3 | L94: 15000 | M94: 0.05 | N94: 42750 | O94: 27506.47 | P94: 15243.53 | Q94: 35.66 | R94: Debit Card | S94: Marketplace | T94: Anjali | U94: June | V94: 2024 | W94: Friday | X94: 6 | Y94: 20-06-2024 | Z94: Completed | AA94: Returning | AB94: Low | AC94: No | AD94: 5
A95: ORD10095 | B95: 45449 | C95: CUST1310 | D95: Neha Chopra | E95: Small Business | F95: Ahmedabad | G95: Gujarat | H95: North | I95: Electronics | J95: Monitor | K95: 3 | L95: 35000 | M95: 0.2 | N95: 84000 | O95: 62543.95 | P95: 21456.05 | Q95: 25.54 | R95: Credit Card | S95: Online | T95: Amit | U95: June | V95: 2024 | W95: Thursday | X95: 3 | Y95: 45541 | Z95: Cancelled | AA95: VIP | AB95: High | AC95: No | AD95: 2
A96: ORD10096 | B96: 23-10-2024 | C96: CUST1208 | D96: Priya Malhotra | E96: Consumer | F96: Lucknow | G96: Uttar Pradesh | H96: North | I96: Clothing | J96: T-Shirt | K96: 1 | L96: 2500 | M96: 0.2 | N96: 2000 | O96: 1232.23 | P96: 767.77 | Q96: 38.39 | R96: Debit Card | S96: Retail Store | T96: Kavita | U96: October | V96: 2024 | W96: Wednesday | X96: 5 | Y96: 28-10-2024 | Z96: Pending | AA96: Returning | AB96: Medium | AC96: Yes | AD96: 3
A97: ORD10097 | B97: 13-05-2024 | C97: CUST1164 | D97: Vikram Malhotra | E97: Consumer | F97: Lucknow | G97: Uttar Pradesh | H97: East | I97: Furniture | J97: Bookshelf | K97: 6 | L97: 6000 | M97: 0.15 | N97: 30600 | O97: 21470.36 | P97: 9129.64 | Q97: 29.84 | R97: Cash | S97: Online | T97: Pooja | U97: May | V97: 2024 | W97: Monday | X97: 6 | Y97: 19-05-2024 | Z97: Cancelled | AA97: New | AB97: Low | AC97: No | AD97: 4
A98: ORD10098 | B98: 16-11-2024 | C98: CUST1264 | D98: Riya Malhotra | E98: Corporate | F98: Lucknow | G98: Uttar Pradesh | H98: West | I98: Clothing | J98: Jeans | K98: 3 | L98: 1800 | M98: 0.2 | N98: 4320 | O98: 2957.18 | P98: 1362.82 | Q98: 31.55 | R98: Credit Card | S98: Online | T98: Kavita | U98: November | V98: 2024 | W98: Saturday | X98: 4 | Y98: 20-11-2024 | Z98: Completed | AA98: VIP | AB98: Medium | AC98: Yes | AD98: 2
A99: ORD10099 | B99: 45725 | C99: CUST1056 | D99: Ishita Gupta | E99: Corporate | F99: Lucknow | G99: Uttar Pradesh | H99: East | I99: Office Supplies | J99: Notebook | K99: 1 | L99: 350 | M99: 0.15 | N99: 297.5 | O99: 206.73 | P99: 90.77 | Q99: 30.51 | R99: Cash | S99: Retail Store | T99: Amit | U99: September | V99: 2025 | W99: Wednesday | X99: 8 | Y99: 45970 | Z99: Completed | AA99: Returning | AB99: Low | AC99: Yes | AD99: 3
A100: ORD10100 | B100: 17-07-2025 | C100: CUST1061 | D100: Rohan Verma | E100: Corporate | F100: Ahmedabad | G100: Gujarat | H100: East | I100: Office Supplies | J100: Notebook | K100: 7 | L100: 800 | M100: 0.15 | N100: 4760 | O100: 3492.45 | P100: 1267.55 | Q100: 26.63 | R100: UPI | S100: Marketplace | T100: Vikas | U100: July | V100: 2025 | W100: Thursday | X100: 5 | Y100: 22-07-2025 | Z100: Cancelled | AA100: New | AB100: Low | AC100: No | AD100: 5
...

Sheet Sheet2
A3: Region | B3: Sum of Sales
A4: East | B4: 7518642.5
A5: North | B5: 5965332.5
A6: South | B6: 8560317.5
A7: West | B7: 8266957.5
A8: Grand Total | B8: 30311250

Sheet Sheet3
A3: Category | B3: Sum of Sales
A4: Accessories | B4: 1466745
A5: Clothing | B5: 1886370
A6: Electronics | B6: 19767000
A7: Furniture | B7: 6779800
A8: Office Supplies | B8: 411335
A9: Grand Total | B9: 30311250

Sheet Sheet4
A3: Product | B3: Sum of Sales
A4: Backpack | B4: 381040
A5: Belt | B5: 331880
A6: Bookshelf | B6: 1141650
A7: Desk | B7: 1791875
A8: File Folder | B8: 64612.5
A9: Headphones | B9: 2740850
A10: Jacket | B10: 420105
A11: Jeans | B11: 319065
A12: Laptop | B12: 3513350
A13: Monitor | B13: 4066900
A14: Notebook | B14: 84285
A15: Office Chair | B15: 1289950
... A29: Grand Total | B29: 30311250

Sheet Sheet6
A3: Month | B3: Sum of Sales
A4: January | B4: 1889497.5
A5: February | B5: 2361560
A6: March | B6: 2618520
A7: April | B7: 1803637.5
A8: May | B8: 1121067.5
A9: June | B9: 2765790
A10: July | B10: 3495020
A11: August | B11: 2480745
A12: September | B12: 3190750
A13: October | B13: 3112707.5
A14: November | B14: 2076795
A15: December | B15: 3395160
A16: Grand Total | B16: 30311250

Sheet Sheet7
A3: Salesperson | B3: Sum of Sales
A4: Amit | B4: 3295187.5
A5: Anjali | B5: 2952162.5
A6: Kavita | B6: 3337090
A7: Manish | B7: 3934230
A8: Neeraj | B8: 2937487.5
A9: Pooja | B9: 2963150
A10: Rahul | B10: 2934365
A11: Rohit | B11: 3031592.5
A12: Sneha | B12: 2992322.5
A13: Vikas | B13: 1933662.5
A14: Grand Total | B14: 30311250

Sheet Sheet8
A3: Customer_Segment | B3: Sum of Sales
A4: Consumer | B4: 10446645
A5: Corporate | B5: 10315895
A6: Small Business | B6: 9548710
A7: Grand Total | B7: 30311250

Sheet Sheet9
A3: Payment_Method | B3: Sum of Sales
A4: Cash | B4: 7422207.5
A5: Credit Card | B5: 5132640
A6: Debit Card | B6: 5321137.5
A7: Net Banking | B7: 7103552.5
A8: UPI | B8: 5331712.5
A9: Grand Total | B9: 30311250

Sheet Sheet10
A3: Order_Status | B3: Sum of Sales
A4: Cancelled | B4: 5967697.5
A5: Completed | B5: 17792045
A6: Pending | B6: 6551507.5
A7: Grand Total | B7: 30311250

Sheet Sheet5
A3: Category | B3: Sum of Profit2 | C3: Sum of Profit
A4: Electronics | B4: 1065908.1 | C4: 1065908.1
A5: Furniture | B5: 481396.74 | C5: 481396.74
A6: Clothing | B6: 153730.63 | C6: 153730.63
A7: Accessories | B7: 104830.38 | C7: 104830.38
A8: Office Supplies | B8: 38664.94 | C8: 38664.94
A9: Grand Total | B9: 1844530.8 | C9: 1844530.8

Sheet Detail1
A1: Details for Sum of Profit - Category: Clothing
A3: Order_ID | B3: Order_Date | C3: Customer_ID | D3: Customer_Name | E3: Customer_Segment | F3: City | G3: State | H3: Region | I3: Category | J3: Product | K3: Quantity | L3: Unit_Price | M3: Discount | N3: Sales | O3: Cost | P3: Profit | Q3: Profit_Margin_% | R3: Payment_Method | S3: Sales_Channel | T3: Salesperson | U3: Month | V3: Year | W3: Day_Name | X3: Delivery_Days | Y3: Delivery_Date | Z3: Order_Status | AA3: Customer_Type | AB3: Priority | AC3: Return_Requested | AD3: Rating | AE3: First_name | AF3: Last_Name | AG3: SUM | AH3: Average | AI3: Count | AJ3: Counta | AK3: MIN | AL3: Max | AM3: IF | AN3: IFS | AO3: AND | AP3: OR | AQ3: IFERROR | AR3: SUMIFS | AS3: COUNTIFS | AT3: AVERAGEIFS | AU3: Region-wise Sales | AV3: Category-wise Sales | AW3: Total Sales | AX3: Salesperson-wise Sales | AY3: Monthly Sales | AZ3: Year-wise Sales | BA3: Profit Analysis | BB3: Profit Margin Analysis | BC3: Discount Analysis | BD3: Region_Total_Sales | BE3: Product_wise Sales | BF3: Total Sales2
A4: ORD10524 | B4: 30-12-2024 | C4: CUST1258 | D4: Arjun Kapoor | E4: Consumer | F4: Pune | G4: Maharashtra | H4: North | I4: Clothing | J4: T-Shirt | K4: 4 | L4: 1800 | M4: 0.15 | N4: 6120 | O4: 3913.47 | P4: 2206.53 | Q4: 36.05 | R4: Net Banking | S4: Retail Store | T4: Rohit | U4: December | V4: 2024 | W4: Monday | X4: 3 | Y4: 45689 | Z4: Completed | AA4: VIP | AB4: Low | AC4: No | AD4: 2 | AE4: Arjun | AF4: Kapoor | AM4: Good | AN4: Low | AO4: No | AP4: No | AQ4: 0.36054412
A5: ORD10480 | B5: 27-10-2025 | C5: CUST1077 | D5: Pooja Singh | E5: Consumer | F5: Chennai | G5: Tamil Nadu | H5: North | I5: Clothing | J5: Jeans | K5: 1 | L5: 700 | M5: 0.2 | N5: 560 | O5: 373.59 | P5: 186.41 | Q5: 33.29 | R5: Debit Card | S5: Retail Store | T5: Rohit | U5: October | V5: 2025 | W5: Monday | X5: 6 | Y5: 45699 | Z5: Cancelled | AA5: Returning | AB5: High | AC5: Yes | AD5: 4 | AE5: Pooja | AF5: Singh | AM5: Good | AN5: Low | AO5: No | AP5: No | AQ5: 0.332875
A6: ORD10477 | B6: 45294 | C6: CUST1108 | D6: Vikram Yadav | E6: Small Business | F6: Lucknow | G6: Uttar Pradesh | H6: North | I6: Clothing | J6: Jeans | K6: 8 | L6: 1800 | M6: 0.15 | N6: 12240 | O6: 9467.99 | P6: 2772.01 | Q6: 22.65 | R6: Debit Card | S6: Retail Store | T6: Kavita | U6: March | V6: 2024 | W6: Friday | X6: 6 | Y6: 45476 | Z6: Completed | AA6: Returning | AB6: High | AC6: Yes | AD6: 1 | AE6: Vikram | AF6: Yadav | AM6: Needs Improvement | AN6: Medium | AO6: No | AP6: No | AQ6: 0.22647141 | AS6: 196 | AT6: 2098.648 | AU6: East | AV6: Office Supplies | AW6: 411335 | BD6: 7518642.5
A7: ORD10619 | B7: 26-08-2024 | C7: CUST1160 | D7: Neha Chopra | E7: Consumer | F7: Bengaluru | G7: Karnataka | H7: North | I7: Clothing | J7: T-Shirt | K7: 8 | L7: 3500 | M7: 0.2 | N7: 22400 | O7: 13844.24 | P7: 8555.76 | Q7: 38.2 | R7: UPI | S7: Marketplace | T7: Manish | U7: August | V7: 2024 | W7: Monday | X7: 1 | Y7: 27-08-2024 | Z7: Pending | AA7: VIP | AB7: Medium | AC7: Yes | AD7: 3 | AE7: Neha | AF7: Chopra | AM7: Good | AN7: Medium | AO7: No | AP7: Yes | AQ7: 0.38195357
A8: ORD10096 | B8: 23-10-2024 | C8: CUST1208 | D8: Priya Malhotra | E8: Consumer | F8: Lucknow | G8: Uttar Pradesh | H8: North | I8: Clothing | J8: T-Shirt | K8: 1 | L8: 2500 | M8: 0.2 | N8: 2000 | O8: 1232.23 | P8: 767.77 | Q8: 38.39 | R8: Debit Card | S8: Retail Store | T8: Kavita | U8: October | V8: 2024 | W8: Wednesday | X8: 5 | Y8: 28-10-2024 | Z8: Pending | AA8: Returning | AB8: Medium | AC8: Yes | AD8: 3 | AE8: Priya | AF8: Malhotra | AM8: Good | AN8: Low | AO8: No | AP8: No | AQ8: 0.383885
A9: ORD10080 | B9: 23-07-2024 | C9: CUST1027 | D9: Kavya Chopra | E9: Corporate | F9: Pune | G9: Maharashtra | H9: North | I9: Clothing | J9: T-Shirt | K9: 9 | L9: 2500 | M9: 0.05 | N9: 21375 | O9: 16794.56 | P9: 4580.44 | Q9: 21.43 | R9: Net Banking | S9: Online | T9: Sneha | U9: July | V9: 2024 | W9: Tuesday | X9: 10 | Y9: 45330 | Z9: Completed | AA9: New | AB9: Low | AC9: No | AD9: 4 | AE9: Kavya | AF9: Chopra | AM9: Needs Improvement | AN9: Medium | AO9: No | AP9: Yes | AQ9: 0.21428959
A10: ORD10515 | B10: 45297 | C10: CUST1229 | D10: Kavya Chopra | E10: Consumer | F10: Pune | G10: Maharashtra | H10: North | I10: Clothing | J10: Jacket | K10: 5 | L10: 700 | M10: 0 | N10: 3500 | O10: 2064.65 | P10: 1435.35 | Q10: 41.01 | R10: Net Banking | S10: Retail Store | T10: Sneha | U10: June | V10: 2024 | W10: Saturday | X10: 3 | Y10: 45388 | Z10: Completed | AA10: New | AB10: Low | AC10: No | AD10: 2 | AE10: Kavya | AF10: Chopra | AM10: Good | AN10: Low | AO10: No | AP10: No | AQ10: 0.4101
A11: ORD10955 | B11: 22-08-2024 | C11: CUST1346 | D11: Ishita Gupta | E11: Consumer | F11: Mumbai | G11: Maharashtra | H11: North | I11: Clothing | J11: Jacket | K11: 10 | L11: 3500 | M11: 0.1 | N11: 31500 | O11: 23234.21 | P11: 8265.79 | Q11: 26.24 | R11: Debit Card | S11: Online | T11: Sneha | U11: August | V11: 2024 | W11: Thursday | X11: 1 | Y11: 23-08-2024 | Z11: Completed | AA11: New | AB11: Medium | AC11: No | AD11: 4 | AE11: Ishita | AF11: Gupta | AM11: Needs Improvement | AN11: High | AO11: No | AP11: Yes | AQ11: 0.26240603
A12: ORD10593 | B12: 22-04-2025 | C12: CUST1285 | D12: Rahul Mehta | E12: Consumer | F12: Bengaluru | G12: Karnataka | H12: North | I12: Clothing | J12: Shoes | K12: 1 | L12: 2500 | M12: 0 | N12: 2500 | O12: 1699.14 | P12: 800.86 | Q12: 32.03 | R12: UPI | S12: Marketplace | T12: Anjali | U12: April | V12: 2025 | W12: Tuesday | X12: 1 | Y12: 23-04-2025 | Z12: Completed | AA12: Returning | AB12: Low | AC12: No | AD12: 2 | AE12: Rahul | AF12: Mehta | AM12: Good | AN12: Low | AO12: No | AP12: Yes | AQ12: 0.320344
A13: ORD10070 | B13: 21-12-2025 | C13: CUST1343 | D13: Sneha Verma | E13: Corporate | F13: Jaipur | G13: Rajasthan | H13: North | I13: Clothing | J13: Jeans | K13: 3 | L13: 2500 | M13: 0.2 | N13: 6000 | O13: 4205.13 | P13: 1794.87 | Q13: 29.91 | R13: Cash | S13: Online | T13: Rohit | U13: December | V13: 2025 | W13: Sunday | X13: 4 | Y13: 25-12-2025 | Z13: Cancelled | AA13: New | AB13: Medium | AC13: No | AD13: 5 | AE13: Sneha | AF13: Verma | AM13: Needs Improvement | AN13: Low | AO13: No | AP13: Yes | AQ13: 0.299145
A14: ORD10511 | B14: 21-10-2025 | C14: CUST1043 | D14: Ananya Gupta | E14: Small Business | F14: Mumbai | G14: Maharashtra | H14: North | I14: Clothing | J14: Shoes | K14: 1 | L14: 700 | M14: 0 | N14: 700 | O14: 431.94 | P14: 268.06 | Q14: 38.29 | R14: Credit Card | S14: Online | T14: Anjali | U14: October | V14: 2025 | W14: Tuesday | X14: 1 | Y14: 22-10-2025 | Z14: Completed | AA14: VIP | AB14: Medium | AC14: Yes | AD14: 2 | AE14: Ananya | AF14: Gupta | AM14: Good | AN14: Low | AO14: No | AP14: Yes | AQ14: 0.38294286
A15: ORD10972 | B15: 20-09-2025 | C15: CUST1241 | D15: Vivaan Kapoor | E15: Small Business | F15: Delhi | G15: Delhi | H15: North | I15: Clothing | J15: T-Shirt | K15: 6 | L15: 700 | M15: 0.15 | N15: 3570 | O15: 2708.04 | P15: 861.96 | Q15: 24.14 | R15: UPI | S15: Marketplace | T15: Rahul | U15: September | V15: 2025 | W15: Saturday | X15: 10 | Y15: 30-09-2025 | Z15: Completed | AA15: Returning | AB15: Medium | AC15: Yes | AD15: 3 | AE15: Vivaan | AF15: Kapoor | AM15: Needs Improvement | AN15: Low | AO15: No | AP15: Yes | AQ15: 0.24144538
A16: ORD10617 | B16: 20-02-2025 | C16: CUST1274 | D16: Meera Singh | E16: Corporate | F16: Jaipur | G16: Rajasthan | H16: North | I16: Clothing | J16: Jacket | K16: 7 | L16: 700 | M16: 0.05 | N16: 4655 | O16: 3167.75 | P16: 1487.25 | Q16: 31.95 | R16: Cash | S16: Marketplace | T16: Kavita | U16: February | V16: 2025 | W16: Thursday | X16: 9 | Y16: 45660 | Z16: Completed | AA16: Returning | AB16: High | AC16: Yes | AD16: 4 | AE16: Meera | AF16: Singh | AM16: Good | AN16: Low | AO16: No | AP16: Yes | AQ16: 0.31949517
A17: ORD10374 | B17: 19-04-2024 | C17: CUST1226 | D17: Ishita Kumar | E17: Small Business | F17: Lucknow | G17: Uttar Pradesh | H17: North | I17: Clothing | J17: Jeans | K17: 7 | L17: 1200 | M17: 0.05 | N17: 7980 | O17: 6478.8 | P17: 1501.2 | Q17: 18.81 | R17: Cash | S17: Marketplace | T17: Vikas | U17: April | V17: 2024 | W17: Friday | X17: 3 | Y17: 22-04-2024 | Z17: Completed | AA17: VIP | AB17: Low | AC17: No | AD17: 5 | AE17: Ishita | AF17: Kumar | AM17: Needs Improvement | AN17: Low | AO17: No | AP17: Yes | AQ17: 0.1881203
A18: ORD10766 | B18: 18-03-2025 | C18: CUST1007 | D18: Nisha Saxena | E18: Consumer | F18: Mumbai | G18: Maharashtra | H18: North | I18: Clothing | J18: Shoes | K18: 1 | L18: 700 | M18: 0.15 | N18: 595 | O18: 355.37 | P18: 239.63 | Q18: 40.27 | R18: UPI | S18: Marketplace | T18: Sneha | U18: March | V18: 2025 | W18: Tuesday | X18: 8 | Y18: 26-03-2025 | Z18: Pending | AA18: VIP | AB18: Medium | AC18: Yes | AD18: 3 | AE18: Nisha | AF18: Saxena | AM18: Good | AN18: Low | AO18: No | AP18: Yes | AQ18: 0.4027395
A19: ORD10037 | B19: 17-07-2025 | C19: CUST1139 | D19: Priya Kumar | E19: Consumer | F19: Chennai | G19: Tamil Nadu | H19: North | I19: Clothing | J19: T-Shirt | K19: 9 | L19: 1800 | M19: 0.15 | N19: 13770 | O19: 10186.64 | P19: 3583.36 | Q19: 26.02 | R19: Debit Card | S19: Retail Store | T19: Neeraj | U19: July | V19: 2025 | W19: Thursday | X19: 6 | Y19: 23-07-2025 | Z19: Completed | AA19: VIP | AB19: High | AC19: Yes | AD19: 2 | AE19: Priya | AF19: Kumar | AM19: Needs Improvement | AN19: Medium | AO19: No | AP19: No | AQ19: 0.26022948
A20: ORD10293 | B20: 16-09-2025 | C20: CUST1001 | D20: Arjun Sharma | E20: Corporate | F20: Lucknow | G20: Uttar Pradesh | H20: North | I20: Clothing | J20: T-Shirt | K20: 8 | L20: 2500 | M20: 0.05 | N20: 19000 | O20: 15473.59 | P20: 3526.41 | Q20: 18.56 | R20: Debit Card | S20: Marketplace | T20: Kavita | U20: September | V20: 2025 | W20: Tuesday | X20: 4 | Y20: 20-09-2025 | Z20: Completed | AA20: Returning | AB20: Low | AC20: No | AD20: 3 | AE20: Arjun | AF20: Sharma | AM20: Needs Improvement | AN20: Medium | AO20: No | AP20: Yes | AQ20: 0.18560053
A21: ORD10980 | B21: 15-03-2024 | C21: CUST1192 | D21: Aarav Malhotra | E21: Consumer | F21: Pune | G21: Maharashtra | H21: North | I21: Clothing | J21: Jeans | K21: 2 | L21: 1200 | M21: 0.15 | N21: 2040 | O21: 1631.05 | P21: 408.95 | Q21: 20.05 | R21: UPI | S21: Marketplace | T21: Amit | U21: March | V21: 2024 | W21: Friday | X21: 7 | Y21: 22-03-2024 | Z21: Cancelled | AA21: New | AB21: Low | AC21: No | AD21: 1 | AE21: Aarav | AF21: Malhotra | AM21: Needs Improvement | AN21: Low | AO21: No | AP21: Yes | AQ21: 0.20046569
A22: ORD10273 | B22: 45326 | C22: CUST1202 | D22: Rohan Gupta | E22: Corporate | F22: Delhi | G22: Delhi | H22: North | I22: Clothing | J22: Shoes | K22: 10 | L22: 3500 | M22: 0.2 | N22: 28000 | O22: 17590.76 | P22: 10409.24 | Q22: 37.18 | R22: Cash | S22: Marketplace | T22: Amit | U22: April | V22: 2024 | W22: Tuesday | X22: 4 | Y22: 45447 | Z22: Pending | AA22: VIP | AB22: Medium | AC22: No | AD22: 1 | AE22: Rohan | AF22: Gupta | AM22: Good | AN22: Medium | AO22: No | AP22: Yes | AQ22: 0.37175857
A23: ORD10452 | B23: 13-09-2025 | C23: CUST1274 | D23: Pooja Gupta | E23: Consumer | F23: Bengaluru | G23: Karnataka | H23: North | I23: Clothing | J23: Jacket | K23: 3 | L23: 1200 | M23: 0 | N23: 3600 | O23: 2265.91 | P23: 1334.09 | Q23: 37.06 | R23: UPI | S23: Online | T23: Rohit | U23: September | V23: 2025 | W23: Saturday | X23: 2 | Y23: 15-09-2025 | Z23: Completed | AA23: Returning | AB23: Low | AC23: Yes | AD23: 1 | AE23: Pooja | AF23: Gupta | AM23: Good | AN23: Low | AO23: No | AP23: Yes | AQ23: 0.37058056
A24: ORD10658 | B24: 13-04-2025 | C24: CUST1103 | D24: Neha Gupta | E24: Corporate | F24: Lucknow | G24: Uttar Pradesh | H24: North | I24: Clothing | J24: T-Shirt | K24: 9 | L24: 1200 | M24: 0.05 | N24: 10260 | O24: 6128.37 | P24: 4131.63 | Q24: 40.27 | R24: Credit Card | S24: Online | T24: Manish | U24: April | V24: 2025 | W24: Sunday | X24: 6 | Y24: 19-04-2025 | Z24: Completed | AA24: Returning | AB24: Medium | AC24: Yes | AD24: 5 | AE24: Neha | AF24: Gupta | AM24: Good | AN24: Medium | AO24: No | AP24: Yes | AQ24: 0.40269298
A25: ORD10178 | B25: 13-03-2025 | C25: CUST1321 | D25: Simran Malhotra | E25: Consumer | F25: Ahmedabad | G25: Gujarat | H25: North | I25: Clothing | J25: Jeans | K25: 1 | L25: 1800 | M25: 0 | N25: 1800 | O25: 1390.41 | P25: 409.59 | Q25: 22.75 | R25: Credit Card | S25: Online | T25: Pooja | U25: March | V25: 2025 | W25: Thursday | X25: 2 | Y25: 15-03-2025 | Z25: Completed | AA25: VIP | AB25: Medium | AC25: Yes | AD25: 4 | AE25: Simran | AF25: Malhotra | AM25: Needs Improvement | AN25: Low | AO25: No | AP25: Yes | AQ25: 0.22755
A26: ORD10556 | B26: 13-02-2025 | C26: CUST1085 | D26: Priya Chopra | E26: Small Business | F26: Chennai | G26: Tamil Nadu | H26: North | I26: Clothing | J26: Shoes | K26: 10 | L26: 3500 | M26: 0.05 | N26: 33250 | O26: 20781.79 | P26: 12468.21 | Q26: 37.5 | R26: Debit Card | S26: Retail Store | T26: Neeraj | U26: February | V26: 2025 | W26: Thursday | X26: 4 | Y26: 17-02-2025 | Z26: Completed | AA26: VIP | AB26: Low | AC26: Yes | AD26: 1 | AE26: Priya | AF26: Chopra | AM26: Good | AN26: High | AO26: Yes | AP26: No | AQ26: 0.37498376
A27: ORD10316 | B27: 13-01-2024 | C27: CUST1162 | D27: Meera Mishra | E27: Consumer | F27: Kolkata | G27: West Bengal | H27: North | I27: Clothing | J27: Jacket | K27: 3 | L27: 3500 | M27: 0.15 | N27: 8925 | O27: 5829.28 | P27: 3095.72 | Q27: 34.69 | R27: Net Banking | S27: Marketplace | T27: Vikas | U27: January | V27: 2024 | W27: Saturday | X27: 5 | Y27: 18-01-2024 | Z27: Pending | AA27: Returning | AB27: High | AC27: No | AD27: 3 | AE27: Meera | AF27: Mishra | AM27: Good | AN27: Low | AO27: No | AP27: Yes | AQ27: 0.34685938
A28: ORD10919 | B28: 46000 | C28: CUST1207 | D28: Arjun Gupta | E28: Consumer | F28: Jaipur | G28: Rajasthan | H28: North | I28: Clothing | J28: Shoes | K28: 3 | L28: 700 | M28: 0 | N28: 2100 | O28: 1218.91 | P28: 881.09 | Q28: 41.96 | R28: Credit Card | S28: Marketplace | T28: Amit | U28: September | V28: 2025 | W28: Friday | X28: 2 | Y28: 14-09-2025 | Z28: Completed | AA28: Returning | AB28: Low | AC28: No | AD28: 5 | AE28: Arjun | AF28: Gupta | AM28: Good | AN28: Low | AO28: No | AP28: Yes | AQ28: 0.41956667
A29: ORD10223 | B29: 45973 | C29: CUST1187 | D29: Neha Mehta | E29: Consumer | F29: Chennai | G29: Tamil Nadu | H29: North | I29: Clothing | J29: Shoes | K29: 6 | L29: 3500 | M29: 0.1 | N29: 18900 | O29: 13281.01 | P29: 5618.99 | Q29: 29.73 | R29: UPI | S29: Online | T29: Rahul | U29: December | V29: 2025 | W29: Thursday | X29: 10 | Y29: 21-12-2025 | Z29: Completed | AA29: VIP | AB29: High | AC29: No | AD29: 3 | AE29: Neha | AF29: Mehta | AM29: Needs Improvement | AN29: Medium | AO29: No | AP29: Yes | AQ29: 0.29730106
A30: ORD10242 | B30: 45940 | C30: CUST1212 | D30: Sneha Kapoor | E30: Small Business | F30: Delhi | G30: Delhi | H30: North | I30: Clothing | J30: Shirt | K30: 5 | L30: 700 | M30: 0.15 | N30: 2975 | O30: 2278.98 | P30: 696.02 | Q30: 23.4 | R30: UPI | S30: Online | T30: Sneha | U30: October | V30: 2025 | W30: Friday | X30: 4 | Y30: 14-10-2025 | Z30: Completed | AA30: New | AB30: Medium | AC30: No | AD30: 1 | AE30: Sneha | AF30: Kapoor | AM30: Needs Improvement | AN30: Low | AO30: No | AP30: Yes | AQ30: 0.2339563
A31: ORD10813 | B31: 45931 | C31: CUST1085 | D31: Priya Jain | E31: Consumer | F31: Delhi | G31: Delhi | H31: North | I31: Clothing | J31: Jeans | K31: 1 | L31: 1200 | M31: 0.1 | N31: 1080 | O31: 619.52 | P31: 460.48 | Q31: 42.64 | R31: Net Banking | S31: Online | T31: Amit | U31: January | V31: 2025 | W31: Friday | X31: 6 | Y31: 16-01-2025 | Z31: Cancelled | AA31: VIP | AB31: Low | AC31: Yes | AD31: 2 | AE31: Priya | AF31: Jain | AM31: Good | AN31: Low | AO31: No | AP31: Yes | AQ31: 0.42637037
A32: ORD10785 | B32: 45849 | C32: CUST1047 | D32: Kavya Jain | E32: Small Business | F32: Jaipur | G32: Rajasthan | H32: North | I32: Clothing | J32: T-Shirt | K32: 9 | L32: 3500 | M32: 0.2 | N32: 25200 | O32: 17053.31 | P32: 8146.69 | Q32: 32.33 | R32: UPI | S32: Marketplace | T32: Sneha | U32: November | V32: 2025 | W32: Friday | X32: 10 | Y32: 17-11-2025 | Z32: Completed | AA32: Returning | AB32: Medium | AC32: Yes | AD32: 3 | AE32: Kavya | AF32: Jain | AM32: Good | AN32: Medium | AO32: No | AP32: Yes | AQ32: 0.32328135
A33: ORD10031 | B33: 45841 | C33: CUST1277 | D33: Vivaan Jain | E33: Consumer | F33: Hyderabad | G33: Telangana | H33: North | I33: Clothing | J33: Jacket | K33: 6 | L33: 2500 | M33: 0.1 | N33: 13500 | O33: 9139.27 | P33: 4360.73 | Q33: 32.3 | R33: Credit Card | S33: Online | T33: Rahul | U33: March | V33: 2025 | W33: Friday | X33: 5 | Y33: 45994 | Z33: Completed | AA33: New | AB33: Low | AC33: Yes | AD33: 2 | AE33: Vivaan | AF33: Jain | AM33: Good | AN33: Medium | AO33: No | AP33: Yes | AQ33: 0.32301704
A34: ORD10009 | B34: 45331 | C34: CUST1041 | D34: Aditya Yadav | E34: Corporate | F34: Chennai | G34: Tamil Nadu | H34: North | I34: Clothing | J34: Shirt | K34: 2 | L34: 1800 | M34: 0.1 | N34: 3240 | O34: 2550.08 | P34: 689.92 | Q34: 21.29 | R34: Net Banking | S34: Online | T34: Pooja | U34: September | V34: 2024 | W34: Monday | X34: 1 | Y34: 45360 | Z34: Completed | AA34: VIP | AB34: Medium | AC34: Yes | AD34: 3 | AE34: Aditya | AF34: Yadav | AM34: Needs Improvement | AN34: Low | AO34: No | AP34: Yes | AQ34: 0.21293827
A35: ORD10893 | B35: 45815 | C35: CUST1232 | D35: Ananya Mehta | E35: Consumer | F35: Ahmedabad | G35: Gujarat | H35: North | I35: Clothing | J35: Shoes | K35: 7 | L35: 2500 | M35: 0.05 | N35: 16625 | O35: 13335.81 | P35: 3289.19 | Q35: 19.78 | R35: Cash | S35: Retail Store | T35: Manish | U35: July | V35: 2025 | W35: Sunday | X35: 3 | Y35: 45907 | Z35: Completed | AA35: VIP | AB35: Medium | AC35: No | AD35: 5 | AE35: Ananya | AF35: Mehta | AM35: Needs Improvement | AN35: Medium | AO35: No | AP35: No | AQ35: 0.19784602
A36: ORD10763 | B36: 45813 | C36: CUST1342 | D36: Vikram Verma | E36: Small Business | F36: Chennai | G36: Tamil Nadu | H36: North | I36: Clothing | J36: Shoes | K36: 10 | L36: 1200 | M36: 0.15 | N36: 10200 | O36: 6395.83 | P36: 3804.17 | Q36: 37.3 | R36: Credit Card | S36: Online | T36: Manish | U36: May | V36: 2025 | W36: Tuesday | X36: 9 | Y36: 15-05-2025 | Z36: Cancelled | AA36: New | AB36: Low | AC36: No | AD36: 1 | AE36: Vikram | AF36: Verma | AM36: Good | AN36: Medium | AO36: No | AP36: Yes | AQ36: 0.37295784
A37: ORD10440 | B37: 45812 | C37: CUST1255 | D37: Neha Kumar | E37: Corporate | F37: Delhi | G37: Delhi | H37: North | I37: Clothing | J37: T-Shirt | K37: 10 | L37: 1800 | M37: 0.15 | N37: 15300 | O37: 10104.38 | P37: 5195.62 | Q37: 33.96 | R37: Debit Card | S37: Retail Store | T37: Rahul | U37: April | V37: 2025 | W37: Sunday | X37: 8 | Y37: 14-04-2025 | Z37: Pending | AA37: Returning | AB37: High | AC37: Yes | AD37: 3 | AE37: Neha | AF37: Kumar | AM37: Good | AN37: Medium | AO37: No | AP37: No | AQ37: 0.33958301
A38: ORD10004 | B38: 45778 | C38: CUST1024 | D38: Vikram Agarwal | E38: Corporate | F38: Mumbai | G38: Maharashtra | H38: North | I38: Clothing | J38: Shirt | K38: 9 | L38: 1800 | M38: 0.2 | N38: 12960 | O38: 9593.44 | P38: 3366.56 | Q38: 25.98 | R38: Debit Card | S38: Online | T38: Kavita | U38: January | V38: 2025 | W38: Sunday | X38: 10 | Y38: 15-01-2025 | Z38: Completed | AA38: Returning | AB38: Medium | AC38: No | AD38: 2 | AE38: Vikram | AF38: Agarwal | AM38: Needs Improvement | AN38: Medium | AO38: No | AP38: Yes | AQ38: 0.25976543
A39: ORD10329 | B39: 45697 | C39: CUST1046 | D39: Priya Jain | E39: Corporate | F39: Jaipur | G39: Rajasthan | H39: North | I39: Clothing | J39: Jeans | K39: 3 | L39: 3500 | M39: 0 | N39: 10500 | O39: 7510.16 | P39: 2989.84 | Q39: 28.47 | R39: Net Banking | S39: Online | T39: Rahul | U39: September | V39: 2025 | W39: Tuesday | X39: 3 | Y39: 45786 | Z39: Pending | AA39: New | AB39: High | AC39: Yes | AD39: 5 | AE39: Priya | AF39: Jain | AM39: Needs Improvement | AN39: Medium | AO39: No | AP39: Yes | AQ39: 0.28474667
A40: ORD10445 | B40: 45662 | C40: CUST1232 | D40: Priya Verma | E40: Consumer | F40: Hyderabad | G40: Telangana | H40: North | I40: Clothing | J40: Shirt | K40: 9 | L40: 2500 | M40: 0.05 | N40: 21375 | O40: 15043.06 | P40: 6331.94 | Q40: 29.62 | R40: Net Banking | S40: Online | T40: Amit | U40: May | V40: 2025 | W40: Thursday | X40: 2 | Y40: 45721 | Z40: Completed | AA40: VIP | AB40: High | AC40: No | AD40: 1 | AE40: Priya | AF40: Verma | AM40: Needs Improvement | AN40: Medium | AO40: No | AP40: Yes | AQ40: 0.29623111
A41: ORD10375 | B41: 45662 | C41: CUST1311 | D41: Vivaan Chopra | E41: Small Business | F41: Kolkata | G41: West Bengal | H41: North | I41: Clothing | J41: Jeans | K41: 5 | L41: 1200 | M41: 0.1 | N41: 5400 | O41: 3000.73 | P41: 2399.27 | Q41: 44.43 | R41: Debit Card | S41: Retail Store | T41: Anjali | U41: May | V41: 2025 | W41: Thursday | X41: 6 | Y41: 45843 | Z41: Completed | AA41: Returning | AB41: Medium | AC41: No | AD41: 1 | AE41: Vivaan | AF41: Chopra | AM41: Good | AN41: Low | AO41: No | AP41: No | AQ41: 0.44430926
A42: ORD10200 | B42: 45630 | C42: CUST1185 | D42: Neha Mehta | E42: Small Business | F42: Hyderabad | G42: Telangana | H42: North | I42: Clothing | J42: Jacket | K42: 5 | L42: 2500 | M42: 0 | N42: 12500 | O42: 9751.34 | P42: 2748.66 | Q42: 21.99 | R42: Credit Card | S42: Online | T42: Amit | U42: April | V42: 2024 | W42: Friday | X42: 3 | Y42: 15-04-2024 | Z42: Completed | AA42: New | AB42: High | AC42: Yes | AD42: 3 | AE42: Neha | AF42: Mehta | AM42: Needs Improvement | AN42: Medium | AO42: No | AP42: Yes | AQ42: 0.2198928
A43: ORD10978 | B43: 45540 | C43: CUST1188 | D43: Kavya Chopra | E43: Consumer | F43: Chennai | G43: Tamil Nadu | H43: North | I43: Clothing | J43: Shirt | K43: 6 | L43: 2500 | M43: 0.2 | N43: 12000 | O43: 7058.58 | P43: 4941.42 | Q43: 41.18 | R43: Credit Card | S43: Online | T43: Kavita | U43: May | V43: 2024 | W43: Thursday | X43: 1 | Y43: 45570 | Z43: Cancelled | AA43: New | AB43: High | AC43: No | AD43: 4 | AE43: Kavya | AF43: Chopra | AM43: Good | AN43: Medium | AO43: No | AP43: Yes | AQ43: 0.411785
A44: ORD10021 | B44: 45515 | C44: CUST1099 | D44: Pooja Jain | E44: Corporate | F44: Delhi | G44: Delhi | H44: North | I44: Clothing | J44: Jeans | K44: 4 | L44: 2500 | M44: 0.1 | N44: 9000 | O44: 5007.5 | P44: 3992.5 | Q44: 44.36 | R44: UPI | S44: Retail Store | T44: Anjali | U44: November | V44: 2024 | W44: Friday | X44: 4 | Y44: 45637 | Z44: Completed | AA44: Returning | AB44: High | AC44: No | AD44: 1 | AE44: Pooja | AF44: Jain | AM44: Good | AN44: Low | AO44: No | AP44: No | AQ44: 0.44361111
A45: ORD10012 | B45: 45447 | C45: CUST1211 | D45: Riya Chopra | E45: Small Business | F45: Lucknow | G45: Uttar Pradesh | H45: North | I45: Clothing | J45: Jeans | K45: 8 | L45: 2500 | M45: 0.05 | N45: 19000 | O45: 12267.55 | P45: 6732.45 | Q45: 35.43 | R45: Credit Card | S45: Online | T45: Kavita | U45: April | V45: 2024 | W45: Saturday | X45: 2 | Y45: 45508 | Z45: Pending | AA45: VIP | AB45: Medium | AC45: Yes | AD45: 2 | AE45: Riya | AF45: Chopra | AM45: Good | AN45: Medium | AO45: No | AP45: Yes | AQ45: 0.35433947
A46: ORD10512 | B46: 45424 | C46: CUST1279 | D46: Ananya Mishra | E46: Small Business | F46: Bengaluru | G46: Karnataka | H46: North | I46: Clothing | J46: T-Shirt | K46: 8 | L46: 1200 | M46: 0.1 | N46: 8640 | O46: 5320.76 | P46: 3319.24 | Q46: 38.42 | R46: Credit Card | S46: Online | T46: Neeraj | U46: December | V46: 2024 | W46: Thursday | X46: 8 | Y46: 13-12-2024 | Z46: Completed | AA46: VIP | AB46: Medium | AC46: Yes | AD46: 5 | AE46: Ananya | AF46: Mishra | AM46: Good | AN46: Low | AO46: No | AP46: Yes | AQ46: 0.3841713
A47: ORD10219 | B47: 45415 | C47: CUST1038 | D47: Sneha Saxena | E47: Small Business | F47: Delhi | G47: Delhi | H47: North | I47: Clothing | J47: Shirt | K47: 9 | L47: 700 | M47: 0.2 | N47: 5040 | O47: 3725.76 | P47: 1314.24 | Q47: 26.08 | R47: UPI | S47: Marketplace | T47: Sneha | U47: March | V47: 2024 | W47: Tuesday | X47: 10 | Y47: 15-03-2024 | Z47: Completed | AA47: VIP | AB47: Low | AC47: No | AD47: 4 | AE47: Sneha | AF47: Saxena | AM47: Needs Improvement | AN47: Low | AO47: No | AP47: Yes | AQ47: 0.2607619
A48: ORD10196 | B48: 45390 | C48: CUST1064 | D48: Sneha Yadav | E48: Small Business | F48: Bengaluru | G48: Karnataka | H48: North | I48: Clothing | J48: Shirt | K48: 4 | L48: 1200 | M48: 0.05 | N48: 4560 | O48: 3129.3 | P48: 1430.7 | Q48: 31.38 | R48: Cash | S48: Marketplace | T48: Sneha | U48: August | V48: 2024 | W48: Sunday | X48: 1 | Y48: 45420 | Z48: Cancelled | AA48: VIP | AB48: High | AC48: Yes | AD48: 5 | AE48: Sneha | AF48: Yadav | AM48: Good | AN48: Low | AO48: No | AP48: Yes | AQ48: 0.31375
A49: ORD10825 | B49: 45386 | C49: CUST1097 | D49: Aditi Kumar | E49: Small Business | F49: Mumbai | G49: Maharashtra | H49: North | I49: Clothing | J49: T-Shirt | K49: 5 | L49: 700 | M49: 0.1 | N49: 3150 | O49: 2062.39 | P49: 1087.61 | Q49: 34.53 | R49: Net Banking | S49: Online | T49: Neeraj | U49: April | V49: 2024 | W49: Thursday | X49: 6 | Y49: 45569 | Z49: Completed | AA49: New | AB49: Low | AC49: No | AD49: 2 | AE49: Aditi | AF49: Kumar | AM49: Good | AN49: Low | AO49: No | AP49: Yes | AQ49: 0.34527302
A50: ORD10127 | B50: 45362 | C50: CUST1195 | D50: Pooja Kapoor | E50: Corporate | F50: Chennai | G50: Tamil Nadu | H50: North | I50: Clothing | J50: Shoes | K50: 10 | L50: 1200 | M50: 0.05 | N50: 11400 | O50: 6557.79 | P50: 4842.21 | Q50: 42.48 | R50: Credit Card | S50: Marketplace | T50: Pooja | U50: November | V50: 2024 | W50: Sunday | X50: 2 | Y50: 45423 | Z50: Completed | AA50: New | AB50: Medium | AC50: No | AD50: 3 | AE50: Pooja | AF50: Kapoor | AM50: Good | AN50: Medium | AO50: No | AP50: Yes | AQ50: 0.42475526

Sheet Dashboard
S1: Total Sales | U1: Total aprofit | W1: Total Orders | Y1: Average Order Value | AA1: Sumproduct
A2: Region | B2: Sum of Sales | S2: =SUM(Sheet1!N2:N1001) -> 30311250 | U2: =SUM(Sheet1!P2:P1001) -> 9519984.1 | W2: =COUNTA(Sheet1!A2:A1001) -> 1000 | Y2: =AVERAGE(Sheet1!N2:N1001) -> 30311.25 | AA2: =SUMPRODUCT(Sheet1!K2:K1001,Sheet1!L2:L1001) -> 33700500
A3: North | B3: 5965332.5
A4: Grand Total | B4: 5965332.5 | S4: Top Product | U4: Top salesperson
S5: Watch | U5: Vikas
A21: Category | B21: Sum of Sales
A22: Accessories | B22: 348330
A23: Clothing | B23: 490985
A24: Electronics | B24: 3481750
A25: Furniture | B25: 1519200
A26: Office Supplies | B26: 125067.5
A27: Grand Total | B27: 5965332.5
A40: Product | B40: Sum of Sales
A41: Watch | B41: 60020
A42: Wallet | B42: 43680
A43: T-Shirt | B43: 150785
A44: Tablet | B44: 580700
A45: Table | B45: 383400
A46: Sunglasses | B46: 81185
A47: Stapler | B47: 6720
A48: Sofa | B48: 311500
A49: Smartphone | B49: 501950
A50: Shoes | B50: 124270
A51: Shirt | B51: 62150
A52: Printer Paper | B52: 38537.5
... A66: Grand Total | B66: 5965332.5
A72: Category | B72: Sum of Profit
A73: Accessories | B73: 104830.38
A74: Clothing | B74: 153730.63
A75: Electronics | B75: 1065908.1
A76: Furniture | B76: 481396.74
A77: Office Supplies | B77: 38664.94
A78: Grand Total | B78: 1844530.8
A86: Month | B86: Sum of Sales
A87: January | B87: 363005
A88: February | B88: 450610
A89: March | B89: 562725
A90: April | B90: 341137.5
A91: May | B91: 146860
A92: June | B92: 659850
A93: July | B93: 920195
A94: August | B94: 539760
A95: September | B95: 301135
A96: October | B96: 636760
A97: November | B97: 364815
A98: December | B98: 678480
A99: Grand Total | B99: 5965332.5
A104: Salesperson | B104: Sum of Sales
A105: Vikas | B105: 228485
A106: Sneha | B106: 484730
A107: Rohit | B107: 568825
A108: Rahul | B108: 463430
A109: Pooja | B109: 806355
A110: Neeraj | B110: 467107.5
A111: Manish | B111: 560260
A112: Kavita | B112: 361525
A113: Anjali | B113: 809160
A114: Amit | B114: 1215455
A115: Grand Total | B115: 5965332.5
A122: Customer_Segment | B122: Sum of Sales
A123: Consumer | B123: 1348000
A124: Corporate | B124: 2692430
A125: Small Business | B125: 1924902.5
A126: Grand Total | B126: 5965332.5
A139: Payment_Method | B139: Sum of Sales
A140: Cash | B140: 1326045
A141: Credit Card | B141: 1475755
A142: Debit Card | B142: 952795
A143: Net Banking | B143: 1122745
A144: UPI | B144: 1087992.5
A145: Grand Total | B145: 5965332.5
A156: Order_Status | B156: Sum of Sales
A157: Cancelled | B157: 1608990
A158: Completed | B158: 3327192.5
A159: Pending | B159: 1029150
A160: Grand Total | B160: 5965332.5

Sheet Sheet1
A1: Order_ID | B1: Order_Date | C1: Customer_ID | D1: Customer_Name | E1: Customer_Segment | F1: City | G1: State | H1: Region | I1: Category | J1: Product | K1: Quantity | L1: Unit_Price | M1: Discount | N1: Sales | O1: Cost | P1: Profit | Q1: Profit_Margin_% | R1: Payment_Method | S1: Sales_Channel | T1: Salesperson | U1: Month | V1: Year | W1: Day_Name | X1: Delivery_Days | Y1: Delivery_Date | Z1: Order_Status | AA1: Customer_Type | AB1: Priority | AC1: Return_Requested | AD1: Rating | AE1: First_name | AF1: Last_Name | AG1: SUM | AH1: Average | AI1: Count | AJ1: Counta | AK1: MIN | AL1: Max | AM1: IF | AN1: IFS | AO1: AND | AP1: OR | AQ1: IFERROR | AR1: COUNTIFS | AS1: AVERAGEIFS | AT1: Region-wise Sales | AU1: Category-wise Sales | AV1: Total Sales | AW1: Region_Total_Sales | AX1: Performance
A2: ORD10146 | B2: 45294 | C2: CUST1306 | D2: Aditi Gupta | E2: Corporate | F2: Kolkata | G2: West Bengal | H2: East | I2: Furniture | J2: Table | K2: 3 | L2: 4000 | M2: 0.05 | N2: 11400 | O2: 7908.36 | P2: 3491.64 | Q2: 30.63 | R2: UPI | S2: Marketplace | T2: Sneha | U2: March | V2: 2024 | W2: Friday | X2: 10 | Y2: 45599 | Z2: Completed | AA2: VIP | AB2: High | AC2: Yes | AD2: 2 | AE2: Aditi | AF2: Gupta | AG2: =SUM(N2:N1001) -> 30311250 | AH2: =AVERAGE(N2:N1001) -> 30311.25 | AI2: =COUNT(N2:N1001) -> 1000 | AJ2: =COUNTA(N2:N1001) -> 1000 | AK2: =MIN(N2:N1001) -> 95 | AL2: =MAX(N2:N1001) -> 450000 | AM2: =IF(Q2>=30,"Good","Needs Improvement") -> Good | AN2: {=_xlfn.IFS(N2<10000,"Low",N2<30000,"Medium",N2>=30000,"High")} -> Medium | AO2: =IF(AND(N2>=30000,P2>=10000),"Yes","No") -> No | AP2: =IF(OR(S2="Online",S2="Marketplace"),"Yes","No") -> Yes | AQ2: =IFERROR(P2/N2,"No Error") -> 0.30628421 | AR2: =COUNTIFS($I$2:$I$1001,AU2) -> 188 | AS2: =AVERAGEIFS($N$2:$N$1001,$I$2:$I$1001,AU2) -> 105143.62 | AT2: North | AU2: Electronics | AV2: =SUMIFS($N$2:$N$1001,$I$2:$I$1001,AU2) -> 19767000 | AW2: =SUMIFS($N$2:$N$1001,$H$2:$H$1001,AT2) -> 5965332.5 | AX2: =IF(P2>=20000,"Excellent",IF(P2>=10000,"Good",IF(P2>=5000,"Average","Low"))) -> Low
A3: ORD10172 | B3: 45294 | C3: CUST1073 | D3: Arjun Chopra | E3: Small Business | F3: Lucknow | G3: Uttar Pradesh | H3: East | I3: Furniture | J3: Desk | K3: 6 | L3: 4000 | M3: 0.1 | N3: 21600 | O3: 15301.1 | P3: 6298.9 | Q3: 29.16 | R3: Credit Card | S3: Retail Store | T3: Kavita | U3: March | V3: 2024 | W3: Friday | X3: 1 | Y3: 45325 | Z3: Completed | AA3: VIP | AB3: Low | AC3: No | AD3: 3 | AE3: Arjun | AF3: Chopra | AM3: =IF(Q3>=30,"Good","Needs Improvement") -> Needs Improvement | AN3: {=_xlfn.IFS(N3<10000,"Low",N3<30000,"Medium",N3>=30000,"High")} -> Medium | AO3: =IF(AND(N3>=30000,P3>=10000),"Yes","No") -> No | AP3: =IF(OR(S3="Online",S3="Marketplace"),"Yes","No") -> No | AQ3: =IFERROR(P3/N3,"No Error") -> 0.29161574 | AR3: =COUNTIFS($I$2:$I$1001,AU3) -> 205 | AS3: =AVERAGEIFS($N$2:$N$1001,$I$2:$I$1001,AU3) -> 33072.195 | AT3: South | AU3: Furniture | AV3: =SUMIFS($N$2:$N$1001,$I$2:$I$1001,AU3) -> 6779800 | AW3: =SUMIFS($N$2:$N$1001,$H$2:$H$1001,AT3) -> 8560317.5 | AX3: =IF(P3>=20000,"Excellent",IF(P3>=10000,"Good",IF(P3>=5000,"Average","Low"))) -> Average
A4: ORD10477 | B4: 45294 | C4: CUST1108 | D4: Vikram Yadav | E4: Small Business | F4: Lucknow | G4: Uttar Pradesh | H4: North | I4: Clothing | J4: Jeans | K4: 8 | L4: 1800 | M4: 0.15 | N4: 12240 | O4: 9467.99 | P4: 2772.01 | Q4: 22.65 | R4: Debit Card | S4: Retail Store | T4: Kavita | U4: March | V4: 2024 | W4: Friday | X4: 6 | Y4: 45476 | Z4: Completed | AA4: Returning | AB4: High | AC4: Yes | AD4: 1 | AE4: Vikram | AF4: Yadav | AM4: =IF(Q4>=30,"Good","Needs Improvement") -> Needs Improvement | AN4: {=_xlfn.IFS(N4<10000,"Low",N4<30000,"Medium",N4>=30000,"High")} -> Medium | AO4: =IF(AND(N4>=30000,P4>=10000),"Yes","No") -> No | AP4: =IF(OR(S4="Online",S4="Marketplace"),"Yes","No") -> No | AQ4: =IFERROR(P4/N4,"No Error") -> 0.22647141 | AR4: =COUNTIFS($I$2:$I$1001,AU4) -> 196 | AS4: =AVERAGEIFS($N$2:$N$1001,$I$2:$I$1001,AU4) -> 2098.648 | AT4: East | AU4: Office Supplies | AV4: =SUMIFS($N$2:$N$1001,$I$2:$I$1001,AU4) -> 411335 | AW4: =SUMIFS($N$2:$N$1001,$H$2:$H$1001,AT4) -> 7518642.5 | AX4: =IF(P4>=20000,"Excellent",IF(P4>=10000,"Good",IF(P4>=5000,"Average","Low"))) -> Low
A5: ORD10927 | B5: 45294 | C5: CUST1107 | D5: Aarav Agarwal | E5: Small Business | F5: Jaipur | G5: Rajasthan | H5: West | I5: Clothing | J5: Shirt | K5: 2 | L5: 700 | M5: 0.2 | N5: 1120 | O5: 653.09 | P5: 466.91 | Q5: 41.69 | R5: Net Banking | S5: Online | T5: Neeraj | U5: March | V5: 2024 | W5: Friday | X5: 2 | Y5: 45354 | Z5: Cancelled | AA5: Returning | AB5: Medium | AC5: No | AD5: 1 | AE5: Aarav | AF5: Agarwal | AM5: =IF(Q5>=30,"Good","Needs Improvement") -> Good | AN5: {=_xlfn.IFS(N5<10000,"Low",N5<30000,"Medium",N5>=30000,"High")} -> Low | AO5: =IF(AND(N5>=30000,P5>=10000),"Yes","No") -> No | AP5: =IF(OR(S5="Online",S5="Marketplace"),"Yes","No") -> Yes | AQ5: =IFERROR(P5/N5,"No Error") -> 0.41688393 | AR5: =COUNTIFS($I$2:$I$1001,AU5) -> 195 | AS5: =AVERAGEIFS($N$2:$N$1001,$I$2:$I$1001,AU5) -> 9673.6923 | AT5: West | AU5: Clothing | AV5: =SUMIFS($N$2:$N$1001,$I$2:$I$1001,AU5) -> 1886370 | AW5: =SUMIFS($N$2:$N$1001,$H$2:$H$1001,AT5) -> 8266957.5 | AX5: =IF(P5>=20000,"Excellent",IF(P5>=10000,"Good",IF(P5>=5000,"Average","Low"))) -> Low
A6: ORD10497 | B6: 45296 | C6: CUST1350 | D6: Rohan Jain | E6: Corporate | F6: Chennai | G6: Tamil Nadu | H6: West | I6: Electronics | J6: Smartphone | K6: 4 | L6: 22000 | M6: 0.1 | N6: 79200 | O6: 55323.84 | P6: 23876.16 | Q6: 30.15 | R6: Debit Card | S6: Online | T6: Neeraj | U6: May | V6: 2024 | W6: Wednesday | X6: 7 | Y6: 45509 | Z6: Pending | AA6: New | AB6: Low | AC6: Yes | AD6: 3 | AE6: Rohan | AF6: Jain | AM6: =IF(Q6>=30,"Good","Needs Improvement") -> Good | AN6: {=_xlfn.IFS(N6<10000,"Low",N6<30000,"Medium",N6>=30000,"High")} -> High | AO6: =IF(AND(N6>=30000,P6>=10000),"Yes","No") -> Yes | AP6: =IF(OR(S6="Online",S6="Marketplace"),"Yes","No") -> Yes | AQ6: =IFERROR(P6/N6,"No Error") -> 0.30146667 | AR6: =COUNTIFS($I$2:$I$1001,AU6) -> 216 | AS6: =AVERAGEIFS($N$2:$N$1001,$I$2:$I$1001,AU6) -> 6790.4861 | AU6: Accessories | AV6: =SUMIFS($N$2:$N$1001,$I$2:$I$1001,AU6) -> 1466745 | AX6: =IF(P6>=20000,"Excellent",IF(P6>=10000,"Good",IF(P6>=5000,"Average","Low"))) -> Excellent
A7: ORD10605 | B7: 45296 | C7: CUST1115 | D7: Karan Kumar | E7: Corporate | F7: Lucknow | G7: Uttar Pradesh | H7: North | I7: Office Supplies | J7: Notebook | K7: 6 | L7: 350 | M7: 0.05 | N7: 1995 | O7: 1359.38 | P7: 635.62 | Q7: 31.86 | R7: Debit Card | S7: Marketplace | T7: Sneha | U7: May | V7: 2024 | W7: Wednesday | X7: 5 | Y7: 45448 | Z7: Completed | AA7: New | AB7: Low | AC7: Yes | AD7: 5 | AE7: Karan | AF7: Kumar | AM7: =IF(Q7>=30,"Good","Needs Improvement") -> Good | AN7: {=_xlfn.IFS(N7<10000,"Low",N7<30000,"Medium",N7>=30000,"High")} -> Low | AO7: =IF(AND(N7>=30000,P7>=10000),"Yes","No") -> No | AP7: =IF(OR(S7="Online",S7="Marketplace"),"Yes","No") -> Yes | AQ7: =IFERROR(P7/N7,"No Error") -> 0.31860652 | AX7: =IF(P7>=20000,"Excellent",IF(P7>=10000,"Good",IF(P7>=5000,"Average","Low"))) -> Low
A8: ORD10515 | B8: 45297 | C8: CUST1229 | D8: Kavya Chopra | E8: Consumer | F8: Pune | G8: Maharashtra | H8: North | I8: Clothing | J8: Jacket | K8: 5 | L8: 700 | M8: 0 | N8: 3500 | O8: 2064.65 | P8: 1435.35 | Q8: 41.01 | R8: Net Banking | S8: Retail Store | T8: Sneha | U8: June | V8: 2024 | W8: Saturday | X8: 3 | Y8: 45388 | Z8: Completed | AA8: New | AB8: Low | AC8: No | AD8: 2 | AE8: Kavya | AF8: Chopra | AM8: =IF(Q8>=30,"Good","Needs Improvement") -> Good | AN8: {=_xlfn.IFS(N8<10000,"Low",N8<30000,"Medium",N8>=30000,"High")} -> Low | AO8: =IF(AND(N8>=30000,P8>=10000),"Yes","No") -> No | AP8: =IF(OR(S8="Online",S8="Marketplace"),"Yes","No") -> No | AQ8: =IFERROR(P8/N8,"No Error") -> 0.4101 | AX8: =IF(P8>=20000,"Excellent",IF(P8>=10000,"Good",IF(P8>=5000,"Average","Low"))) -> Low
A9: ORD10324 | B9: 45300 | C9: CUST1277 | D9: Priya Malhotra | E9: Small Business | F9: Bengaluru | G9: Karnataka | H9: West | I9: Electronics | J9: Smartphone | K9: 1 | L9: 50000 | M9: 0.2 | N9: 40000 | O9: 22680.32 | P9: 17319.68 | Q9: 43.3 | R9: Credit Card | S9: Online | T9: Vikas | U9: September | V9: 2024 | W9: Sunday | X9: 8 | Y9: 45544 | Z9: Pending | AA9: New | AB9: Medium | AC9: Yes | AD9: 4 | AE9: Priya | AF9: Malhotra | AM9: =IF(Q9>=30,"Good","Needs Improvement") -> Good | AN9: {=_xlfn.IFS(N9<10000,"Low",N9<30000,"Medium",N9>=30000,"High")} -> High | AO9: =IF(AND(N9>=30000,P9>=10000),"Yes","No") -> Yes | AP9: =IF(OR(S9="Online",S9="Marketplace"),"Yes","No") -> Yes | AQ9: =IFERROR(P9/N9,"No Error") -> 0.432992 | AX9: =IF(P9>=20000,"Excellent",IF(P9>=10000,"Good",IF(P9>=5000,"Average","Low"))) -> Good
A10: ORD10559 | B10: 45300 | C10: CUST1116 | D10: Simran Yadav | E10: Small Business | F10: Hyderabad | G10: Telangana | H10: West | I10: Electronics | J10: Laptop | K10: 1 | L10: 35000 | M10: 0.1 | N10: 31500 | O10: 18184.28 | P10: 13315.72 | Q10: 42.27 | R10: Cash | S10: Retail Store | T10: Neeraj | U10: September | V10: 2024 | W10: Sunday | X10: 2 | Y10: 45360 | Z10: Cancelled | AA10: New | AB10: High | AC10: No | AD10: 4 | AE10: Simran | AF10: Yadav | AM10: =IF(Q10>=30,"Good","Needs Improvement") -> Good | AN10: {=_xlfn.IFS(N10<10000,"Low",N10<30000,"Medium",N10>=30000,"High")} -> High | AO10: =IF(AND(N10>=30000,P10>=10000),"Yes","No") -> Yes | AP10: =IF(OR(S10="Online",S10="Marketplace"),"Yes","No") -> No | AQ10: =IFERROR(P10/N10,"No Error") -> 0.42272127 | AX10: =IF(P10>=20000,"Excellent",IF(P10>=10000,"Good",IF(P10>=5000,"Average","Low"))) -> Good
A11: ORD10370 | B11: 45301 | C11: CUST1223 | D11: Nisha Yadav | E11: Small Business | F11: Ahmedabad | G11: Gujarat | H11: North | I11: Furniture | J11: Table | K11: 8 | L11: 4000 | M11: 0.15 | N11: 27200 | O11: 21222.78 | P11: 5977.22 | Q11: 21.98 | R11: Net Banking | S11: Online | T11: Vikas | U11: October | V11: 2024 | W11: Tuesday | X11: 9 | Y11: 45575 | Z11: Cancelled | AA11: Returning | AB11: Low | AC11: Yes | AD11: 2 | AE11: Nisha | AF11: Yadav | AM11: =IF(Q11>=30,"Good","Needs Improvement") -> Needs Improvement | AN11: {=_xlfn.IFS(N11<10000,"Low",N11<30000,"Medium",N11>=30000,"High")} -> Medium | AO11: =IF(AND(N11>=30000,P11>=10000),"Yes","No") -> No | AP11: =IF(OR(S11="Online",S11="Marketplace"),"Yes","No") -> Yes | AQ11: =IFERROR(P11/N11,"No Error") -> 0.21975074 | AX11: =IF(P11>=20000,"Excellent",IF(P11>=10000,"Good",IF(P11>=5000,"Average","Low"))) -> Average
A12: ORD10538 | B12: 45301 | C12: CUST1213 | D12: Vikram Sharma | E12: Corporate | F12: Kolkata | G12: West Bengal | H12: North | I12: Electronics | J12: Tablet | K12: 4 | L12: 35000 | M12: 0.1 | N12: 126000 | O12: 97825.23 | P12: 28174.77 | Q12: 22.36 | R12: Credit Card | S12: Online | T12: Pooja | U12: October | V12: 2024 | W12: Tuesday | X12: 5 | Y12: 45453 | Z12: Completed | AA12: Returning | AB12: High | AC12: No | AD12: 3 | AE12: Vikram | AF12: Sharma | AM12: =IF(Q12>=30,"Good","Needs Improvement") -> Needs Improvement | AN12: {=_xlfn.IFS(N12<10000,"Low",N12<30000,"Medium",N12>=30000,"High")} -> High | AO12: =IF(AND(N12>=30000,P12>=10000),"Yes","No") -> Yes | AP12: =IF(OR(S12="Online",S12="Marketplace"),"Yes","No") -> Yes | AQ12: =IFERROR(P12/N12,"No Error") -> 0.22360929 | AX12: =IF(P12>=20000,"Excellent",IF(P12>=10000,"Good",IF(P12>=5000,"Average","Low"))) -> Excellent
A13: ORD10437 | B13: 45303 | C13: CUST1144 | D13: Rohan Chopra | E13: Small Business | F13: Lucknow | G13: Uttar Pradesh | H13: West | I13: Accessories | J13: Watch | K13: 9 | L13: 1200 | M13: 0.05 | N13: 10260 | O13: 7386.73 | P13: 2873.27 | Q13: 28 | R13: Debit Card | S13: Marketplace | T13: Neeraj | U13: December | V13: 2024 | W13: Sunday | X13: 4 | Y13: 45424 | Z13: Completed | AA13: Returning | AB13: High | AC13: Yes | AD13: 2 | AE13: Rohan | AF13: Chopra | AM13: =IF(Q13>=30,"Good","Needs Improvement") -> Needs Improvement | AN13: {=_xlfn.IFS(N13<10000,"Low",N13<30000,"Medium",N13>=30000,"High")} -> Medium | AO13: =IF(AND(N13>=30000,P13>=10000),"Yes","No") -> No | AP13: =IF(OR(S13="Online",S13="Marketplace"),"Yes","No") -> Yes | AQ13: =IFERROR(P13/N13,"No Error") -> 0.28004581 | AX13: =IF(P13>=20000,"Excellent",IF(P13>=10000,"Good",IF(P13>=5000,"Average","Low"))) -> Low
A14: ORD10475 | B14: 45323 | C14: CUST1098 | D14: Pooja Mehta | E14: Corporate | F14: Lucknow | G14: Uttar Pradesh | H14: East | I14: Office Supplies | J14: Printer Paper | K14: 6 | L14: 500 | M14: 0.2 | N14: 2400 | O14: 1702.36 | P14: 697.64 | Q14: 29.07 | R14: Debit Card | S14: Marketplace | T14: Manish | U14: January | V14: 2024 | W14: Tuesday | X14: 5 | Y14: 45474 | Z14: Completed | AA14: VIP | AB14: Low | AC14: Yes | AD14: 4 | AE14: Pooja | AF14: Mehta | AM14: =IF(Q14>=30,"Good","Needs Improvement") -> Needs Improvement | AN14: {=_xlfn.IFS(N14<10000,"Low",N14<30000,"Medium",N14>=30000,"High")} -> Low | AO14: =IF(AND(N14>=30000,P14>=10000),"Yes","No") -> No | AP14: =IF(OR(S14="Online",S14="Marketplace"),"Yes","No") -> Yes | AQ14: =IFERROR(P14/N14,"No Error") -> 0.29068333 | AX14: =IF(P14>=20000,"Excellent",IF(P14>=10000,"Good",IF(P14>=5000,"Average","Low"))) -> Low
A15: ORD10714 | B15: 45323 | C15: CUST1197 | D15: Priya Sharma | E15: Small Business | F15: Delhi | G15: Delhi | H15: East | I15: Accessories | J15: Backpack | K15: 6 | L15: 500 | M15: 0.05 | N15: 2850 | O15: 1571.09 | P15: 1278.91 | Q15: 44.87 | R15: Credit Card | S15: Online | T15: Rahul | U15: January | V15: 2024 | W15: Tuesday | X15: 9 | Y15: 45597 | Z15: Completed | AA15: VIP | AB15: High | AC15: No | AD15: 2 | AE15: Priya | AF15: Sharma | AM15: =IF(Q15>=30,"Good","Needs Improvement") -> Good | AN15: {=_xlfn.IFS(N15<10000,"Low",N15<30000,"Medium",N15>=30000,"High")} -> Low | AO15: =IF(AND(N15>=30000,P15>=10000),"Yes","No") -> No | AP15: =IF(OR(S15="Online",S15="Marketplace"),"Yes","No") -> Yes | AQ15: =IFERROR(P15/N15,"No Error") -> 0.44874035 | AX15: =IF(P15>=20000,"Excellent",IF(P15>=10000,"Good",IF(P15>=5000,"Average","Low"))) -> Low
A16: ORD10115 | B16: 45324 | C16: CUST1070 | D16: Ishita Jain | E16: Corporate | F16: Chennai | G16: Tamil Nadu | H16: West | I16: Electronics | J16: Monitor | K16: 1 | L16: 8000 | M16: 0.15 | N16: 6800 | O16: 4070.45 | P16: 2729.55 | Q16: 40.14 | R16: Cash | S16: Retail Store | T16: Neeraj | U16: February | V16: 2024 | W16: Friday | X16: 5 | Y16: 45475 | Z16: Pending | AA16: VIP | AB16: High | AC16: Yes | AD16: 3 | AE16: Ishita | AF16: Jain | AM16: =IF(Q16>=30,"Good","Needs Improvement") -> Good | AN16: {=_xlfn.IFS(N16<10000,"Low",N16<30000,"Medium",N16>=30000,"High")} -> Low | AO16: =IF(AND(N16>=30000,P16>=10000),"Yes","No") -> No | AP16: =IF(OR(S16="Online",S16="Marketplace"),"Yes","No") -> No | AQ16: =IFERROR(P16/N16,"No Error") -> 0.40140441 | AX16: =IF(P16>=20000,"Excellent",IF(P16>=10000,"Good",IF(P16>=5000,"Average","Low"))) -> Low
A17: ORD10992 | B17: 45324 | C17: CUST1314 | D17: Priya Verma | E17: Consumer | F17: Lucknow | G17: Uttar Pradesh | H17: East | I17: Electronics | J17: Laptop | K17: 5 | L17: 15000 | M17: 0.05 | N17: 71250 | O17: 40064.87 | P17: 31185.13 | Q17: 43.77 | R17: Net Banking | S17: Online | T17: Rahul | U17: February | V17: 2024 | W17: Friday | X17: 4 | Y17: 45445 | Z17: Pending | AA17: VIP | AB17: Medium | AC17: Yes | AD17: 5 | AE17: Priya | AF17: Verma | AM17: =IF(Q17>=30,"Good","Needs Improvement") -> Good | AN17: {=_xlfn.IFS(N17<10000,"Low",N17<30000,"Medium",N17>=30000,"High")} -> High | AO17: =IF(AND(N17>=30000,P17>=10000),"Yes","No") -> Yes | AP17: =IF(OR(S17="Online",S17="Marketplace"),"Yes","No") -> Yes | AQ17: =IFERROR(P17/N17,"No Error") -> 0.43768604 | AX17: =IF(P17>=20000,"Excellent",IF(P17>=10000,"Good",IF(P17>=5000,"Average","Low"))) -> Excellent
A18: ORD10660 | B18: 45325 | C18: CUST1021 | D18: Sneha Mehta | E18: Small Business | F18: Mumbai | G18: Maharashtra | H18: West | I18: Accessories | J18: Belt | K18: 1 | L18: 2000 | M18: 0.15 | N18: 1700 | O18: 1315.19 | P18: 384.81 | Q18: 22.64 | R18: Cash | S18: Online | T18: Neeraj | U18: March | V18: 2024 | W18: Saturday | X18: 5 | Y18: 45476 | Z18: Pending | AA18: New | AB18: Medium | AC18: Yes | AD18: 2 | AE18: Sneha | AF18: Mehta | AM18: =IF(Q18>=30,"Good","Needs Improvement") -> Needs Improvement | AN18: {=_xlfn.IFS(N18<10000,"Low",N18<30000,"Medium",N18>=30000,"High")} -> Low | AO18: =IF(AND(N18>=30000,P18>=10000),"Yes","No") -> No | AP18: =IF(OR(S18="Online",S18="Marketplace"),"Yes","No") -> Yes | AQ18: =IFERROR(P18/N18,"No Error") -> 0.22635882 | AX18: =IF(P18>=20000,"Excellent",IF(P18>=10000,"Good",IF(P18>=5000,"Average","Low"))) -> Low
... A56: ORD10742 | B56: 45383 | C56: CUST1041 | D56: Pooja Jain | E56: Small Business | F56: Hyderabad | G56: Telangana | H56: South | I56: Electronics | J56: Smartphone | K56: 2 | L56: 50000 | M56: 0 | N56: 100000 | O56: 60675.91 | P56: 39324.09 | Q56: 39.32 | R56: Cash | S56: Online | T56: Rohit | U56: January | V56: 2024 | W56: Thursday | X56: 7 | Y56: 45597 | Z56: Completed | AA56: VIP | AB56: High | AC56: Yes | AD56: 4 | AE56: Pooja | AF56: Jain | AM56: =IF(Q56>=30,"Good","Needs Improvement") -> Good | AN56: {=_xlfn.IFS(N56<10000,"Low",N56<30000,"Medium",N56>=30000,"High")} -> High | AO56: =IF(AND(N56>=30000,P56>=10000),"Yes","No") -> Yes | AP56: =IF(OR(S56="Online",S56="Marketplace"),"Yes","No") -> Yes | AQ56: =IFERROR(P56/N56,"No Error") -> 0.3932409 | AX56: =IF(P56>=20000,"Excellent",IF(P56>=10000,"Good",IF(P56>=5000,"Average","Low"))) -> Excellent
A57: ORD10055 | B57: 45384 | C57: CUST1047 | D57: Priya Jain | E57: Small Business | F57: Pune | G57: Maharashtra | H57: West | I57: Furniture | J57: Office Chair | K57: 1 | L57: 6000 | M57: 0.15 | N57: 5100 | O57: 3813.46 | P57: 1286.54 | Q57: 25.23 | R57: Debit Card | S57: Online | T57: Pooja | U57: February | V57: 2024 | W57: Sunday | X57: 10 | Y57: 14-02-2024 | Z57: Completed | AA57: VIP | AB57: Medium | AC57: No | AD57: 2 | AE57: Priya | AF57: Jain | AM57: =IF(Q57>=30,"Good","Needs Improvement") -> Needs Improvement | AN57: {=_xlfn.IFS(N57<10000,"Low",N57<30000,"Medium",N57>=30000,"High")} -> Low | AO57: =IF(AND(N57>=30000,P57>=10000),"Yes","No") -> No | AP57: =IF(OR(S57="Online",S57="Marketplace"),"Yes","No") -> Yes | AQ57: =IFERROR(P57/N57,"No Error") -> 0.25226275 | AX57: =IF(P57>=20000,"Excellent",IF(P57>=10000,"Good",IF(P57>=5000,"Average","Low"))) -> Low
A58: ORD10176 | B58: 45384 | C58: CUST1054 | D58: Aditya Jain | E58: Consumer | F58: Jaipur | G58: Rajasthan | H58: West | I58: Accessories | J58: Watch | K58: 3 | L58: 2000 | M58: 0 | N58: 6000 | O58: 3816.32 | P58: 2183.68 | Q58: 36.39 | R58: Debit Card | S58: Marketplace | T58: Neeraj | U58: February | V58: 2024 | W58: Sunday | X58: 5 | Y58: 45537 | Z58: Completed | AA58: VIP | AB58: Low | AC58: No | AD58: 5 | AE58: Aditya | AF58: Jain | AM58: =IF(Q58>=30,"Good","Needs Improvement") -> Good | AN58: {=_xlfn.IFS(N58<10000,"Low",N58<30000,"Medium",N58>=30000,"High")} -> Low | AO58: =IF(AND(N58>=30000,P58>=10000),"Yes","No") -> No | AP58: =IF(OR(S58="Online",S58="Marketplace"),"Yes","No") -> Yes | AQ58: =IFERROR(P58/N58,"No Error") -> 0.36394667 | AX58: =IF(P58>=20000,"Excellent",IF(P58>=10000,"Good",IF(P58>=5000,"Average","Low"))) -> Low
A59: ORD10575 | B59: 45384 | C59: CUST1182 | D59: Rohan Malhotra | E59: Small Business | F59: Mumbai | G59: Maharashtra | H59: West | I59: Accessories | J59: Sunglasses | K59: 1 | L59: 3000 | M59: 0.1 | N59: 2700 | O59: 1516.08 | P59: 1183.92 | Q59: 43.85 | R59: UPI | S59: Online | T59: Pooja | U59: February | V59: 2024 | W59: Sunday | X59: 10 | Y59: 14-02-2024 | Z59: Pending | AA59: Returning | AB59: High | AC59: Yes | AD59: 3 | AE59: Rohan | AF59: Malhotra | AM59: =IF(Q59>=30,"Good","Needs Improvement") -> Good | AN59: {=_xlfn.IFS(N59<10000,"Low",N59<30000,"Medium",N59>=30000,"High")} -> Low | AO59: =IF(AND(N59>=30000,P59>=10000),"Yes","No") -> No | AP59: =IF(OR(S59="Online",S59="Marketplace"),"Yes","No") -> Yes | AQ59: =IFERROR(P59/N59,"No Error") -> 0.43848889 | AX59: =IF(P59>=20000,"Excellent",IF(P59>=10000,"Good",IF(P59>=5000,"Average","Low"))) -> Low
A60: ORD10075 | B60: 45385 | C60: CUST1176 | D60: Aditya Kapoor | E60: Small Business | F60: Hyderabad | G60: Telangana | H60: South | I60: Office Supplies | J60: Stapler | K60: 8 | L60: 800 | M60: 0.05 | N60: 6080 | O60: 4675.28 | P60: 1404.72 | Q60: 23.1 | R60: Credit Card | S60: Online | T60: Rohit | U60: March | V60: 2024 | W60: Monday | X60: 8 | Y60: 45629 | Z60: Completed | AA60: Returning | AB60: High | AC60: Yes | AD60: 3 | AE60: Aditya | AF60: Kapoor | AM60: =IF(Q60>=30,"Good","Needs Improvement") -> Needs Improvement | AN60: {=_xlfn.IFS(N60<10000,"Low",N60<30000,"Medium",N60>=30000,"High")} -> Low | AO60: =IF(AND(N60>=30000,P60>=10000),"Yes","No") -> No | AP60: =IF(OR(S60="Online",S60="Marketplace"),"Yes","No") -> Yes | AQ60: =IFERROR(P60/N60,"No Error") -> 0.23103947 | AX60: =IF(P60>=20000,"Excellent",IF(P60>=10000,"Good",IF(P60>=5000,"Average","Low"))) -> Low
A61: ORD10521 | B61: 45386 | C61: CUST1065 | D61: Rahul Mehta | E61: Small Business | F61: Ahmedabad | G61: Gujarat | H61: North | I61: Office Supplies | J61: Printer Paper | K61: 7 | L61: 200 | M61: 0.1 | N61: 1260 | O61: 1025.69 | P61: 234.31 | Q61: 18.6 | R61: Debit Card | S61: Retail Store | T61: Pooja | U61: April | V61: 2024 | W61: Thursday | X61: 9 | Y61: 13-04-2024 | Z61: Pending | AA61: VIP | AB61: High | AC61: Yes | AD61: 4 | AE61: Rahul | AF61: Mehta | AM61: =IF(Q61>=30,"Good","Needs Improvement") -> Needs Improvement | AN61: {=_xlfn.IFS(N61<10000,"Low",N61<30000,"Medium",N61>=30000,"High")} -> Low | AO61: =IF(AND(N61>=30000,P61>=10000),"Yes","No") -> No | AP61: =IF(OR(S61="Online",S61="Marketplace"),"Yes","No") -> No | AQ61: =IFERROR(P61/N61,"No Error") -> 0.18596032 | AX61: =IF(P61>=20000,"Excellent",IF(P61>=10000,"Good",IF(P61>=5000,"Average","Low"))) -> Low
A62: ORD10797 | B62: 45386 | C62: CUST1041 | D62: Meera Saxena | E62: Corporate | F62: Kolkata | G62: West Bengal | H62: West | I62: Office Supplies | J62: Notebook | K62: 4 | L62: 100 | M62: 0.05 | N62: 380 | O62: 214.14 | P62: 165.86 | Q62: 43.65 | R62: Debit Card | S62: Retail Store | T62: Pooja | U62: April | V62: 2024 | W62: Thursday | X62: 10 | Y62: 14-04-2024 | Z62: Cancelled | AA62: Returning | AB62: Medium | AC62: Yes | AD62: 2 | AE62: Meera | AF62: Saxena | AM62: =IF(Q62>=30,"Good","Needs Improvement") -> Good | AN62: {=_xlfn.IFS(N62<10000,"Low",N62<30000,"Medium",N62>=30000,"High")} -> Low | AO62: =IF(AND(N62>=30000,P62>=10000),"Yes","No") -> No | AP62: =IF(OR(S62="Online",S62="Marketplace"),"Yes","No") -> No | AQ62: =IFERROR(P62/N62,"No Error") -> 0.43647368 | AX62: =IF(P62>=20000,"Excellent",IF(P62>=10000,"Good",IF(P62>=5000,"Average","Low"))) -> Low
A63: ORD10798 | B63: 45386 | C63: CUST1091 | D63: Priya Kapoor | E63: Corporate | F63: Kolkata | G63: West Bengal | H63: West | I63: Office Supplies | J63: Printer Paper | K63: 9 | L63: 100 | M63: 0.05 | N63: 855 | O63: 602.44 | P63: 252.56 | Q63: 29.54 | R63: Debit Card | S63: Online | T63: Amit | U63: April | V63: 2024 | W63: Thursday | X63: 10 | Y63: 14-04-2024 | Z63: Completed | AA63: New | AB63: High | AC63: Yes | AD63: 1 | AE63: Priya | AF63: Kapoor | AM63: =IF(Q63>=30,"Good","Needs Improvement") -> Needs Improvement | AN63: {=_xlfn.IFS(N63<10000,"Low",N63<30000,"Medium",N63>=30000,"High")} -> Low | AO63: =IF(AND(N63>=30000,P63>=10000),"Yes","No") -> No | AP63: =IF(OR(S63="Online",S63="Marketplace"),"Yes","No") -> Yes | AQ63: =IFERROR(P63/N63,"No Error") -> 0.29539181 | AX63: =IF(P63>=20000,"Excellent",IF(P63>=10000,"Good",IF(P63>=5000,"Average","Low"))) -> Low
A64: ORD10825 | B64: 45386 | C64: CUST1097 | D64: Aditi Kumar | E64: Small Business | F64: Mumbai | G64: Maharashtra | H64: North | I64: Clothing | J64: T-Shirt | K64: 5 | L64: 700 | M64: 0.1 | N64: 3150 | O64: 2062.39 | P64: 1087.61 | Q64: 34.53 | R64: Net Banking | S64: Online | T64: Neeraj | U64: April | V64: 2024 | W64: Thursday | X64: 6 | Y64: 45569 | Z64: Completed | AA64: New | AB64: Low | AC64: No | AD64: 2 | AE64: Aditi | AF64: Kumar | AM64: =IF(Q64>=30,"Good","Needs Improvement") -> Good | AN64: {=_xlfn.IFS(N64<10000,"Low",N64<30000,"Medium",N64>=30000,"High")} -> Low | AO64: =IF(AND(N64>=30000,P64>=10000),"Yes","No") -> No | AP64: =IF(OR(S64="Online",S64="Marketplace"),"Yes","No") -> Yes | AQ64: =IFERROR(P64/N64,"No Error") -> 0.34527302 | AX64: =IF(P64>=20000,"Excellent",IF(P64>=10000,"Good",IF(P64>=5000,"Average","Low"))) -> Low
A65: ORD10868 | B65: 45386 | C65: CUST1151 | D65: Rohan Kapoor | E65: Small Business | F65: Jaipur | G65: Rajasthan | H65: West | I65: Office Supplies | J65: Pen Set | K65: 6 | L65: 500 | M65: 0 | N65: 3000 | O65: 2213.29 | P65: 786.71 | Q65: 26.22 | R65: Credit Card | S65: Retail Store | T65: Amit | U65: April | V65: 2024 | W65: Thursday | X65: 5 | Y65: 45539 | Z65: Completed | AA65: Returning | AB65: Low | AC65: No | AD65: 4 | AE65: Rohan | AF65: Kapoor | AM65: =IF(Q65>=30,"Good","Needs Improvement") -> Needs Improvement | AN65: {=_xlfn.IFS(N65<10000,"Low",N65<30000,"Medium",N65>=30000,"High")} -> Low | AO65: =IF(AND(N65>=30000,P65>=10000),"Yes","No") -> No | AP65: =IF(OR(S65="Online",S65="Marketplace"),"Yes","No") -> No | AQ65: =IFERROR(P65/N65,"No Error") -> 0.26223667 | AX65: =IF(P65>=20000,"Excellent",IF(P65>=10000,"Good",IF(P65>=5000,"Average","Low"))) -> Low
A66: ORD10202 | B66: 45389 | C66: CUST1314 | D66: Aarav Chopra | E66: Small Business | F66: Mumbai | G66: Maharashtra | H66: South | I66: Clothing | J66: T-Shirt | K66: 8 | L66: 3500 | M66: 0.15 | N66: 23800 | O66: 18096.91 | P66: 5703.09 | Q66: 23.96 | R66: Cash | S66: Retail Store | T66: Neeraj | U66: July | V66: 2024 | W66: Thursday | X66: 10 | Y66: 14-07-2024 | Z66: Pending | AA66: Returning | AB66: Medium | AC66: Yes | AD66: 1 | AE66: Aarav | AF66: Chopra | AM66: =IF(Q66>=30,"Good","Needs Improvement") -> Needs Improvement | AN66: {=_xlfn.IFS(N66<10000,"Low",N66<30000,"Medium",N66>=30000,"High")} -> Medium | AO66: =IF(AND(N66>=30000,P66>=10000),"Yes","No") -> No | AP66: =IF(OR(S66="Online",S66="Marketplace"),"Yes","No") -> No | AQ66: =IFERROR(P66/N66,"No Error") -> 0.23962563 | AX66: =IF(P66>=20000,"Excellent",IF(P66>=10000,"Good",IF(P66>=5000,"Average","Low"))) -> Average
A67: ORD10196 | B67: 45390 | C67: CUST1064 | D67: Sneha Yadav | E67: Small Business | F67: Bengaluru | G67: Karnataka | H67: North | I67: Clothing | J67: Shirt | K67: 4 | L67: 1200 | M67: 0.05 | N67: 4560 | O67: 3129.3 | P67: 1430.7 | Q67: 31.38 | R67: Cash | S67: Marketplace | T67: Sneha | U67: August | V67: 2024 | W67: Sunday | X67: 1 | Y67: 45420 | Z67: Cancelled | AA67: VIP | AB67: High | AC67: Yes | AD67: 5 | AE67: Sneha | AF67: Yadav | AM67: =IF(Q67>=30,"Good","Needs Improvement") -> Good | AN67: {=_xlfn.IFS(N67<10000,"Low",N67<30000,"Medium",N67>=30000,"High")} -> Low | AO67: =IF(AND(N67>=30000,P67>=10000),"Yes","No") -> No | AP67: =IF(OR(S67="Online",S67="Marketplace"),"Yes","No") -> Yes | AQ67: =IFERROR(P67/N67,"No Error") -> 0.31375 | AX67: =IF(P67>=20000,"Excellent",IF(P67>=10000,"Good",IF(P67>=5000,"Average","Low"))) -> Low
A68: ORD10597 | B68: 45390 | C68: CUST1261 | D68: Nisha Yadav | E68: Corporate | F68: Pune | G68: Maharashtra | H68: South | I68: Furniture | J68: Table | K68: 1 | L68: 2500 | M68: 0.2 | N68: 2000 | O68: 1486.51 | P68: 513.49 | Q68: 25.67 | R68: Cash | S68: Marketplace | T68: Amit | U68: August | V68: 2024 | W68: Sunday | X68: 6 | Y68: 45573 | Z68: Cancelled | AA68: VIP | AB68: High | AC68: Yes | AD68: 4 | AE68: Nisha | AF68: Yadav | AM68: =IF(Q68>=30,"Good","Needs Improvement") -> Needs Improvement | AN68: {=_xlfn.IFS(N68<10000,"Low",N68<30000,"Medium",N68>=30000,"High")} -> Low | AO68: =IF(AND(N68>=30000,P68>=10000),"Yes","No") -> No | AP68: =IF(OR(S68="Online",S68="Marketplace"),"Yes","No") -> Yes | AQ68: =IFERROR(P68/N68,"No Error") -> 0.256745 | AX68: =IF(P68>=20000,"Excellent",IF(P68>=10000,"Good",IF(P68>=5000,"Average","Low"))) -> Low
A69: ORD10800 | B69: 45391 | C69: CUST1143 | D69: Riya Singh | E69: Corporate | F69: Bengaluru | G69: Karnataka | H69: South | I69: Furniture | J69: Office Chair | K69: 8 | L69: 4000 | M69: 0.05 | N69: 30400 | O69: 21430.28 | P69: 8969.72 | Q69: 29.51 | R69: Credit Card | S69: Marketplace | T69: Rahul | U69: September | V69: 2024 | W69: Wednesday | X69: 10 | Y69: 14-09-2024 | Z69: Completed | AA69: New | AB69: High | AC69: Yes | AD69: 1 | AE69: Riya | AF69: Singh | AM69: =IF(Q69>=30,"Good","Needs Improvement") -> Needs Improvement | AN69: {=_xlfn.IFS(N69<10000,"Low",N69<30000,"Medium",N69>=30000,"High")} -> High | AO69: =IF(AND(N69>=30000,P69>=10000),"Yes","No") -> No | AP69: =IF(OR(S69="Online",S69="Marketplace"),"Yes","No") -> Yes | AQ69: =IFERROR(P69/N69,"No Error") -> 0.29505658 | AX69: =IF(P69>=20000,"Excellent",IF(P69>=10000,"Good",IF(P69>=5000,"Average","Low"))) -> Average
A70: ORD10253 | B70: 45414 | C70: CUST1240 | D70: Aditi Saxena | E70: Corporate | F70: Jaipur | G70: Rajasthan | H70: West | I70: Furniture | J70: Desk | K70: 9 | L70: 4000 | M70: 0 | N70: 36000 | O70: 28200.42 | P70: 7799.58 | Q70: 21.67 | R70: Debit Card | S70: Marketplace | T70: Anjali | U70: February | V70: 2024 | W70: Monday | X70: 6 | Y70: 45598 | Z70: Completed | AA70: New | AB70: High | AC70: No | AD70: 5 | AE70: Aditi | AF70: Saxena | AM70: =IF(Q70>=30,"Good","Needs Improvement") -> Needs Improvement | AN70: {=_xlfn.IFS(N70<10000,"Low",N70<30000,"Medium",N70>=30000,"High")} -> High | AO70: =IF(AND(N70>=30000,P70>=10000),"Yes","No") -> No | AP70: =IF(OR(S70="Online",S70="Marketplace"),"Yes","No") -> Yes | AQ70: =IFERROR(P70/N70,"No Error") -> 0.216655 | AX70: =IF(P70>=20000,"Excellent",IF(P70>=10000,"Good",IF(P70>=5000,"Average","Low"))) -> Average
A71: ORD10219 | B71: 45415 | C71: CUST1038 | D71: Sneha Saxena | E71: Small Business | F71: Delhi | G71: Delhi | H71: North | I71: Clothing | J71: Shirt | K71: 9 | L71: 700 | M71: 0.2 | N71: 5040 | O71: 3725.76 | P71: 1314.24 | Q71: 26.08 | R71: UPI | S71: Marketplace | T71: Sneha | U71: March | V71: 2024 | W71: Tuesday | X71: 10 | Y71: 15-03-2024 | Z71: Completed | AA71: VIP | AB71: Low | AC71: No | AD71: 4 | AE71: Sneha | AF71: Saxena | AM71: =IF(Q71>=30,"Good","Needs Improvement") -> Needs Improvement | AN71: {=_xlfn.IFS(N71<10000,"Low",N71<30000,"Medium",N71>=30000,"High")} -> Low | AO71: =IF(AND(N71>=30000,P71>=10000),"Yes","No") -> No | AP71: =IF(OR(S71="Online",S71="Marketplace"),"Yes","No") -> Yes | AQ71: =IFERROR(P71/N71,"No Error") -> 0.2607619 | AX71: =IF(P71>=20000,"Excellent",IF(P71>=10000,"Good",IF(P71>=5000,"Average","Low"))) -> Low
A72: ORD10683 | B72: 45416 | C72: CUST1265 | D72: Arjun Gupta | E72: Consumer | F72: Kolkata | G72: West Bengal | H72: North | I72: Furniture | J72: Desk | K72: 7 | L72: 15000 | M72: 0 | N72: 105000 | O72: 83641.58 | P72: 21358.42 | Q72: 20.34 | R72: Cash | S72: Marketplace | T72: Manish | U72: April | V72: 2024 | W72: Friday | X72: 3 | Y72: 45508 | Z72: Cancelled | AA72: Returning | AB72: High | AC72: No | AD72: 4 | AE72: Arjun | AF72: Gupta | AM72: =IF(Q72>=30,"Good","Needs Improvement") -> Needs Improvement | AN72: {=_xlfn.IFS(N72<10000,"Low",N72<30000,"Medium",N72>=30000,"High")} -> High | AO72: =IF(AND(N72>=30000,P72>=10000),"Yes","No") -> Yes | AP72: =IF(OR(S72="Online",S72="Marketplace"),"Yes","No") -> Yes | AQ72: =IFERROR(P72/N72,"No Error") -> 0.20341352 | AX72: =IF(P72>=20000,"Excellent",IF(P72>=10000,"Good",IF(P72>=5000,"Average","Low"))) -> Excellent
A73: ORD10851 | B73: 45416 | C73: CUST1070 | D73: Karan Sharma | E73: Corporate | F73: Ahmedabad | G73: Gujarat | H73: West | I73: Accessories | J73: Backpack | K73: 6 | L73: 3000 | M73: 0.2 | N73: 14400 | O73: 9211.11 | P73: 5188.89 | Q73: 36.03 | R73: Debit Card | S73: Online | T73: Rahul | U73: April | V73: 2024 | W73: Friday | X73: 5 | Y73: 45569 | Z73: Completed | AA73: VIP | AB73: High | AC73: Yes | AD73: 5 | AE73: Karan | AF73: Sharma | AM73: =IF(Q73>=30,"Good","Needs Improvement") -> Good | AN73: {=_xlfn.IFS(N73<10000,"Low",N73<30000,"Medium",N73>=30000,"High")} -> Medium | AO73: =IF(AND(N73>=30000,P73>=10000),"Yes","No") -> No | AP73: =IF(OR(S73="Online",S73="Marketplace"),"Yes","No") -> Yes | AQ73: =IFERROR(P73/N73,"No Error") -> 0.36033958 | AX73: =IF(P73>=20000,"Excellent",IF(P73>=10000,"Good",IF(P73>=5000,"Average","Low"))) -> Average
A74: ORD10917 | B74: 45416 | C74: CUST1086 | D74: Nisha Yadav | E74: Corporate | F74: Jaipur | G74: Rajasthan | H74: North | I74: Electronics | J74: Tablet | K74: 3 | L74: 12000 | M74: 0.2 | N74: 28800 | O74: 20839.28 | P74: 7960.72 | Q74: 27.64 | R74: Credit Card | S74: Retail Store | T74: Rahul | U74: April | V74: 2024 | W74: Friday | X74: 1 | Y74: 45447 | Z74: Completed | AA74: Returning | AB74: Medium | AC74: Yes | AD74: 1 | AE74: Nisha | AF74: Yadav | AM74: =IF(Q74>=30,"Good","Needs Improvement") -> Needs Improvement | AN74: {=_xlfn.IFS(N74<10000,"Low",N74<30000,"Medium",N74>=30000,"High")} -> Medium | AO74: =IF(AND(N74>=30000,P74>=10000),"Yes","No") -> No | AP74: =IF(OR(S74="Online",S74="Marketplace"),"Yes","No") -> No | AQ74: =IFERROR(P74/N74,"No Error") -> 0.27641389 | AX74: =IF(P74>=20000,"Excellent",IF(P74>=10000,"Good",IF(P74>=5000,"Average","Low"))) -> Average
A75: ORD10526 | B75: 45418 | C75: CUST1008 | D75: Rohan Agarwal | E75: Corporate | F75: Kolkata | G75: West Bengal | H75: North | I75: Furniture | J75: Desk | K75: 10 | L75: 15000 | M75: 0 | N75: 150000 | O75: 86444.94 | P75: 63555.06 | Q75: 42.37 | R75: Cash | S75: Online | T75: Rohit | U75: June | V75: 2024 | W75: Wednesday | X75: 10 | Y75: 15-06-2024 | Z75: Pending | AA75: Returning | AB75: Low | AC75: No | AD75: 2 | AE75: Rohan | AF75: Agarwal | AM75: =IF(Q75>=30,"Good","Needs Improvement") -> Good | AN75: {=_xlfn.IFS(N75<10000,"Low",N75<30000,"Medium",N75>=30000,"High")} -> High | AO75: =IF(AND(N75>=30000,P75>=10000),"Yes","No") -> Yes | AP75: =IF(OR(S75="Online",S75="Marketplace"),"Yes","No") -> Yes | AQ75: =IFERROR(P75/N75,"No Error") -> 0.4237004 | AX75: =IF(P75>=20000,"Excellent",IF(P75>=10000,"Good",IF(P75>=5000,"Average","Low"))) -> Excellent
A76: ORD10670 | B76: 45419 | C76: CUST1261 | D76: Kavya Malhotra | E76: Consumer | F76: Pune | G76: Maharashtra | H76: South | I76: Accessories | J76: Belt | K76: 5 | L76: 2000 | M76: 0 | N76: 10000 | O76: 6361.86 | P76: 3638.14 | Q76: 36.38 | R76: Credit Card | S76: Retail Store | T76: Sneha | U76: July | V76: 2024 | W76: Friday | X76: 8 | Y76: 13-07-2024 | Z76: Completed | AA76: New | AB76: Medium | AC76: No | AD76: 5 | AE76: Kavya | AF76: Malhotra | AM76: =IF(Q76>=30,"Good","Needs Improvement") -> Good | AN76: {=_xlfn.IFS(N76<10000,"Low",N76<30000,"Medium",N76>=30000,"High")} -> Medium | AO76: =IF(AND(N76>=30000,P76>=10000),"Yes","No") -> No | AP76: =IF(OR(S76="Online",S76="Marketplace"),"Yes","No") -> No | AQ76: =IFERROR(P76/N76,"No Error") -> 0.363814 | AX76: =IF(P76>=20000,"Excellent",IF(P76>=10000,"Good",IF(P76>=5000,"Average","Low"))) -> Low
A77: ORD10911 | B77: 45419 | C77: CUST1291 | D77: Simran Singh | E77: Small Business | F77: Hyderabad | G77: Telangana | H77: West | I77: Accessories | J77: Belt | K77: 3 | L77: 500 | M77: 0.1 | N77: 1350 | O77: 952.69 | P77: 397.31 | Q77: 29.43 | R77: Debit Card | S77: Online | T77: Kavita | U77: July | V77: 2024 | W77: Friday | X77: 3 | Y77: 45511 | Z77: Completed | AA77: Returning | AB77: High | AC77: Yes | AD77: 3 | AE77: Simran | AF77: Singh | AM77: =IF(Q77>=30,"Good","Needs Improvement") -> Needs Improvement | AN77: {=_xlfn.IFS(N77<10000,"Low",N77<30000,"Medium",N77>=30000,"High")} -> Low | AO77: =IF(AND(N77>=30000,P77>=10000),"Yes","No") -> No | AP77: =IF(OR(S77="Online",S77="Marketplace"),"Yes","No") -> Yes | AQ77: =IFERROR(P77/N77,"No Error") -> 0.2943037 | AX77: =IF(P77>=20000,"Excellent",IF(P77>=10000,"Good",IF(P77>=5000,"Average","Low"))) -> Low
A78: ORD10512 | B78: 45424 | C78: CUST1279 | D78: Ananya Mishra | E78: Small Business | F78: Bengaluru | G78: Karnataka | H78: North | I78: Clothing | J78: T-Shirt | K78: 8 | L78: 1200 | M78: 0.1 | N78: 8640 | O78: 5320.76 | P78: 3319.24 | Q78: 38.42 | R78: Credit Card | S78: Online | T78: Neeraj | U78: December | V78: 2024 | W78: Thursday | X78: 8 | Y78: 13-12-2024 | Z78: Completed | AA78: VIP | AB78: Medium | AC78: Yes | AD78: 5 | AE78: Ananya | AF78: Mishra | AM78: =IF(Q78>=30,"Good","Needs Improvement") -> Good | AN78: {=_xlfn.IFS(N78<10000,"Low",N78<30000,"Medium",N78>=30000,"High")} -> Low | AO78: =IF(AND(N78>=30000,P78>=10000),"Yes","No") -> No | AP78: =IF(OR(S78="Online",S78="Marketplace"),"Yes","No") -> Yes | AQ78: =IFERROR(P78/N78,"No Error") -> 0.3841713 | AX78: =IF(P78>=20000,"Excellent",IF(P78>=10000,"Good",IF(P78>=5000,"Average","Low"))) -> Low
A79: ORD10914 | B79: 45424 | C79: CUST1270 | D79: Kavya Yadav | E79: Consumer | F79: Lucknow | G79: Uttar Pradesh | H79: South | I79: Furniture | J79: Sofa | K79: 2 | L79: 4000 | M79: 0 | N79: 8000 | O79: 5411.98 | P79: 2588.02 | Q79: 32.35 | R79: Cash | S79: Marketplace | T79: Vikas | U79: December | V79: 2024 | W79: Thursday | X79: 4 | Y79: 45547 | Z79: Cancelled | AA79: New | AB79: High | AC79: Yes | AD79: 2 | AE79: Kavya | AF79: Yadav | AM79: =IF(Q79>=30,"Good","Needs Improvement") -> Good | AN79: {=_xlfn.IFS(N79<10000,"Low",N79<30000,"Medium",N79>=30000,"High")} -> Low | AO79: =IF(AND(N79>=30000,P79>=10000),"Yes","No") -> No | AP79: =IF(OR(S79="Online",S79="Marketplace"),"Yes","No") -> Yes | AQ79: =IFERROR(P79/N79,"No Error") -> 0.3235025 | AX79: =IF(P79>=20000,"Excellent",IF(P79>=10000,"Good",IF(P79>=5000,"Average","Low"))) -> Low
A80: ORD10335 | B80: 45444 | C80: CUST1241 | D80: Meera Sharma | E80: Corporate | F80: Kolkata | G80: West Bengal | H80: West | I80: Accessories | J80: Watch | K80: 10 | L80: 800 | M80: 0.2 | N80: 6400 | O80: 3589.22 | P80: 2810.78 | Q80: 43.92 | R80: Cash | S80: Marketplace | T80: Neeraj | U80: January | V80: 2024 | W80: Saturday | X80: 7 | Y80: 13-01-2024 | Z80: Completed | AA80: Returning | AB80: Medium | AC80: Yes | AD80: 1 | AE80: Meera | AF80: Sharma | AM80: =IF(Q80>=30,"Good","Needs Improvement") -> Good | AN80: {=_xlfn.IFS(N80<10000,"Low",N80<30000,"Medium",N80>=30000,"High")} -> Low | AO80: =IF(AND(N80>=30000,P80>=10000),"Yes","No") -> No | AP80: =IF(OR(S80="Online",S80="Marketplace"),"Yes","No") -> Yes | AQ80: =IFERROR(P80/N80,"No Error") -> 0.43918438 | AX80: =IF(P80>=20000,"Excellent",IF(P80>=10000,"Good",IF(P80>=5000,"Average","Low"))) -> Low
A81: ORD10673 | B81: 45444 | C81: CUST1182 | D81: Rohan Malhotra | E81: Corporate | F81: Jaipur | G81: Rajasthan | H81: North | I81: Office Supplies | J81: File Folder | K81: 10 | L81: 500 | M81: 0.15 | N81: 4250 | O81: 3449.06 | P81: 800.94 | Q81: 18.85 | R81: Debit Card | S81: Online | T81: Sneha | U81: January | V81: 2024 | W81: Saturday | X81: 7 | Y81: 13-01-2024 | Z81: Completed | AA81: Returning | AB81: Medium | AC81: Yes | AD81: 3 | AE81: Rohan | AF81: Malhotra | AM81: =IF(Q81>=30,"Good","Needs Improvement") -> Needs Improvement | AN81: {=_xlfn.IFS(N81<10000,"Low",N81<30000,"Medium",N81>=30000,"High")} -> Low | AO81: =IF(AND(N81>=30000,P81>=10000),"Yes","No") -> No | AP81: =IF(OR(S81="Online",S81="Marketplace"),"Yes","No") -> Yes | AQ81: =IFERROR(P81/N81,"No Error") -> 0.18845647 | AX81: =IF(P81>=20000,"Excellent",IF(P81>=10000,"Good",IF(P81>=5000,"Average","Low"))) -> Low
A82: ORD10997 | B82: 45444 | C82: CUST1262 | D82: Ananya Singh | E82: Consumer | F82: Lucknow | G82: Uttar Pradesh | H82: South | I82: Electronics | J82: Headphones | K82: 1 | L82: 15000 | M82: 0.05 | N82: 14250 | O82: 11352.29 | P82: 2897.71 | Q82: 20.33 | R82: Credit Card | S82: Online | T82: Kavita | U82: January | V82: 2024 | W82: Saturday | X82: 9 | Y82: 15-01-2024 | Z82: Cancelled | AA82: Returning | AB82: Medium | AC82: Yes | AD82: 2 | AE82: Ananya | AF82: Singh | AM82: =IF(Q82>=30,"Good","Needs Improvement") -> Needs Improvement | AN82: {=_xlfn.IFS(N82<10000,"Low",N82<30000,"Medium",N82>=30000,"High")} -> Medium | AO82: =IF(AND(N82>=30000,P82>=10000),"Yes","No") -> No | AP82: =IF(OR(S82="Online",S82="Marketplace"),"Yes","No") -> Yes | AQ82: =IFERROR(P82/N82,"No Error") -> 0.20334807 | AX82: =IF(P82>=20000,"Excellent",IF(P82>=10000,"Good",IF(P82>=5000,"Average","Low"))) -> Low
A83: ORD10724 | B83: 45445 | C83: CUST1118 | D83: Vivaan Chopra | E83: Corporate | F83: Mumbai | G83: Maharashtra | H83: South | I83: Accessories | J83: Sunglasses | K83: 4 | L83: 800 | M83: 0.2 | N83: 2560 | O83: 1483.58 | P83: 1076.42 | Q83: 42.05 | R83: Credit Card | S83: Marketplace | T83: Neeraj | U83: February | V83: 2024 | W83: Tuesday | X83: 8 | Y83: 14-02-2024 | Z83: Pending | AA83: New | AB83: Medium | AC83: No | AD83: 4 | AE83: Vivaan | AF83: Chopra | AM83: =IF(Q83>=30,"Good","Needs Improvement") -> Good | AN83: {=_xlfn.IFS(N83<10000,"Low",N83<30000,"Medium",N83>=30000,"High")} -> Low | AO83: =IF(AND(N83>=30000,P83>=10000),"Yes","No") -> No | AP83: =IF(OR(S83="Online",S83="Marketplace"),"Yes","No") -> Yes | AQ83: =IFERROR(P83/N83,"No Error") -> 0.42047656 | AX83: =IF(P83>=20000,"Excellent",IF(P83>=10000,"Good",IF(P83>=5000,"Average","Low"))) -> Low
A84: ORD10482 | B84: 45446 | C84: CUST1011 | D84: Pooja Kapoor | E84: Small Business | F84: Kolkata | G84: West Bengal | H84: West | I84: Office Supplies | J84: Stapler | K84: 3 | L84: 100 | M84: 0.1 | N84: 270 | O84: 178.05 | P84: 91.95 | Q84: 34.06 | R84: Credit Card | S84: Marketplace | T84: Manish | U84: March | V84: 2024 | W84: Wednesday | X84: 9 | Y84: 15-03-2024 | Z84: Completed | AA84: VIP | AB84: High | AC84: Yes | AD84: 2 | AE84: Pooja | AF84: Kapoor | AM84: =IF(Q84>=30,"Good","Needs Improvement") -> Good | AN84: {=_xlfn.IFS(N84<10000,"Low",N84<30000,"Medium",N84>=30000,"High")} -> Low | AO84: =IF(AND(N84>=30000,P84>=10000),"Yes","No") -> No | AP84: =IF(OR(S84="Online",S84="Marketplace"),"Yes","No") -> Yes | AQ84: =IFERROR(P84/N84,"No Error") -> 0.34055556 | AX84: =IF(P84>=20000,"Excellent",IF(P84>=10000,"Good",IF(P84>=5000,"Average","Low"))) -> Low
A85: ORD10578 | B85: 45446 | C85: CUST1020 | D85: Aditya Malhotra | E85: Corporate | F85: Hyderabad | G85: Telangana | H85: North | I85: Furniture | J85: Office Chair | K85: 3 | L85: 9000 | M85: 0.15 | N85: 22950 | O85: 14174.62 | P85: 8775.38 | Q85: 38.24 | R85: Debit Card | S85: Retail Store | T85: Neeraj | U85: March | V85: 2024 | W85: Wednesday | X85: 1 | Y85: 45476 | Z85: Cancelled | AA85: VIP | AB85: Medium | AC85: No | AD85: 2 | AE85: Aditya | AF85: Malhotra | AM85: =IF(Q85>=30,"Good","Needs Improvement") -> Good | AN85: {=_xlfn.IFS(N85<10000,"Low",N85<30000,"Medium",N85>=30000,"High")} -> Medium | AO85: =IF(AND(N85>=30000,P85>=10000),"Yes","No") -> No | AP85: =IF(OR(S85="Online",S85="Marketplace"),"Yes","No") -> No | AQ85: =IFERROR(P85/N85,"No Error") -> 0.3823695 | AX85: =IF(P85>=20000,"Excellent",IF(P85>=10000,"Good",IF(P85>=5000,"Average","Low"))) -> Average
A86: ORD10012 | B86: 45447 | C86: CUST1211 | D86: Riya Chopra | E86: Small Business | F86: Lucknow | G86: Uttar Pradesh | H86: North | I86: Clothing | J86: Jeans | K86: 8 | L86: 2500 | M86: 0.05 | N86: 19000 | O86: 12267.55 | P86: 6732.45 | Q86: 35.43 | R86: Credit Card | S86: Online | T86: Kavita | U86: April | V86: 2024 | W86: Saturday | X86: 2 | Y86: 45508 | Z86: Pending | AA86: VIP | AB86: Medium | AC86: Yes | AD86: 2 | AE86: Riya | AF86: Chopra | AM86: =IF(Q86>=30,"Good","Needs Improvement") -> Good | AN86: {=_xlfn.IFS(N86<10000,"Low",N86<30000,"Medium",N86>=30000,"High")} -> Medium | AO86: =IF(AND(N86>=30000,P86>=10000),"Yes","No") -> No | AP86: =IF(OR(S86="Online",S86="Marketplace"),"Yes","No") -> Yes | AQ86: =IFERROR(P86/N86,"No Error") -> 0.35433947 | AX86: =IF(P86>=20000,"Excellent",IF(P86>=10000,"Good",IF(P86>=5000,"Average","Low"))) -> Average
A87: ORD10562 | B87: 45447 | C87: CUST1172 | D87: Riya Malhotra | E87: Small Business | F87: Pune | G87: Maharashtra | H87: East | I87: Furniture | J87: Table | K87: 9 | L87: 4000 | M87: 0.05 | N87: 34200 | O87: 26233.14 | P87: 7966.86 | Q87: 23.29 | R87: Net Banking | S87: Retail Store | T87: Rohit | U87: April | V87: 2024 | W87: Saturday | X87: 2 | Y87: 45508 | Z87: Completed | AA87: Returning | AB87: Medium | AC87: No | AD87: 1 | AE87: Riya | AF87: Malhotra | AM87: =IF(Q87>=30,"Good","Needs Improvement") -> Needs Improvement | AN87: {=_xlfn.IFS(N87<10000,"Low",N87<30000,"Medium",N87>=30000,"High")} -> High | AO87: =IF(AND(N87>=30000,P87>=10000),"Yes","No") -> No | AP87: =IF(OR(S87="Online",S87="Marketplace"),"Yes","No") -> No | AQ87: =IFERROR(P87/N87,"No Error") -> 0.23294912 | AX87: =IF(P87>=20000,"Excellent",IF(P87>=10000,"Good",IF(P87>=5000,"Average","Low"))) -> Average
A88: ORD10386 | B88: 45448 | C88: CUST1146 | D88: Karan Chopra | E88: Consumer | F88: Ahmedabad | G88: Gujarat | H88: East | I88: Clothing | J88: Shoes | K88: 8 | L88: 700 | M88: 0.05 | N88: 5320 | O88: 3218.64 | P88: 2101.36 | Q88: 39.5 | R88: Net Banking | S88: Marketplace | T88: Manish | U88: May | V88: 2024 | W88: Monday | X88: 6 | Y88: 45631 | Z88: Completed | AA88: New | AB88: High | AC88: Yes | AD88: 5 | AE88: Karan | AF88: Chopra | AM88: =IF(Q88>=30,"Good","Needs Improvement") -> Good | AN88: {=_xlfn.IFS(N88<10000,"Low",N88<30000,"Medium",N88>=30000,"High")} -> Low | AO88: =IF(AND(N88>=30000,P88>=10000),"Yes","No") -> No | AP88: =IF(OR(S88="Online",S88="Marketplace"),"Yes","No") -> Yes | AQ88: =IFERROR(P88/N88,"No Error") -> 0.39499248 | AX88: =IF(P88>=20000,"Excellent",IF(P88>=10000,"Good",IF(P88>=5000,"Average","Low"))) -> Low
A89: ORD10095 | B89: 45449 | C89: CUST1310 | D89: Neha Chopra | E89: Small Business | F89: Ahmedabad | G89: Gujarat | H89: North | I89: Electronics | J89: Monitor | K89: 3 | L89: 35000 | M89: 0.2 | N89: 84000 | O89: 62543.95 | P89: 21456.05 | Q89: 25.54 | R89: Credit Card | S89: Online | T89: Amit | U89: June | V89: 2024 | W89: Thursday | X89: 3 | Y89: 45541 | Z89: Cancelled | AA89: VIP | AB89: High | AC89: No | AD89: 2 | AE89: Neha | AF89: Chopra | AM89: =IF(Q89>=30,"Good","Needs Improvement") -> Needs Improvement | AN89: {=_xlfn.IFS(N89<10000,"Low",N89<30000,"Medium",N89>=30000,"High")} -> High | AO89: =IF(AND(N89>=30000,P89>=10000),"Yes","No") -> Yes | AP89: =IF(OR(S89="Online",S89="Marketplace"),"Yes","No") -> Yes | AQ89: =IFERROR(P89/N89,"No Error") -> 0.25542917 | AX89: =IF(P89>=20000,"Excellent",IF(P89>=10000,"Good",IF(P89>=5000,"Average","Low"))) -> Excellent
A90: ORD10495 | B90: 45449 | C90: CUST1004 | D90: Rohan Agarwal | E90: Small Business | F90: Kolkata | G90: West Bengal | H90: East | I90: Clothing | J90: Jeans | K90: 2 | L90: 3500 | M90: 0.2 | N90: 5600 | O90: 4460.62 | P90: 1139.38 | Q90: 20.35 | R90: Debit Card | S90: Retail Store | T90: Kavita | U90: June | V90: 2024 | W90: Thursday | X90: 7 | Y90: 13-06-2024 | Z90: Completed | AA90: Returning | AB90: Medium | AC90: No | AD90: 4 | AE90: Rohan | AF90: Agarwal | AM90: =IF(Q90>=30,"Good","Needs Improvement") -> Needs Improvement | AN90: {=_xlfn.IFS(N90<10000,"Low",N90<30000,"Medium",N90>=30000,"High")} -> Low | AO90: =IF(AND(N90>=30000,P90>=10000),"Yes","No") -> No | AP90: =IF(OR(S90="Online",S90="Marketplace"),"Yes","No") -> No | AQ90: =IFERROR(P90/N90,"No Error") -> 0.20346071 | AX90: =IF(P90>=20000,"Excellent",IF(P90>=10000,"Good",IF(P90>=5000,"Average","Low"))) -> Low
A91: ORD10894 | B91: 45449 | C91: CUST1101 | D91: Kavya Yadav | E91: Consumer | F91: Bengaluru | G91: Karnataka | H91: East | I91: Accessories | J91: Belt | K91: 7 | L91: 3000 | M91: 0.15 | N91: 17850 | O91: 12304.93 | P91: 5545.07 | Q91: 31.06 | R91: Net Banking | S91: Online | T91: Kavita | U91: June | V91: 2024 | W91: Thursday | X91: 3 | Y91: 45541 | Z91: Completed | AA91: VIP | AB91: Low | AC91: Yes | AD91: 3 | AE91: Kavya | AF91: Yadav | AM91: =IF(Q91>=30,"Good","Needs Improvement") -> Good | AN91: {=_xlfn.IFS(N91<10000,"Low",N91<30000,"Medium",N91>=30000,"High")} -> Medium | AO91: =IF(AND(N91>=30000,P91>=10000),"Yes","No") -> No | AP91: =IF(OR(S91="Online",S91="Marketplace"),"Yes","No") -> Yes | AQ91: =IFERROR(P91/N91,"No Error") -> 0.31064818 | AX91: =IF(P91>=20000,"Excellent",IF(P91>=10000,"Good",IF(P91>=5000,"Average","Low"))) -> Average
A92: ORD10013 | B92: 45450 | C92: CUST1039 | D92: Riya Agarwal | E92: Small Business | F92: Hyderabad | G92: Telangana | H92: North | I92: Furniture | J92: Table | K92: 8 | L92: 4000 | M92: 0.15 | N92: 27200 | O92: 16794.58 | P92: 10405.42 | Q92: 38.26 | R92: Credit Card | S92: Marketplace | T92: Anjali | U92: July | V92: 2024 | W92: Saturday | X92: 5 | Y92: 45603 | Z92: Pending | AA92: New | AB92: Low | AC92: Yes | AD92: 2 | AE92: Riya | AF92: Agarwal | AM92: =IF(Q92>=30,"Good","Needs Improvement") -> Good | AN92: {=_xlfn.IFS(N92<10000,"Low",N92<30000,"Medium",N92>=30000,"High")} -> Medium | AO92: =IF(AND(N92>=30000,P92>=10000),"Yes","No") -> No | AP92: =IF(OR(S92="Online",S92="Marketplace"),"Yes","No") -> Yes | AQ92: =IFERROR(P92/N92,"No Error") -> 0.38255221 | AX92: =IF(P92>=20000,"Excellent",IF(P92>=10000,"Good",IF(P92>=5000,"Average","Low"))) -> Good
A93: ORD10348 | B93: 45454 | C93: CUST1034 | D93: Nisha Agarwal | E93: Corporate | F93: Bengaluru | G93: Karnataka | H93: North | I93: Accessories | J93: Belt | K93: 2 | L93: 800 | M93: 0.05 | N93: 1520 | O93: 1240.92 | P93: 279.08 | Q93: 18.36 | R93: Credit Card | S93: Retail Store | T93: Sneha | U93: November | V93: 2024 | W93: Wednesday | X93: 8 | Y93: 14-11-2024 | Z93: Cancelled | AA93: Returning | AB93: Low | AC93: No | AD93: 5 | AE93: Nisha | AF93: Agarwal | AM93: =IF(Q93>=30,"Good","Needs Improvement") -> Needs Improvement | AN93: {=_xlfn.IFS(N93<10000,"Low",N93<30000,"Medium",N93>=30000,"High")} -> Low | AO93: =IF(AND(N93>=30000,P93>=10000),"Yes","No") -> No | AP93: =IF(OR(S93="Online",S93="Marketplace"),"Yes","No") -> No | AQ93: =IFERROR(P93/N93,"No Error") -> 0.18360526 | AX93: =IF(P93>=20000,"Excellent",IF(P93>=10000,"Good",IF(P93>=5000,"Average","Low"))) -> Low
A94: ORD10411 | B94: 45454 | C94: CUST1074 | D94: Rohan Agarwal | E94: Small Business | F94: Ahmedabad | G94: Gujarat | H94: West | I94: Furniture | J94: Office Chair | K94: 6 | L94: 6000 | M94: 0.1 | N94: 32400 | O94: 18064.75 | P94: 14335.25 | Q94: 44.24 | R94: Credit Card | S94: Retail Store | T94: Sneha | U94: November | V94: 2024 | W94: Wednesday | X94: 5 | Y94: 45607 | Z94: Pending | AA94: New | AB94: Low | AC94: No | AD94: 1 | AE94: Rohan | AF94: Agarwal | AM94: =IF(Q94>=30,"Good","Needs Improvement") -> Good | AN94: {=_xlfn.IFS(N94<10000,"Low",N94<30000,"Medium",N94>=30000,"High")} -> High | AO94: =IF(AND(N94>=30000,P94>=10000),"Yes","No") -> Yes | AP94: =IF(OR(S94="Online",S94="Marketplace"),"Yes","No") -> No | AQ94: =IFERROR(P94/N94,"No Error") -> 0.44244599 | AX94: =IF(P94>=20000,"Excellent",IF(P94>=10000,"Good",IF(P94>=5000,"Average","Low"))) -> Good
A95: ORD10748 | B95: 45454 | C95: CUST1250 | D95: Simran Yadav | E95: Corporate | F95: Chennai | G95: Tamil Nadu | H95: West | I95: Furniture | J95: Office Chair | K95: 8 | L95: 9000 | M95: 0.05 | N95: 68400 | O95: 41825.89 | P95: 26574.11 | Q95: 38.85 | R95: Cash | S95: Online | T95: Rohit | U95: November | V95: 2024 | W95: Wednesday | X95: 9 | Y95: 15-11-2024 | Z95: Completed | AA95: VIP | AB95: Low | AC95: No | AD95: 1 | AE95: Simran | AF95: Yadav | AM95: =IF(Q95>=30,"Good","Needs Improvement") -> Good | AN95: {=_xlfn.IFS(N95<10000,"Low",N95<30000,"Medium",N95>=30000,"High")} -> High | AO95: =IF(AND(N95>=30000,P95>=10000),"Yes","No") -> Yes | AP95: =IF(OR(S95="Online",S95="Marketplace"),"Yes","No") -> Yes | AQ95: =IFERROR(P95/N95,"No Error") -> 0.38851038 | AX95: =IF(P95>=20000,"Excellent",IF(P95>=10000,"Good",IF(P95>=5000,"Average","Low"))) -> Excellent
A96: ORD10984 | B96: 45455 | C96: CUST1288 | D96: Simran Mehta | E96: Consumer | F96: Ahmedabad | G96: Gujarat | H96: South | I96: Electronics | J96: Smartphone | K96: 2 | L96: 8000 | M96: 0.1 | N96: 14400 | O96: 9287.78 | P96: 5112.22 | Q96: 35.5 | R96: Credit Card | S96: Retail Store | T96: Sneha | U96: December | V96: 2024 | W96: Friday | X96: 1 | Y96: 45485 | Z96: Completed | AA96: New | AB96: High | AC96: No | AD96: 4 | AE96: Simran | AF96: Mehta | AM96: =IF(Q96>=30,"Good","Needs Improvement") -> Good | AN96: {=_xlfn.IFS(N96<10000,"Low",N96<30000,"Medium",N96>=30000,"High")} -> Medium | AO96: =IF(AND(N96>=30000,P96>=10000),"Yes","No") -> No | AP96: =IF(OR(S96="Online",S96="Marketplace"),"Yes","No") -> No | AQ96: =IFERROR(P96/N96,"No Error") -> 0.35501528 | AX96: =IF(P96>=20000,"Excellent",IF(P96>=10000,"Good",IF(P96>=5000,"Average","Low"))) -> Average
A97: ORD11001 | B97: 45455 | C97: CUST1302 | D97: Neha Bansal | E97: Small Business | F97: Mumbai | G97: Maharashtra | H97: West | I97: Accessories | J97: Sunglasses | K97: 4 | L97: 3000 | M97: 0.1 | N97: 10800 | O97: 6177.81 | P97: 4622.19 | Q97: 42.8 | R97: Cash | S97: Online | T97: Neeraj | U97: December | V97: 2024 | W97: Friday | X97: 9 | Y97: 15-12-2024 | Z97: Cancelled | AA97: Returning | AB97: High | AC97: Yes | AD97: 1 | AE97: Neha | AF97: Bansal | AM97: =IF(Q97>=30,"Good","Needs Improvement") -> Good | AN97: {=_xlfn.IFS(N97<10000,"Low",N97<30000,"Medium",N97>=30000,"High")} -> Medium | AO97: =IF(AND(N97>=30000,P97>=10000),"Yes","No") -> No | AP97: =IF(OR(S97="Online",S97="Marketplace"),"Yes","No") -> Yes | AQ97: =IFERROR(P97/N97,"No Error") -> 0.42798056 | AX97: =IF(P97>=20000,"Excellent",IF(P97>=10000,"Good",IF(P97>=5000,"Average","Low"))) -> Low
A98: ORD10680 | B98: 45474 | C98: CUST1116 | D98: Neha Mehta | E98: Consumer | F98: Ahmedabad | G98: Gujarat | H98: East | I98: Clothing | J98: Shirt | K98: 7 | L98: 3500 | M98: 0.1 | N98: 22050 | O98: 12239.85 | P98: 9810.15 | Q98: 44.49 | R98: Debit Card | S98: Marketplace | T98: Vikas | U98: January | V98: 2024 | W98: Sunday | X98: 10 | Y98: 17-01-2024 | Z98: Pending | AA98: VIP | AB98: Medium | AC98: Yes | AD98: 5 | AE98: Neha | AF98: Mehta | AM98: =IF(Q98>=30,"Good","Needs Improvement") -> Good | AN98: {=_xlfn.IFS(N98<10000,"Low",N98<30000,"Medium",N98>=30000,"High")} -> Medium | AO98: =IF(AND(N98>=30000,P98>=10000),"Yes","No") -> No | AP98: =IF(OR(S98="Online",S98="Marketplace"),"Yes","No") -> Yes | AQ98: =IFERROR(P98/N98,"No Error") -> 0.44490476 | AX98: =IF(P98>=20000,"Excellent",IF(P98>=10000,"Good",IF(P98>=5000,"Average","Low"))) -> Average
A99: ORD10743 | B99: 45474 | C99: CUST1135 | D99: Rohan Saxena | E99: Small Business | F99: Pune | G99: Maharashtra | H99: South | I99: Accessories | J99: Backpack | K99: 8 | L99: 800 | M99: 0.2 | N99: 5120 | O99: 4162.72 | P99: 957.28 | Q99: 18.7 | R99: Credit Card | S99: Marketplace | T99: Neeraj | U99: January | V99: 2024 | W99: Sunday | X99: 2 | Y99: 45536 | Z99: Completed | AA99: New | AB99: Low | AC99: No | AD99: 2 | AE99: Rohan | AF99: Saxena | AM99: =IF(Q99>=30,"Good","Needs Improvement") -> Needs Improvement | AN99: {=_xlfn.IFS(N99<10000,"Low",N99<30000,"Medium",N99>=30000,"High")} -> Low | AO99: =IF(AND(N99>=30000,P99>=10000),"Yes","No") -> No | AP99: =IF(OR(S99="Online",S99="Marketplace"),"Yes","No") -> Yes | AQ99: =IFERROR(P99/N99,"No Error") -> 0.18696875 | AX99: =IF(P99>=20000,"Excellent",IF(P99>=10000,"Good",IF(P99>=5000,"Average","Low"))) -> Low
A100: ORD10428 | B100: 45478 | C100: CUST1194 | D100: Neha Saxena | E100: Small Business | F100: Lucknow | G100: Uttar Pradesh | H100: North | I100: Accessories | J100: Sunglasses | K100: 2 | L100: 2000 | M100: 0.2 | N100: 3200 | O100: 2552.04 | P100: 647.96 | Q100: 20.25 | R100: Debit Card | S100: Online | T100: Rohit | U100: May | V100: 2024 | W100: Tuesday | X100: 2 | Y100: 45540 | Z100: Completed | AA100: New | AB100: Medium | AC100: No | AD100: 1 | AE100: Neha | AF100: Saxena | AM100: =IF(Q100>=30,"Good","Needs Improvement") -> Needs Improvement | AN100: {=_xlfn.IFS(N100<10000,"Low",N100<30000,"Medium",N100>=30000,"High")} -> Low | AO100: =IF(AND(N100>=30000,P100>=10000),"Yes","No") -> No | AP100: =IF(OR(S100="Online",S100="Marketplace"),"Yes","No") -> Yes | AQ100: =IFERROR(P100/N100,"No Error") -> 0.2024875 | AX100: =IF(P100>=20000,"Excellent",IF(P100>=10000,"Good",IF(P100>=5000,"Average","Low"))) -> Low
A101: ORD10950 | B101: 45478 | C101: CUST1348 | D101: Karan Sharma | E101: Small Business | F101: Chennai | G101: Tamil Nadu | H101: West | I101: Accessories | J101: Wallet | K101: 6 | L101: 500 | M101: 0 | N101: 3000 | O101: 2235.13 | P101: 764.87 | Q101: 25.5 | R101: UPI | S101: Online | T101: Kavita | U101: May | V101: 2024 | W101: Tuesday | X101: 10 | Y101: 17-05-2024 | Z101: Completed | AA101: VIP | AB101: Low | AC101: No | AD101: 1 | AE101: Karan | AF101: Sharma | AM101: =IF(Q101>=30,"Good","Needs Improvement") -> Needs Improvement | AN101: {=_xlfn.IFS(N101<10000,"Low",N101<30000,"Medium",N101>=30000,"High")} -> Low | AO101: =IF(AND(N101>=30000,P101>=10000),"Yes","No") -> No | AP101: =IF(OR(S101="Online",S101="Marketplace"),"Yes","No") -> Yes | AQ101: =IFERROR(P101/N101,"No Error") -> 0.25495667 | AX101: =IF(P101>=20000,"Excellent",IF(P101>=10000,"Good",IF(P101>=5000,"Average","Low"))) -> Low
A102: ORD10020 | B102: 45479 | C102: CUST1091 | D102: Ishita Sharma | E102: Consumer | F102: Hyderabad | G102: Telangana | H102: East | I102: Electronics | J102: Tablet | K102: 9 | L102: 22000 | M102: 0.2 | N102: 158400 | O102: 128870.38 | P102: 29529.62 | Q102: 18.64 | R102: Cash | S102: Marketplace | T102: Rahul | U102: June | V102: 2024 | W102: Friday | X102: 4 | Y102: 45602 | Z102: Completed | AA102: Returning | AB102: Low | AC102: Yes | AD102: 4 | AE102: Ishita | AF102: Sharma | AM102: =IF(Q102>=30,"Good","Needs Improvement") -> Needs Improvement | AN102: {=_xlfn.IFS(N102<10000,"Low",N102<30000,"Medium",N102>=30000,"High")} -> High | AO102: =IF(AND(N102>=30000,P102>=10000),"Yes","No") -> Yes | AP102: =IF(OR(S102="Online",S102="Marketplace"),"Yes","No") -> Yes | AQ102: =IFERROR(P102/N102,"No Error") -> 0.18642437 | AX102: =IF(P102>=20000,"Excellent",IF(P102>=10000,"Good",IF(P102>=5000,"Average","Low"))) -> Excellent
A103: ORD10283 | B103: 45480 | C103: CUST1084 | D103: Rahul Singh | E103: Consumer | F103: Jaipur | G103: Rajasthan | H103: West | I103: Furniture | J103: Table | K103: 10 | L103: 9000 | M103: 0.1 | N103: 81000 | O103: 54913.03 | P103: 26086.97 | Q103: 32.21 | R103: Credit Card | S103: Retail Store | T103: Kavita | U103: July | V103: 2024 | W103: Sunday | X103: 7 | Y103: 14-07-2024 | Z103: Pending | AA103: New | AB103: High | AC103: Yes | AD103: 2 | AE103: Rahul | AF103: Singh | AM103: =IF(Q103>=30,"Good","Needs Improvement") -> Good | AN103: {=_xlfn.IFS(N103<10000,"Low",N103<30000,"Medium",N103>=30000,"High")} -> High | AO103: =IF(AND(N103>=30000,P103>=10000),"Yes","No") -> Yes | AP103: =IF(OR(S103="Online",S103="Marketplace"),"Yes","No") -> No | AQ103: =IFERROR(P103/N103,"No Error") -> 0.32206136 | AX103: =IF(P103>=20000,"Excellent",IF(P103>=10000,"Good",IF(P103>=5000,"Average","Low"))) -> Excellent
A104: ORD10996 | B104: 45480 | C104: CUST1339 | D104: Nisha Yadav | E104: Consumer | F104: Bengaluru | G104: Karnataka | H104: South | I104: Office Supplies | J104: Notebook | K104: 8 | L104: 800 | M104: 0.1 | N104: 5760 | O104: 4144.26 | P104: 1615.74 | Q104: 28.05 | R104: Debit Card | S104: Retail Store | T104: Vikas | U104: July | V104: 2024 | W104: Sunday | X104: 10 | Y104: 17-07-2024 | Z104: Completed | AA104: New | AB104: Low | AC104: Yes | AD104: 1 | AE104: Nisha | AF104: Yadav | AM104: =IF(Q104>=30,"Good","Needs Improvement") -> Needs Improvement | AN104: {=_xlfn.IFS(N104<10000,"Low",N104<30000,"Medium",N104>=30000,"High")} -> Low | AO104: =IF(AND(N104>=30000,P104>=10000),"Yes","No") -> No | AP104: =IF(OR(S104="Online",S104="Marketplace"),"Yes","No") -> No | AQ104: =IFERROR(P104/N104,"No Error") -> 0.28051042 | AX104: =IF(P104>=20000,"Excellent",IF(P104>=10000,"Good",IF(P104>=5000,"Average","Low"))) -> Low
A105: ORD10720 | B105: 45481 | C105: CUST1114 | D105: Neha Verma | E105: Small Business | F105: Ahmedabad | G105: Gujarat | H105: South | I105: Accessories | J105: Watch | K105: 9 | L105: 1200 | M105: 0 | N105: 10800 | O105: 8710.1 | P105: 2089.9 | Q105: 19.35 | R105: Cash | S105: Online | T105: Manish | U105: August | V105: 2024 | W105: Wednesday | X105: 2 | Y105: 45543 | Z105: Pending | AA105: VIP | AB105: High | AC105: Yes | AD105: 1 | AE105: Neha | AF105: Verma | AM105: =IF(Q105>=30,"Good","Needs Improvement") -> Needs Improvement | AN105: {=_xlfn.IFS(N105<10000,"Low",N105<30000,"Medium",N105>=30000,"High")} -> Medium | AO105: =IF(AND(N105>=30000,P105>=10000),"Yes","No") -> No | AP105: =IF(OR(S105="Online",S105="Marketplace"),"Yes","No") -> Yes | AQ105: =IFERROR(P105/N105,"No Error") -> 0.19350926 | AX105: =IF(P105>=20000,"Excellent",IF(P105>=10000,"Good",IF(P105>=5000,"Average","Low"))) -> Low
A106: ORD10945 | B106: 45481 | C106: CUST1128 | D106: Sneha Mishra | E106: Small Business | F106: Delhi | G106: Delhi | H106: South | I106: Accessories | J106: Backpack | K106: 2 | L106: 1200 | M106: 0 | N106: 2400 | O106: 1900.65 | P106: 499.35 | Q106: 20.81 | R106: Debit Card | S106: Marketplace | T106: Kavita | U106: August | V106: 2024 | W106: Wednesday | X106: 2 | Y106: 45543 | Z106: Cancelled | AA106: New | AB106: Low | AC106: Yes | AD106: 4 | AE106: Sneha | AF106: Mishra | AM106: =IF(Q106>=30,"Good","Needs Improvement") -> Needs Improvement | AN106: {=_xlfn.IFS(N106<10000,"Low",N106<30000,"Medium",N106>=30000,"High")} -> Low | AO106: =IF(AND(N106>=30000,P106>=10000),"Yes","No") -> No | AP106: =IF(OR(S106="Online",S106="Marketplace"),"Yes","No") -> Yes | AQ106: =IFERROR(P106/N106,"No Error") -> 0.2080625 | AX106: =IF(P106>=20000,"Excellent",IF(P106>=10000,"Good",IF(P106>=5000,"Average","Low"))) -> Low
A107: ORD10990 | B107: 45481 | C107: CUST1336 | D107: Nisha Kumar | E107: Corporate | F107: Kolkata | G107: West Bengal | H107: East | I107: Electronics | J107: Laptop | K107: 6 | L107: 8000 | M107: 0.1 | N107: 43200 | O107: 35034.57 | P107: 8165.43 | Q107: 18.9 | R107: Credit Card | S107: Retail Store | T107: Sneha | U107: August | V107: 2024 | W107: Wednesday | X107: 3 | Y107: 45573 | Z107: Completed | AA107: New | AB107: Medium | AC107: Yes | AD107: 4 | AE107: Nisha | AF107: Kumar | AM107: =IF(Q107>=30,"Good","Needs Improvement") -> Needs Improvement | AN107: {=_xlfn.IFS(N107<10000,"Low",N107<30000,"Medium",N107>=30000,"High")} -> High | AO107: =IF(AND(N107>=30000,P107>=10000),"Yes","No") -> No | AP107: =IF(OR(S107="Online",S107="Marketplace"),"Yes","No") -> No | AQ107: =IFERROR(P107/N107,"No Error") -> 0.18901458 | AX107: =IF(P107>=20000,"Excellent",IF(P107>=10000,"Good",IF(P107>=5000,"Average","Low"))) -> Average
A108: ORD10803 | B108: 45482 | C108: CUST1225 | D108: Ananya Malhotra | E108: Corporate | F108: Bengaluru | G108: Karnataka | H108: West | I108: Clothing | J108: T-Shirt | K108: 3 | L108: 1800 | M108: 0.15 | N108: 4590 | O108: 3640.49 | P108: 949.51 | Q108: 20.69 | R108: Cash | S108: Retail Store | T108: Rahul | U108: September | V108: 2024 | W108: Saturday | X108: 3 | Y108: 45574 | Z108: Completed | AA108: Returning | AB108: Low | AC108: No | AD108: 1 | AE108: Ananya | AF108: Malhotra | AM108: =IF(Q108>=30,"Good","Needs Improvement") -> Needs Improvement | AN108: {=_xlfn.IFS(N108<10000,"Low",N108<30000,"Medium",N108>=30000,"High")} -> Low | AO108: =IF(AND(N108>=30000,P108>=10000),"Yes","No") -> No | AP108: =IF(OR(S108="Online",S108="Marketplace"),"Yes","No") -> No | AQ108: =IFERROR(P108/N108,"No Error") -> 0.20686492 | AX108: =IF(P108>=20000,"Excellent",IF(P108>=10000,"Good",IF(P108>=5000,"Average","Low"))) -> Low
A109: ORD10564 | B109: 45483 | C109: CUST1270 | D109: Karan Kumar | E109: Small Business | F109: Hyderabad | G109: Telangana | H109: East | I109: Electronics | J109: Smartphone | K109: 7 | L109: 50000 | M109: 0 | N109: 350000 | O109: 285802.84 | P109: 64197.16 | Q109: 18.34 | R109: UPI | S109: Retail Store | T109: Manish | U109: October | V109: 2024 | W109: Monday | X109: 9 | Y109: 16-10-2024 | Z109: Pending | AA109: Returning | AB109: Medium | AC109: No | AD109: 2 | AE109: Karan | AF109: Kumar | AM109: =IF(Q109>=30,"Good","Needs Improvement") -> Needs Improvement | AN109: {=_xlfn.IFS(N109<10000,"Low",N109<30000,"Medium",N109>=30000,"High")} -> High | AO109: =IF(AND(N109>=30000,P109>=10000),"Yes","No") -> Yes | AP109: =IF(OR(S109="Online",S109="Marketplace"),"Yes","No") -> No | AQ109: =IFERROR(P109/N109,"No Error") -> 0.18342046 | AX109: =IF(P109>=20000,"Excellent",IF(P109>=10000,"Good",IF(P109>=5000,"Average","Low"))) -> Excellent
A110: ORD10862 | B110: 45506 | C110: CUST1150 | D110: Vikram Singh | E110: Consumer | F110: Chennai | G110: Tamil Nadu | H110: South | I110: Furniture | J110: Sofa | K110: 10 | L110: 2500 | M110: 0.1 | N110: 22500 | O110: 18408.24 | P110: 4091.76 | Q110: 18.19 | R110: UPI | S110: Online | T110: Anjali | U110: February | V110: 2024 | W110: Thursday | X110: 5 | Y110: 13-02-2024 | Z110: Completed | AA110: Returning | AB110: High | AC110: No | AD110: 1 | AE110: Vikram | AF110: Singh | AM110: =IF(Q110>=30,"Good","Needs Improvement") -> Needs Improvement | AN110: {=_xlfn.IFS(N110<10000,"Low",N110<30000,"Medium",N110>=30000,"High")} -> Medium | AO110: =IF(AND(N110>=30000,P110>=10000),"Yes","No") -> No | AP110: =IF(OR(S110="Online",S110="Marketplace"),"Yes","No") -> Yes | AQ110: =IFERROR(P110/N110,"No Error") -> 0.181856 | AX110: =IF(P110>=20000,"Excellent",IF(P110>=10000,"Good",IF(P110>=5000,"Average","Low"))) -> Low
A111: ORD10063 | B111: 45507 | C111: CUST1300 | D111: Aditi Yadav | E111: Corporate | F111: Jaipur | G111: Rajasthan | H111: West | I111: Electronics | J111: Laptop | K111: 6 | L111: 35000 | M111: 0.05 | N111: 199500 | O111: 143353.86 | P111: 56146.14 | Q111: 28.14 | R111: Net Banking | S111: Marketplace | T111: Sneha | U111: March | V111: 2024 | W111: Friday | X111: 3 | Y111: 45599 | Z111: Completed | AA111: Returning | AB111: High | AC111: No | AD111: 1 | AE111: Aditi | AF111: Yadav | AM111: =IF(Q111>=30,"Good","Needs Improvement") -> Needs Improvement | AN111: {=_xlfn.IFS(N111<10000,"Low",N111<30000,"Medium",N111>=30000,"High")} -> High | AO111: =IF(AND(N111>=30000,P111>=10000),"Yes","No") -> Yes | AP111: =IF(OR(S111="Online",S111="Marketplace"),"Yes","No") -> Yes | AQ111: =IFERROR(P111/N111,"No Error") -> 0.28143429 | AX111: =IF(P111>=20000,"Excellent",IF(P111>=10000,"Good",IF(P111>=5000,"Average","Low"))) -> Excellent
A112: ORD10688 | B112: 45507 | C112: CUST1213 | D112: Aditi Malhotra | E112: Consumer | F112: Mumbai | G112: Maharashtra | H112: North | I112: Electronics | J112: Tablet | K112: 4 | L112: 8000 | M112: 0.15 | N112: 27200 | O112: 18370.8 | P112: 8829.2 | Q112: 32.46 | R112: UPI | S112: Retail Store | T112: Rohit | U112: March | V112: 2024 | W112: Friday | X112: 2 | Y112: 45568 | Z112: Pending | AA112: Returning | AB112: Low | AC112: No | AD112: 5 | AE112: Aditi | AF112: Malhotra | AM112: =IF(Q112>=30,"Good","Needs Improvement") -> Good | AN112: {=_xlfn.IFS(N112<10000,"Low",N112<30000,"Medium",N112>=30000,"High")} -> Medium | AO112: =IF(AND(N112>=30000,P112>=10000),"Yes","No") -> No | AP112: =IF(OR(S112="Online",S112="Marketplace"),"Yes","No") -> No | AQ112: =IFERROR(P112/N112,"No Error") -> 0.32460294 | AX112: =IF(P112>=20000,"Excellent",IF(P112>=10000,"Good",IF(P112>=5000,"Average","Low"))) -> Average
A113: ORD10808 | B113: 45507 | C113: CUST1085 | D113: Kavya Verma | E113: Consumer | F113: Delhi | G113: Delhi | H113: West | I113: Electronics | J113: Smartphone | K113: 1 | L113: 15000 | M113: 0.15 | N113: 12750 | O113: 10162.85 | P113: 2587.15 | Q113: 20.29 | R113: UPI | S113: Marketplace | T113: Vikas | U113: March | V113: 2024 | W113: Friday | X113: 4 | Y113: 45629 | Z113: Pending | AA113: Returning | AB113: Medium | AC113: No | AD113: 3 | AE113: Kavya | AF113: Verma | AM113: =IF(Q113>=30,"Good","Needs Improvement") -> Needs Improvement | AN113: {=_xlfn.IFS(N113<10000,"Low",N113<30000,"Medium",N113>=30000,"High")} -> Medium | AO113: =IF(AND(N113>=30000,P113>=10000),"Yes","No") -> No | AP113: =IF(OR(S113="Online",S113="Marketplace"),"Yes","No") -> Yes | AQ113: =IFERROR(P113/N113,"No Error") -> 0.20291373 | AX113: =IF(P113>=20000,"Excellent",IF(P113>=10000,"Good",IF(P113>=5000,"Average","Low"))) -> Low
A114: ORD10880 | B114: 45507 | C114: CUST1332 | D114: Ananya Verma | E114: Corporate | F114: Mumbai | G114: Maharashtra | H114: North | I114: Furniture | J114: Table | K114: 6 | L114: 2500 | M114: 0 | N114: 15000 | O114: 8476.74 | P114: 6523.26 | Q114: 43.49 | R114: UPI | S114: Online | T114: Rohit | U114: March | V114: 2024 | W114: Friday | X114: 7 | Y114: 15-03-2024 | Z114: Cancelled | AA114: Returning | AB114: Low | AC114: Yes | AD114: 5 | AE114: Ananya | AF114: Verma | AM114: =IF(Q114>=30,"Good","Needs Improvement") -> Good | AN114: {=_xlfn.IFS(N114<10000,"Low",N114<30000,"Medium",N114>=30000,"High")} -> Medium | AO114: =IF(AND(N114>=30000,P114>=10000),"Yes","No") -> No | AP114: =IF(OR(S114="Online",S114="Marketplace"),"Yes","No") -> Yes | AQ114: =IFERROR(P114/N114,"No Error") -> 0.434884 | AX114: =IF(P114>=20000,"Excellent",IF(P114>=10000,"Good",IF(P114>=5000,"Average","Low"))) -> Average
A115: ORD10217 | B115: 45508 | C115: CUST1321 | D115: Aditya Singh | E115: Small Business | F115: Delhi | G115: Delhi | H115: South | I115: Office Supplies | J115: Printer Paper | K115: 6 | L115: 800 | M115: 0 | N115: 4800 | O115: 3331.03 | P115: 1468.97 | Q115: 30.6 | R115: Cash | S115: Online | T115: Rahul | U115: April | V115: 2024 | W115: Monday | X115: 3 | Y115: 45600 | Z115: Cancelled | AA115: VIP | AB115: High | AC115: No | AD115: 1 | AE115: Aditya | AF115: Singh | AM115: =IF(Q115>=30,"Good","Needs Improvement") -> Good | AN115: {=_xlfn.IFS(N115<10000,"Low",N115<30000,"Medium",N115>=30000,"High")} -> Low | AO115: =IF(AND(N115>=30000,P115>=10000),"Yes","No") -> No | AP115: =IF(OR(S115="Online",S115="Marketplace"),"Yes","No") -> Yes | AQ115: =IFERROR(P115/N115,"No Error") -> 0.30603542 | AX115: =IF(P115>=20000,"Excellent",IF(P115>=10000,"Good",IF(P115>=5000,"Average","Low"))) -> Low
A116: ORD10060 | B116: 45509 | C116: CUST1284 | D116: Rahul Bansal | E116: Consumer | F116: Hyderabad | G116: Telangana | H116: South | I116: Accessories | J116: Backpack | K116: 1 | L116: 1200 | M116: 0.05 | N116: 1140 | O116: 648.12 | P116: 491.88 | Q116: 43.15 | R116: UPI | S116: Online | T116: Manish | U116: May | V116: 2024 | W116: Wednesday | X116: 10 | Y116: 18-05-2024 | Z116: Completed | AA116: New | AB116: Medium | AC116: Yes | AD116: 2 | AE116: Rahul | AF116: Bansal | AM116: =IF(Q116>=30,"Good","Needs Improvement") -> Good | AN116: {=_xlfn.IFS(N116<10000,"Low",N116<30000,"Medium",N116>=30000,"High")} -> Low | AO116: =IF(AND(N116>=30000,P116>=10000),"Yes","No") -> No | AP116: =IF(OR(S116="Online",S116="Marketplace"),"Yes","No") -> Yes | AQ116: =IFERROR(P116/N116,"No Error") -> 0.43147368 | AX116: =IF(P116>=20000,"Excellent",IF(P116>=10000,"Good",IF(P116>=5000,"Average","Low"))) -> Low
A117: ORD10509 | B117: 45510 | C117: CUST1223 | D117: Sneha Gupta | E117: Corporate | F117: Hyderabad | G117: Telangana | H117: North | I117: Office Supplies | J117: Pen Set | K117: 4 | L117: 800 | M117: 0.15 | N117: 2720 | O117: 2031.97 | P117: 688.03 | Q117: 25.3 | R117: Cash | S117: Online | T117: Rohit | U117: June | V117: 2024 | W117: Saturday | X117: 8 | Y117: 16-06-2024 | Z117: Completed | AA117: New | AB117: Low | AC117: Yes | AD117: 5 | AE117: Sneha | AF117: Gupta | AM117: =IF(Q117>=30,"Good","Needs Improvement") -> Needs Improvement | AN117: {=_xlfn.IFS(N117<10000,"Low",N117<30000,"Medium",N117>=30000,"High")} -> Low | AO117: =IF(AND(N117>=30000,P117>=10000),"Yes","No") -> No | AP117: =IF(OR(S117="Online",S117="Marketplace"),"Yes","No") -> Yes | AQ117: =IFERROR(P117/N117,"No Error") -> 0.25295221 | AX117: =IF(P117>=20000,"Excellent",IF(P117>=10000,"Good",IF(P117>=5000,"Average","Low"))) -> Low
A118: ORD10520 | B118: 45510 | C118: CUST1089 | D118: Meera Gupta | E118: Consumer | F118: Kolkata | G118: West Bengal | H118: West | I118: Office Supplies | J118: File Folder | K118: 1 | L118: 350 | M118: 0 | N118: 350 | O118: 249.59 | P118: 100.41 | Q118: 28.69 | R118: Cash | S118: Marketplace | T118: Rohit | U118: June | V118: 2024 | W118: Saturday | X118: 1 | Y118: 45541 | Z118: Completed | AA118: VIP | AB118: High | AC118: No | AD118: 5 | AE118: Meera | AF118: Gupta | AM118: =IF(Q118>=30,"Good","Needs Improvement") -> Needs Improvement | AN118: {=_xlfn.IFS(N118<10000,"Low",N118<30000,"Medium",N118>=30000,"High")} -> Low | AO118: =IF(AND(N118>=30000,P118>=10000),"Yes","No") -> No | AP118: =IF(OR(S118="Online",S118="Marketplace"),"Yes","No") -> Yes | AQ118: =IFERROR(P118/N118,"No Error") -> 0.28688571 | AX118: =IF(P118>=20000,"Excellent",IF(P118>=10000,"Good",IF(P118>=5000,"Average","Low"))) -> Low
A119: ORD10155 | B119: 45512 | C119: CUST1204 | D119: Meera Kumar | E119: Small Business | F119: Mumbai | G119: Maharashtra | H119: West | I119: Electronics | J119: Monitor | K119: 2 | L119: 8000 | M119: 0.1 | N119: 14400 | O119: 11608.47 | P119: 2791.53 | Q119: 19.39 | R119: Cash | S119: Marketplace | T119: Kavita | U119: August | V119: 2024 | W119: Thursday | X119: 1 | Y119: 45543 | Z119: Completed | AA119: New | AB119: High | AC119: Yes | AD119: 3 | AE119: Meera | AF119: Kumar | AM119: =IF(Q119>=30,"Good","Needs Improvement") -> Needs Improvement | AN119: {=_xlfn.IFS(N119<10000,"Low",N119<30000,"Medium",N119>=30000,"High")} -> Medium | AO119: =IF(AND(N119>=30000,P119>=10000),"Yes","No") -> No | AP119: =IF(OR(S119="Online",S119="Marketplace"),"Yes","No") -> Yes | AQ119: =IFERROR(P119/N119,"No Error") -> 0.19385625 | AX119: =IF(P119>=20000,"Excellent",IF(P119>=10000,"Good",IF(P119>=5000,"Average","Low"))) -> Low
A120: ORD10485 | B120: 45512 | C120: CUST1303 | D120: Sneha Kumar | E120: Consumer | F120: Delhi | G120: Delhi | H120: West | I120: Furniture | J120: Office Chair | K120: 4 | L120: 4000 | M120: 0.1 | N120: 14400 | O120: 10066.45 | P120: 4333.55 | Q120: 30.09 | R120: Credit Card | S120: Marketplace | T120: Sneha | U120: August | V120: 2024 | W120: Thursday | X120: 3 | Y120: 45604 | Z120: Cancelled | AA120: Returning | AB120: Medium | AC120: Yes | AD120: 4 | AE120: Sneha | AF120: Kumar | AM120: =IF(Q120>=30,"Good","Needs Improvement") -> Good | AN120: {=_xlfn.IFS(N120<10000,"Low",N120<30000,"Medium",N120>=30000,"High")} -> Medium | AO120: =IF(AND(N120>=30000,P120>=10000),"Yes","No") -> No | AP120: =IF(OR(S120="Online",S120="Marketplace"),"Yes","No") -> Yes | AQ120: =IFERROR(P120/N120,"No Error") -> 0.30094097 | AX120: =IF(P120>=20000,"Excellent",IF(P120>=10000,"Good",IF(P120>=5000,"Average","Low"))) -> Low
A121: ORD10674 | B121: 45512 | C121: CUST1141 | D121: Arjun Verma | E121: Consumer | F121: Kolkata | G121: West Bengal | H121: South | I121: Clothing | J121: Jacket | K121: 9 | L121: 3500 | M121: 0.05 | N121: 29925 | O121: 20014.67 | P121: 9910.33 | Q121: 33.12 | R121: UPI | S121: Marketplace | T121: Rohit | U121: August | V121: 2024 | W121: Thursday | X121: 10 | Y121: 18-08-2024 | Z121: Cancelled | AA121: VIP | AB121: High | AC121: No | AD121: 1 | AE121: Arjun | AF121: Verma | AM121: =IF(Q121>=30,"Good","Needs Improvement") -> Good | AN121: {=_xlfn.IFS(N121<10000,"Low",N121<30000,"Medium",N121>=30000,"High")} -> Medium | AO121: =IF(AND(N121>=30000,P121>=10000),"Yes","No") -> No | AP121: =IF(OR(S121="Online",S121="Marketplace"),"Yes","No") -> Yes | AQ121: =IFERROR(P121/N121,"No Error") -> 0.33117226 | AX121: =IF(P121>=20000,"Excellent",IF(P121>=10000,"Good",IF(P121>=5000,"Average","Low"))) -> Average
A122: ORD10435 | B122: 45513 | C122: CUST1135 | D122: Arjun Sharma | E122: Small Business | F122: Bengaluru | G122: Karnataka | H122: South | I122: Furniture | J122: Bookshelf | K122: 3 | L122: 6000 | M122: 0.2 | N122: 14400 | O122: 8003.56 | P122: 6396.44 | Q122: 44.42 | R122: Cash | S122: Marketplace | T122: Neeraj | U122: September | V122: 2024 | W122: Sunday | X122: 3 | Y122: 45605 | Z122: Completed | AA122: Returning | AB122: Low | AC122: No | AD122: 4 | AE122: Arjun | AF122: Sharma | AM122: =IF(Q122>=30,"Good","Needs Improvement") -> Good | AN122: {=_xlfn.IFS(N122<10000,"Low",N122<30000,"Medium",N122>=30000,"High")} -> Medium | AO122: =IF(AND(N122>=30000,P122>=10000),"Yes","No") -> No | AP122: =IF(OR(S122="Online",S122="Marketplace"),"Yes","No") -> Yes | AQ122: =IFERROR(P122/N122,"No Error") -> 0.44419722 | AX122: =IF(P122>=20000,"Excellent",IF(P122>=10000,"Good",IF(P122>=5000,"Average","Low"))) -> Average
A123: ORD10809 | B123: 45513 | C123: CUST1140 | D123: Neha Kapoor | E123: Corporate | F123: Ahmedabad | G123: Gujarat | H123: West | I123: Furniture | J123: Table | K123: 9 | L123: 6000 | M123: 0.2 | N123: 43200 | O123: 28820.7 | P123: 14379.3 | Q123: 33.29 | R123: Cash | S123: Online | T123: Manish | U123: September | V123: 2024 | W123: Sunday | X123: 4 | Y123: 45635 | Z123: Completed | AA123: Returning | AB123: Medium | AC123: Yes | AD123: 2 | AE123: Neha | AF123: Kapoor | AM123: =IF(Q123>=30,"Good","Needs Improvement") -> Good | AN123: {=_xlfn.IFS(N123<10000,"Low",N123<30000,"Medium",N123>=30000,"High")} -> High | AO123: =IF(AND(N123>=30000,P123>=10000),"Yes","No") -> Yes | AP123: =IF(OR(S123="Online",S123="Marketplace"),"Yes","No") -> Yes | AQ123: =IFERROR(P123/N123,"No Error") -> 0.33285417 | AX123: =IF(P123>=20000,"Excellent",IF(P123>=10000,"Good",IF(P123>=5000,"Average","Low"))) -> Good
A124: ORD10021 | B124: 45515 | C124: CUST1099 | D124: Pooja Jain | E124: Corporate | F124: Delhi | G124: Delhi | H124: North | I124: Clothing | J124: Jeans | K124: 4 | L124: 2500 | M124: 0.1 | N124: 9000 | O124: 5007.5 | P124: 3992.5 | Q124: 44.36 | R124: UPI | S124: Retail Store | T124: Anjali | U124: November | V124: 2024 | W124: Friday | X124: 4 | Y124: 45637 | Z124: Completed | AA124: Returning | AB124: High | AC124: No | AD124: 1 | AE124: Pooja | AF124: Jain | AM124: =IF(Q124>=30,"Good","Needs Improvement") -> Good | AN124: {=_xlfn.IFS(N124<10000,"Low",N124<30000,"Medium",N124>=30000,"High")} -> Low | AO124: =IF(AND(N124>=30000,P124>=10000),"Yes","No") -> No | AP124: =IF(OR(S124="Online",S124="Marketplace"),"Yes","No") -> No | AQ124: =IFERROR(P124/N124,"No Error") -> 0.44361111 | AX124: =IF(P124>=20000,"Excellent",IF(P124>=10000,"Good",IF(P124>=5000,"Average","Low"))) -> Low
A125: ORD10142 | B125: 45515 | C125: CUST1073 | D125: Meera Mehta | E125: Corporate | F125: Lucknow | G125: Uttar Pradesh | H125: South | I125: Electronics | J125: Smartphone | K125: 6 | L125: 8000 | M125: 0.05 | N125: 45600 | O125: 29676.14 | P125: 15923.86 | Q125: 34.92 | R125: Net Banking | S125: Retail Store | T125: Kavita | U125: November | V125: 2024 | W125: Friday | X125: 2 | Y125: 45576 | Z125: Completed | AA125: New | AB125: Medium | AC125: Yes | AD125: 5 | AE125: Meera | AF125: Mehta | AM125: =IF(Q125>=30,"Good","Needs Improvement") -> Good | AN125: {=_xlfn.IFS(N125<10000,"Low",N125<30000,"Medium",N125>=30000,"High")} -> High | AO125: =IF(AND(N125>=30000,P125>=10000),"Yes","No") -> Yes | AP125: =IF(OR(S125="Online",S125="Marketplace"),"Yes","No") -> No | AQ125: =IFERROR(P125/N125,"No Error") -> 0.34920746 | AX125: =IF(P125>=20000,"Excellent",IF(P125>=10000,"Good",IF(P125>=5000,"Average","Low"))) -> Good
A126: ORD10865 | B126: 45516 | C126: CUST1306 | D126: Meera Saxena | E126: Consumer | F126: Bengaluru | G126: Karnataka | H126: South | I126: Furniture | J126: Office Chair | K126: 1 | L126: 15000 | M126: 0 | N126: 15000 | O126: 10476.45 | P126: 4523.55 | Q126: 30.16 | R126: Cash | S126: Retail Store | T126: Rohit | U126: December | V126: 2024 | W126: Sunday | X126: 7 | Y126: 15-12-2024 | Z126: Completed | AA126: VIP | AB126: High | AC126: No | AD126: 3 | AE126: Meera | AF126: Saxena | AM126: =IF(Q126>=30,"Good","Needs Improvement") -> Good | AN126: {=_xlfn.IFS(N126<10000,"Low",N126<30000,"Medium",N126>=30000,"High")} -> Medium | AO126: =IF(AND(N126>=30000,P126>=10000),"Yes","No") -> No | AP126: =IF(OR(S126="Online",S126="Marketplace"),"Yes","No") -> No | AQ126: =IFERROR(P126/N126,"No Error") -> 0.30157 | AX126: =IF(P126>=20000,"Excellent",IF(P126>=10000,"Good",IF(P126>=5000,"Average","Low"))) -> Low
A127: ORD10621 | B127: 45537 | C127: CUST1269 | D127: Kavya Gupta | E127: Small Business | F127: Ahmedabad | G127: Gujarat | H127: West | I127: Electronics | J127: Smartphone | K127: 4 | L127: 22000 | M127: 0 | N127: 88000 | O127: 52456.36 | P127: 35543.64 | Q127: 40.39 | R127: Cash | S127: Online | T127: Sneha | U127: February | V127: 2024 | W127: Friday | X127: 7 | Y127: 16-02-2024 | Z127: Pending | AA127: New | AB127: Medium | AC127: No | AD127: 3 | AE127: Kavya | AF127: Gupta | AM127: =IF(Q127>=30,"Good","Needs Improvement") -> Good | AN127: {=_xlfn.IFS(N127<10000,"Low",N127<30000,"Medium",N127>=30000,"High")} -> High | AO127: =IF(AND(N127>=30000,P127>=10000),"Yes","No") -> Yes | AP127: =IF(OR(S127="Online",S127="Marketplace"),"Yes","No") -> Yes | AQ127: =IFERROR(P127/N127,"No Error") -> 0.403905 | AX127: =IF(P127>=20000,"Excellent",IF(P127>=10000,"Good",IF(P127>=5000,"Average","Low"))) -> Excellent
A128: ORD10779 | B128: 45538 | C128: CUST1341 | D128: Sneha Malhotra | E128: Corporate | F128: Jaipur | G128: Rajasthan | H128: South | I128: Electronics | J128: Tablet | K128: 7 | L128: 35000 | M128: 0.15 | N128: 208250 | O128: 129312.71 | P128: 78937.29 | Q128: 37.91 | R128: Debit Card | S128: Online | T128: Amit | U128: March | V128: 2024 | W128: Saturday | X128: 2 | Y128: 45599 | Z128: Completed | AA128: New | AB128: Low | AC128: Yes | AD128: 2 | AE128: Sneha | AF128: Malhotra | AM128: =IF(Q128>=30,"Good","Needs Improvement") -> Good | AN128: {=_xlfn.IFS(N128<10000,"Low",N128<30000,"Medium",N128>=30000,"High")} -> High | AO128: =IF(AND(N128>=30000,P128>=10000),"Yes","No") -> Yes | AP128: =IF(OR(S128="Online",S128="Marketplace"),"Yes","No") -> Yes | AQ128: =IFERROR(P128/N128,"No Error") -> 0.37905061 | AX128: =IF(P128>=20000,"Excellent",IF(P128>=10000,"Good",IF(P128>=5000,"Average","Low"))) -> Excellent
A129: ORD10780 | B129: 45538 | C129: CUST1287 | D129: Vivaan Singh | E129: Consumer | F129: Jaipur | G129: Rajasthan | H129: South | I129: Accessories | J129: Wallet | K129: 9 | L129: 1200 | M129: 0.15 | N129: 9180 | O129: 6073.3 | P129: 3106.7 | Q129: 33.84 | R129: UPI | S129: Online | T129: Kavita | U129: March | V129: 2024 | W129: Saturday | X129: 3 | Y129: 45629 | Z129: Cancelled | AA129: New | AB129: Medium | AC129: Yes | AD129: 5 | AE129: Vivaan | AF129: Singh | AM129: =IF(Q129>=30,"Good","Needs Improvement") -> Good | AN129: {=_xlfn.IFS(N129<10000,"Low",N129<30000,"Medium",N129>=30000,"High")} -> Low | AO129: =IF(AND(N129>=30000,P129>=10000),"Yes","No") -> No | AP129: =IF(OR(S129="Online",S129="Marketplace"),"Yes","No") -> Yes | AQ129: =IFERROR(P129/N129,"No Error") -> 0.33842048 | AX129: =IF(P129>=20000,"Excellent",IF(P129>=10000,"Good",IF(P129>=5000,"Average","Low"))) -> Low
A130: ORD10956 | B130: 45538 | C130: CUST1091 | D130: Ananya Yadav | E130: Consumer | F130: Jaipur | G130: Rajasthan | H130: North | I130: Office Supplies | J130: File Folder | K130: 3 | L130: 350 | M130: 0.2 | N130: 840 | O130: 485.51 | P130: 354.49 | Q130: 42.2 | R130: UPI | S130: Marketplace | T130: Sneha | U130: March | V130: 2024 | W130: Saturday | X130: 7 | Y130: 16-03-2024 | Z130: Completed | AA130: VIP | AB130: High | AC130: No | AD130: 1 | AE130: Ananya | AF130: Yadav | AM130: =IF(Q130>=30,"Good","Needs Improvement") -> Good | AN130: {=_xlfn.IFS(N130<10000,"Low",N130<30000,"Medium",N130>=30000,"High")} -> Low | AO130: =IF(AND(N130>=30000,P130>=10000),"Yes","No") -> No | AP130: =IF(OR(S130="Online",S130="Marketplace"),"Yes","No") -> Yes | AQ130: =IFERROR(P130/N130,"No Error") -> 0.4220119 | AX130: =IF(P130>=20000,"Excellent",IF(P130>=10000,"Good",IF(P130>=5000,"Average","Low"))) -> Low
A131: ORD10058 | B131: 45539 | C131: CUST1233 | D131: Sneha Mishra | E131: Small Business | F131: Bengaluru | G131: Karnataka | H131: West | I131: Electronics | J131: Laptop | K131: 5 | L131: 22000 | M131: 0 | N131: 110000 | O131: 64529.22 | P131: 45470.78 | Q131: 41.34 | R131: Net Banking | S131: Marketplace | T131: Pooja | U131: April | V131: 2024 | W131: Tuesday | X131: 4 | Y131: 13-04-2024 | Z131: Cancelled | AA131: Returning | AB131: High | AC131: Yes | AD131: 4 | AE131: Sneha | AF131: Mishra | AM131: =IF(Q131>=30,"Good","Needs Improvement") -> Good | AN131: {=_xlfn.IFS(N131<10000,"Low",N131<30000,"Medium",N131>=30000,"High")} -> High | AO131: =IF(AND(N131>=30000,P131>=10000),"Yes","No") -> Yes | AP131: =IF(OR(S131="Online",S131="Marketplace"),"Yes","No") -> Yes | AQ131: =IFERROR(P131/N131,"No Error") -> 0.41337073 | AX131: =IF(P131>=20000,"Excellent",IF(P131>=10000,"Good",IF(P131>=5000,"Average","Low"))) -> Excellent
A132: ORD10191 | B132: 45539 | C132: CUST1287 | D132: Karan Mishra | E132: Corporate | F132: Ahmedabad | G132: Gujarat | H132: North | I132: Office Supplies | J132: Printer Paper | K132: 9 | L132: 200 | M132: 0.1 | N132: 1620 | O132: 1215.08 | P132: 404.92 | Q132: 25 | R132: Debit Card | S132: Retail Store | T132: Rahul | U132: April | V132: 2024 | W132: Tuesday | X132: 8 | Y132: 17-04-2024 | Z132: Completed | AA132: VIP | AB132: Medium | AC132: No | AD132: 3 | AE132: Karan | AF132: Mishra | AM132: =IF(Q132>=30,"Good","Needs Improvement") -> Needs Improvement | AN132: {=_xlfn.IFS(N132<10000,"Low",N132<30000,"Medium",N132>=30000,"High")} -> Low | AO132: =IF(AND(N132>=30000,P132>=10000),"Yes","No") -> No | AP132: =IF(OR(S132="Online",S132="Marketplace"),"Yes","No") -> No | AQ132: =IFERROR(P132/N132,"No Error") -> 0.24995062 | AX132: =IF(P132>=20000,"Excellent",IF(P132>=10000,"Good",IF(P132>=5000,"Average","Low"))) -> Low
A133: ORD10571 | B133: 45539 | C133: CUST1170 | D133: Vivaan Verma | E133: Small Business | F133: Mumbai | G133: Maharashtra | H133: North | I133: Electronics | J133: Tablet | K133: 2 | L133: 15000 | M133: 0.2 | N133: 24000 | O133: 16319.91 | P133: 7680.09 | Q133: 32 | R133: Debit Card | S133: Marketplace | T133: Pooja | U133: April | V133: 2024 | W133: Tuesday | X133: 5 | Y133: 14-04-2024 | Z133: Cancelled | AA133: VIP | AB133: High | AC133: No | AD133: 2 | AE133: Vivaan | AF133: Verma | AM133: =IF(Q133>=30,"Good","Needs Improvement") -> Good | AN133: {=_xlfn.IFS(N133<10000,"Low",N133<30000,"Medium",N133>=30000,"High")} -> Medium | AO133: =IF(AND(N133>=30000,P133>=10000),"Yes","No") -> No | AP133: =IF(OR(S133="Online",S133="Marketplace"),"Yes","No") -> Yes | AQ133: =IFERROR(P133/N133,"No Error") -> 0.32000375 | AX133: =IF(P133>=20000,"Excellent",IF(P133>=10000,"Good",IF(P133>=5000,"Average","Low"))) -> Average
A134: ORD10693 | B134: 45540 | C134: CUST1284 | D134: Aditya Chopra | E134: Small Business | F134: Hyderabad | G134: Telangana | H134: South | I134: Clothing | J134: Shirt | K134: 2 | L134: 3500 | M134: 0.1 | N134: 6300 | O134: 4234.81 | P134: 2065.19 | Q134: 32.78 | R134: Cash | S134: Marketplace | T134: Rahul | U134: May | V134: 2024 | W134: Thursday | X134: 6 | Y134: 15-05-2024 | Z134: Completed | AA134: New | AB134: High | AC134: Yes | AD134: 1 | AE134: Aditya | AF134: Chopra | AM134: =IF(Q134>=30,"Good","Needs Improvement") -> Good | AN134: {=_xlfn.IFS(N134<10000,"Low",N134<30000,"Medium",N134>=30000,"High")} -> Low | AO134: =IF(AND(N134>=30000,P134>=10000),"Yes","No") -> No | AP134: =IF(OR(S134="Online",S134="Marketplace"),"Yes","No") -> Yes | AQ134: =IFERROR(P134/N134,"No Error") -> 0.32780794 | AX134: =IF(P134>=20000,"Excellent",IF(P134>=10000,"Good",IF(P134>=5000,"Average","Low"))) -> Low
A135: ORD10978 | B135: 45540 | C135: CUST1188 | D135: Kavya Chopra | E135: Consumer | F135: Chennai | G135: Tamil Nadu | H135: North | I135: Clothing | J135: Shirt | K135: 6 | L135: 2500 | M135: 0.2 | N135: 12000 | O135: 7058.58 | P135: 4941.42 | Q135: 41.18 | R135: Credit Card | S135: Online | T135: Kavita | U135: May | V135: 2024 | W135: Thursday | X135: 1 | Y135: 45570 | Z135: Cancelled | AA135: New | AB135: High | AC135: No | AD135: 4 | AE135: Kavya | AF135: Chopra | AM135: =IF(Q135>=30,"Good","Needs Improvement") -> Good | AN135: {=_xlfn.IFS(N135<10000,"Low",N135<30000,"Medium",N135>=30000,"High")} -> Medium | AO135: =IF(AND(N135>=30000,P135>=10000),"Yes","No") -> No | AP135: =IF(OR(S135="Online",S135="Marketplace"),"Yes","No") -> Yes | AQ135: =IFERROR(P135/N135,"No Error") -> 0.411785 | AX135: =IF(P135>=20000,"Excellent",IF(P135>=10000,"Good",IF(P135>=5000,"Average","Low"))) -> Low
A136: ORD10846 | B136: 45541 | C136: CUST1101 | D136: Rahul Singh | E136: Consumer | F136: Mumbai | G136: Maharashtra | H136: East | I136: Accessories | J136: Backpack | K136: 5 | L136: 800 | M136: 0.05 | N136: 3800 | O136: 2841.48 | P136: 958.52 | Q136: 25.22 | R136: Cash | S136: Online | T136: Rohit | U136: June | V136: 2024 | W136: Sunday | X136: 4 | Y136: 13-06-2024 | Z136: Completed | AA136: New | AB136: High | AC136: Yes | AD136: 1 | AE136: Rahul | AF136: Singh | AM136: =IF(Q136>=30,"Good","Needs Improvement") -> Needs Improvement | AN136: {=_xlfn.IFS(N136<10000,"Low",N136<30000,"Medium",N136>=30000,"High")} -> Low | AO136: =IF(AND(N136>=30000,P136>=10000),"Yes","No") -> No | AP136: =IF(OR(S136="Online",S136="Marketplace"),"Yes","No") -> Yes | AQ136: =IFERROR(P136/N136,"No Error") -> 0.25224211 | AX136: =IF(P136>=20000,"Excellent",IF(P136>=10000,"Good",IF(P136>=5000,"Average","Low"))) -> Low
A137: ORD10931 | B137: 45541 | C137: CUST1202 | D137: Ishita Chopra | E137: Consumer | F137: Delhi | G137: Delhi | H137: North | I137: Office Supplies | J137: Printer Paper | K137: 4 | L137: 800 | M137: 0.15 | N137: 2720 | O137: 2111.67 | P137: 608.33 | Q137: 22.37 | R137: UPI | S137: Marketplace | T137: Neeraj | U137: June | V137: 2024 | W137: Sunday | X137: 8 | Y137: 17-06-2024 | Z137: Completed | AA137: VIP | AB137: Low | AC137: Yes | AD137: 4 | AE137: Ishita | AF137: Chopra | AM137: =IF(Q137>=30,"Good","Needs Improvement") -> Needs Improvement | AN137: {=_xlfn.IFS(N137<10000,"Low",N137<30000,"Medium",N137>=30000,"High")} -> Low | AO137: =IF(AND(N137>=30000,P137>=10000),"Yes","No") -> No | AP137: =IF(OR(S137="Online",S137="Marketplace"),"Yes","No") -> Yes | AQ137: =IFERROR(P137/N137,"No Error") -> 0.22365074 | AX137: =IF(P137>=20000,"Excellent",IF(P137>=10000,"Good",IF(P137>=5000,"Average","Low"))) -> Low
...

Sheet Analaysis
A1: Product | B1: Total sales | D1: Salesperson | E1: Total Sales | G1: Month | H1: Total sales | J1: Year | K1: Total sales | M1: Profit Analaysis | N1: Total sales | P1: Profit Margin Analysis | Q1: Average Profit Margin | S1: Discount Analaysis | T1: Average Discount | V1: Product | W1: Category | X1: Unit price | Z1: Search Product | AA1: Category Result | AB1: Unit Price Result | AD1: Product | AE1: Table | AF1: Desk | AG1: Jeans | AH1: Shirt | AJ1: Search Product | AK1: Category | AL1: Unit price | AN1: Date Functions | BD1: Search product | BE1: Category | BF1: Unit price | BH1: Search Product | BI1: Category | BJ1: Unit Price | BL1: Filter | BN1: Unique | BP1: Sort | BR1: What if Analaysis | BU1: Goal seek
A2: {=_xlfn.UNIQUE(Sheet1!J2:J1001)} -> Table | B2: =SUMIFS(Sheet1!$N$2:$N$1001,Sheet1!$J$2:$J$1001,A2) -> 1352275 | D2: {=_xlfn.UNIQUE(Sheet1!T2:T1001)} -> Sneha | E2: =SUMIFS(Sheet1!$N$2:$N$1001,Sheet1!$T$2:$T$1001,D2) -> 2992322.5 | G2: {=_xlfn.UNIQUE(Sheet1!U2:U1001)} -> March | H2: =SUMIFS(Sheet1!$N$2:$N$1001,Sheet1!$U$2:$U$1001,G2) -> 2618520 | J2: {=_xlfn.UNIQUE(Sheet1!V2:V1001)} -> 2024 | K2: =SUMIFS(Sheet1!$N$2:$N$1001,Sheet1!$V$2:$V$1001,J2) -> 16651332 | M2: Total Profit | N2: =SUM(Sheet1!P2:P1001) -> 9519984.1 | P2: Average Profit Margin | Q2: =AVERAGE(Sheet1!Q2:Q1001) -> 31.33576 | S2: Average Discount | T2: =AVERAGE(Sheet1!M2:M1001) -> 0.10135 | V2: =Sheet1!J2 -> Table | W2: =Sheet1!I2 -> Furniture | X2: =Sheet1!L2 -> 4000 | Z2: Table | AA2: =VLOOKUP(Z2,$V$2:$X$11,2,FALSE) -> Furniture | AB2: =VLOOKUP(Z2,$V$2:$X$11,3,FALSE) -> 4000 | AD2: Unit price | AE2: 4000 | AF2: 4000 | AG2: 1800 | AH2: 700 | AJ2: Laptop | AK2: =INDEX(Sheet1!$I$2:$I$1001,MATCH(AJ2,Sheet1!$J$2:$J$1001,0)) -> Electronics | AL2: =INDEX(Sheet1!$L$2:$L$1001,MATCH(AJ2,Sheet1!$J$2:$J$1001,0)) -> 35000 | AN2: Order_Date | AO2: Days | AP2: Month Number | AQ2: Year | AR2: Month-year | AS2: Date Created | AT2: Days Since Order | AU2: First 3 Letters | AV2: Last 2 Letters | AW2: Middle Letters | AX2: Name Length | AY2: Upper Name | AZ2: Lower Name | BA2: Proper Name | BB2: Full Name | BD2: Laptop | BE2: =INDEX(Sheet1!I2:I1001,MATCH("Laptop",Sheet1!J2:J1001,0)) -> Electronics | BF2: =INDEX(Sheet1!L2:L1001,MATCH("Laptop",Sheet1!J2:J1001,0)) -> 35000 | BH2: Laptop | BI2: =_xlfn.XLOOKUP("Laptop",Sheet1!J2:J1001,Sheet1!I2:I1001,"Not Found",0) -> Electronics | BJ2: =_xlfn.XLOOKUP("Laptop",Sheet1!J2:J1001,Sheet1!L2:L1001,"Not Found",0) -> 35000 | BL2: {=_xlfn._xlws.FILTER(Sheet1!J2:J1001,Sheet1!I2:I1001="Electronics")} -> Smartphone | BN2: {=_xlfn.UNIQUE(Sheet1!I2:I1001)} -> Furniture | BP2: {=_xlfn._xlws.SORT(_xlfn.UNIQUE(Sheet1!I2:I1001))} -> Accessories | BR2: Current Sales | BS2: =SUM(Sheet1!N2:N1001) -> 30311250 | BU2: Target Sales | BV2: 35000000
A3: Desk | B3: =SUMIFS(Sheet1!$N$2:$N$1001,Sheet1!$J$2:$J$1001,A3) -> 1791875 | D3: Kavita | E3: =SUMIFS(Sheet1!$N$2:$N$1001,Sheet1!$T$2:$T$1001,D3) -> 3337090 | G3: May | H3: =SUMIFS(Sheet1!$N$2:$N$1001,Sheet1!$U$2:$U$1001,G3) -> 1121067.5 | J3: 2025 | K3: =SUMIFS(Sheet1!$N$2:$N$1001,Sheet1!$V$2:$V$1001,J3) -> 13659918 | V3: =Sheet1!J3 -> Desk | W3: =Sheet1!I3 -> Furniture | X3: =Sheet1!L3 -> 4000 | Z3: Desk | AA3: =VLOOKUP(Z3,$V$2:$X$11,2,FALSE) -> Furniture | AB3: =VLOOKUP(Z3,$V$2:$X$11,3,FALSE) -> 4000 | AN3: =Sheet1!B2 -> 45294 | AO3: =IFERROR(DAY(AN3),VALUE(LEFT(AN3,2))) -> 3 | AP3: =IFERROR(MONTH(AN3),VALUE(MID(AN3,4,2))) -> 1 | AQ3: =IFERROR(YEAR(AN3),VALUE(RIGHT(AN3,4))) -> 2024 | AR3: =IF(ISNUMBER(AN3),TEXT(AN3,"mmm-yyyy"),TEXT(DATE(VALUE(RIGHT(AN3,4)),VALUE(MID(AN3,4,2)),VALUE(LEFT(AN3,2))),"mmm-yyyy")) -> Jan-2024 | AS3: =DATE(AQ3,AP3,AO3) -> 45294 | AT3: =TODAY()-AS3 -> 984 | AU3: =LEFT(Sheet1!AE2,3) -> Adi | AV3: =RIGHT(Sheet1!AF2,2) -> ta | AW3: =MID(Sheet1!AE2,2,3) -> dit | AX3: =LEN(Sheet1!AE2) -> 5 | AY3: =UPPER(Sheet1!AE2) -> ADITI | AZ3: =LOWER(Sheet1!AE2) -> aditi | BA3: =PROPER(Sheet1!AE2) -> Aditi | BB3: =_xlfn.CONCAT(Sheet1!AE2," ",Sheet1!AF2) -> Aditi Gupta | BL3: Smartphone | BN3: Clothing | BP3: Clothing | BR3: Target Sales | BS3: =SUM(Sheet1!N2:N1001) -> 30311250 | BU3: Current Sales | BV3: =SUM(Sheet1!N2:N1001) -> 30311250
A4: Jeans | B4: =SUMIFS(Sheet1!$N$2:$N$1001,Sheet1!$J$2:$J$1001,A4) -> 319065 | D4: Neeraj | E4: =SUMIFS(Sheet1!$N$2:$N$1001,Sheet1!$T$2:$T$1001,D4) -> 2937487.5 | G4: June | H4: =SUMIFS(Sheet1!$N$2:$N$1001,Sheet1!$U$2:$U$1001,G4) -> 2765790 | V4: =Sheet1!J4 -> Jeans | W4: =Sheet1!I4 -> Clothing | X4: =Sheet1!L4 -> 1800 | Z4: Jeans | AA4: =VLOOKUP(Z4,$V$2:$X$11,2,FALSE) -> Clothing | AB4: =VLOOKUP(Z4,$V$2:$X$11,3,FALSE) -> 1800 | AD4: Search product | AE4: Table | AN4: =Sheet1!B3 -> 45294 | AO4: =IFERROR(DAY(AN4),VALUE(LEFT(AN4,2))) -> 3 | AP4: =IFERROR(MONTH(AN4),VALUE(MID(AN4,4,2))) -> 1 | AQ4: =IFERROR(YEAR(AN4),VALUE(RIGHT(AN4,4))) -> 2024 | AR4: =IF(ISNUMBER(AN4),TEXT(AN4,"mmm-yyyy"),TEXT(DATE(VALUE(RIGHT(AN4,4)),VALUE(MID(AN4,4,2)),VALUE(LEFT(AN4,2))),"mmm-yyyy")) -> Jan-2024 | AS4: =DATE(AQ4,AP4,AO4) -> 45294 | AT4: =TODAY()-AS4 -> 984 | AU4: =LEFT(Sheet1!AE3,3) -> Arj | AV4: =RIGHT(Sheet1!AF3,2) -> ra | AW4: =MID(Sheet1!AE3,2,3) -> rju | AX4: =LEN(Sheet1!AE3) -> 5 | AY4: =UPPER(Sheet1!AE3) -> ARJUN | AZ4: =LOWER(Sheet1!AE3) -> arjun | BA4: =PROPER(Sheet1!AE3) -> Arjun | BB4: =_xlfn.CONCAT(Sheet1!AE3," ",Sheet1!AF3) -> Arjun Chopra | BL4: Laptop | BN4: Electronics | BP4: Electronics
A5: Shirt | B5: =SUMIFS(Sheet1!$N$2:$N$1001,Sheet1!$J$2:$J$1001,A5) -> 318170 | D5: Vikas | E5: =SUMIFS(Sheet1!$N$2:$N$1001,Sheet1!$T$2:$T$1001,D5) -> 1933662.5 | G5: September | H5: =SUMIFS(Sheet1!$N$2:$N$1001,Sheet1!$U$2:$U$1001,G5) -> 3190750 | V5: =Sheet1!J5 -> Shirt | W5: =Sheet1!I5 -> Clothing | X5: =Sheet1!L5 -> 700 | Z5: Shirt | AA5: =VLOOKUP(Z5,$V$2:$X$11,2,FALSE) -> Clothing | AB5: =VLOOKUP(Z5,$V$2:$X$11,3,FALSE) -> 700 | AD5: Desk | AE5: =HLOOKUP(AD5,$AE$1:$AH$2,2,FALSE) -> 4000 | AN5: =Sheet1!B4 -> 45294 | AO5: =IFERROR(DAY(AN5),VALUE(LEFT(AN5,2))) -> 3 | AP5: =IFERROR(MONTH(AN5),VALUE(MID(AN5,4,2))) -> 1 | AQ5: =IFERROR(YEAR(AN5),VALUE(RIGHT(AN5,4))) -> 2024 | AR5: =IF(ISNUMBER(AN5),TEXT(AN5,"mmm-yyyy"),TEXT(DATE(VALUE(RIGHT(AN5,4)),VALUE(MID(AN5,4,2)),VALUE(LEFT(AN5,2))),"mmm-yyyy")) -> Jan-2024 | AS5: =DATE(AQ5,AP5,AO5) -> 45294 | AT5: =TODAY()-AS5 -> 984 | AU5: =LEFT(Sheet1!AE4,3) -> Vik | AV5: =RIGHT(Sheet1!AF4,2) -> av | AW5: =MID(Sheet1!AE4,2,3) -> ikr | AX5: =LEN(Sheet1!AE4) -> 6 | AY5: =UPPER(Sheet1!AE4) -> VIKRAM | AZ5: =LOWER(Sheet1!AE4) -> vikram | BA5: =PROPER(Sheet1!AE4) -> Vikram | BB5: =_xlfn.CONCAT(Sheet1!AE4," ",Sheet1!AF4) -> Vikram Yadav | BL5: Tablet | BN5: Office Supplies | BP5: Furniture
A6: Smartphone | B6: =SUMIFS(Sheet1!$N$2:$N$1001,Sheet1!$J$2:$J$1001,A6) -> 4899550 | D6: Pooja | E6: =SUMIFS(Sheet1!$N$2:$N$1001,Sheet1!$T$2:$T$1001,D6) -> 2963150 | G6: October | H6: =SUMIFS(Sheet1!$N$2:$N$1001,Sheet1!$U$2:$U$1001,G6) -> 3112707.5 | V6: =Sheet1!J6 -> Smartphone | W6: =Sheet1!I6 -> Electronics | X6: =Sheet1!L6 -> 22000 | Z6: Smartphone | AA6: =VLOOKUP(Z6,$V$2:$X$11,2,FALSE) -> Electronics | AB6: =VLOOKUP(Z6,$V$2:$X$11,3,FALSE) -> 22000 | AN6: =Sheet1!B5 -> 45294 | AO6: =IFERROR(DAY(AN6),VALUE(LEFT(AN6,2))) -> 3 | AP6: =IFERROR(MONTH(AN6),VALUE(MID(AN6,4,2))) -> 1 | AQ6: =IFERROR(YEAR(AN6),VALUE(RIGHT(AN6,4))) -> 2024 | AR6: =IF(ISNUMBER(AN6),TEXT(AN6,"mmm-yyyy"),TEXT(DATE(VALUE(RIGHT(AN6,4)),VALUE(MID(AN6,4,2)),VALUE(LEFT(AN6,2))),"mmm-yyyy")) -> Jan-2024 | AS6: =DATE(AQ6,AP6,AO6) -> 45294 | AT6: =TODAY()-AS6 -> 984 | AU6: =LEFT(Sheet1!AE5,3) -> Aar | AV6: =RIGHT(Sheet1!AF5,2) -> al | AW6: =MID(Sheet1!AE5,2,3) -> ara | AX6: =LEN(Sheet1!AE5) -> 5 | AY6: =UPPER(Sheet1!AE5) -> AARAV | AZ6: =LOWER(Sheet1!AE5) -> aarav | BA6: =PROPER(Sheet1!AE5) -> Aarav | BB6: =_xlfn.CONCAT(Sheet1!AE5," ",Sheet1!AF5) -> Aarav Agarwal | BL6: Monitor | BN6: Accessories | BP6: Office Supplies
A7: Notebook | B7: =SUMIFS(Sheet1!$N$2:$N$1001,Sheet1!$J$2:$J$1001,A7) -> 84285 | D7: Manish | E7: =SUMIFS(Sheet1!$N$2:$N$1001,Sheet1!$T$2:$T$1001,D7) -> 3934230 | G7: December | H7: =SUMIFS(Sheet1!$N$2:$N$1001,Sheet1!$U$2:$U$1001,G7) -> 3395160 | V7: =Sheet1!J7 -> Notebook | W7: =Sheet1!I7 -> Office Supplies | X7: =Sheet1!L7 -> 350 | Z7: Notebook | AA7: =VLOOKUP(Z7,$V$2:$X$11,2,FALSE) -> Office Supplies | AB7: =VLOOKUP(Z7,$V$2:$X$11,3,FALSE) -> 350 | AN7: =Sheet1!B6 -> 45296 | AO7: =IFERROR(DAY(AN7),VALUE(LEFT(AN7,2))) -> 5 | AP7: =IFERROR(MONTH(AN7),VALUE(MID(AN7,4,2))) -> 1 | AQ7: =IFERROR(YEAR(AN7),VALUE(RIGHT(AN7,4))) -> 2024 | AR7: =IF(ISNUMBER(AN7),TEXT(AN7,"mmm-yyyy"),TEXT(DATE(VALUE(RIGHT(AN7,4)),VALUE(MID(AN7,4,2)),VALUE(LEFT(AN7,2))),"mmm-yyyy")) -> Jan-2024 | AS7: =DATE(AQ7,AP7,AO7) -> 45296 | AT7: =TODAY()-AS7 -> 982 | AU7: =LEFT(Sheet1!AE6,3) -> Roh | AV7: =RIGHT(Sheet1!AF6,2) -> in | AW7: =MID(Sheet1!AE6,2,3) -> oha | AX7: =LEN(Sheet1!AE6) -> 5 | AY7: =UPPER(Sheet1!AE6) -> ROHAN | AZ7: =LOWER(Sheet1!AE6) -> rohan | BA7: =PROPER(Sheet1!AE6) -> Rohan | BB7: =_xlfn.CONCAT(Sheet1!AE6," ",Sheet1!AF6) -> Rohan Jain | BL7: Laptop
A8: Jacket | B8: =SUMIFS(Sheet1!$N$2:$N$1001,Sheet1!$J$2:$J$1001,A8) -> 420105 | D8: Rahul | E8: =SUMIFS(Sheet1!$N$2:$N$1001,Sheet1!$T$2:$T$1001,D8) -> 2934365 | G8: January | H8: =SUMIFS(Sheet1!$N$2:$N$1001,Sheet1!$U$2:$U$1001,G8) -> 1889497.5 | V8: Jacket | W8: =Sheet1!I8 -> Clothing | X8: =Sheet1!L8 -> 700 | Z8: Jacket | AA8: Clothing | AB8: 700 | AN8: =Sheet1!B7 -> 45296 | AO8: =IFERROR(DAY(AN8),VALUE(LEFT(AN8,2))) -> 5 | AP8: =IFERROR(MONTH(AN8),VALUE(MID(AN8,4,2))) -> 1 | AQ8: =IFERROR(YEAR(AN8),VALUE(RIGHT(AN8,4))) -> 2024 | AR8: =IF(ISNUMBER(AN8),TEXT(AN8,"mmm-yyyy"),TEXT(DATE(VALUE(RIGHT(AN8,4)),VALUE(MID(AN8,4,2)),VALUE(LEFT(AN8,2))),"mmm-yyyy")) -> Jan-2024 | AS8: =DATE(AQ8,AP8,AO8) -> 45296 | AT8: =TODAY()-AS8 -> 982 | AU8: =LEFT(Sheet1!AE7,3) -> Kar | AV8: =RIGHT(Sheet1!AF7,2) -> ar | AW8: =MID(Sheet1!AE7,2,3) -> ara | AX8: =LEN(Sheet1!AE7) -> 5 | AY8: =UPPER(Sheet1!AE7) -> KARAN | AZ8: =LOWER(Sheet1!AE7) -> karan | BA8: =PROPER(Sheet1!AE7) -> Karan | BB8: =_xlfn.CONCAT(Sheet1!AE7," ",Sheet1!AF7) -> Karan Kumar | BL8: Monitor
A9: Laptop | B9: =SUMIFS(Sheet1!$N$2:$N$1001,Sheet1!$J$2:$J$1001,A9) -> 3513350 | D9: Amit | E9: =SUMIFS(Sheet1!$N$2:$N$1001,Sheet1!$T$2:$T$1001,D9) -> 3295187.5 | G9: February | H9: =SUMIFS(Sheet1!$N$2:$N$1001,Sheet1!$U$2:$U$1001,G9) -> 2361560 | V9: =Sheet1!J9 -> Smartphone | W9: =Sheet1!I9 -> Electronics | X9: =Sheet1!L9 -> 50000 | Z9: Smartphone | AA9: =VLOOKUP(Z9,$V$2:$X$11,2,FALSE) -> Electronics | AB9: =VLOOKUP(Z9,$V$2:$X$11,3,FALSE) -> 22000 | AN9: =Sheet1!B8 -> 45297 | AO9: =IFERROR(DAY(AN9),VALUE(LEFT(AN9,2))) -> 6 | AP9: =IFERROR(MONTH(AN9),VALUE(MID(AN9,4,2))) -> 1 | AQ9: =IFERROR(YEAR(AN9),VALUE(RIGHT(AN9,4))) -> 2024 | AR9: =IF(ISNUMBER(AN9),TEXT(AN9,"mmm-yyyy"),TEXT(DATE(VALUE(RIGHT(AN9,4)),VALUE(MID(AN9,4,2)),VALUE(LEFT(AN9,2))),"mmm-yyyy")) -> Jan-2024 | AS9: =DATE(AQ9,AP9,AO9) -> 45297 | AT9: =TODAY()-AS9 -> 981 | AU9: =LEFT(Sheet1!AE8,3) -> Kav | AV9: =RIGHT(Sheet1!AF8,2) -> ra | AW9: =MID(Sheet1!AE8,2,3) -> avy | AX9: =LEN(Sheet1!AE8) -> 5 | AY9: =UPPER(Sheet1!AE8) -> KAVYA | AZ9: =LOWER(Sheet1!AE8) -> kavya | BA9: =PROPER(Sheet1!AE8) -> Kavya | BB9: =_xlfn.CONCAT(Sheet1!AE8," ",Sheet1!AF8) -> Kavya Chopra | BL9: Laptop
A10: Tablet | B10: =SUMIFS(Sheet1!$N$2:$N$1001,Sheet1!$J$2:$J$1001,A10) -> 4546350 | D10: Anjali | E10: =SUMIFS(Sheet1!$N$2:$N$1001,Sheet1!$T$2:$T$1001,D10) -> 2952162.5 | G10: April | H10: =SUMIFS(Sheet1!$N$2:$N$1001,Sheet1!$U$2:$U$1001,G10) -> 1803637.5 | V10: =Sheet1!J10 -> Laptop | W10: =Sheet1!I10 -> Electronics | X10: =Sheet1!L10 -> 35000 | Z10: Laptop | AA10: =VLOOKUP(Z10,$V$2:$X$11,2,FALSE) -> Electronics | AB10: =VLOOKUP(Z10,$V$2:$X$11,3,FALSE) -> 35000 | AN10: =Sheet1!B9 -> 45300 | AO10: =IFERROR(DAY(AN10),VALUE(LEFT(AN10,2))) -> 9 | AP10: =IFERROR(MONTH(AN10),VALUE(MID(AN10,4,2))) -> 1 | AQ10: =IFERROR(YEAR(AN10),VALUE(RIGHT(AN10,4))) -> 2024 | AR10: =IF(ISNUMBER(AN10),TEXT(AN10,"mmm-yyyy"),TEXT(DATE(VALUE(RIGHT(AN10,4)),VALUE(MID(AN10,4,2)),VALUE(LEFT(AN10,2))),"mmm-yyyy")) -> Jan-2024 | AS10: =DATE(AQ10,AP10,AO10) -> 45300 | AT10: =TODAY()-AS10 -> 978 | AU10: =LEFT(Sheet1!AE9,3) -> Pri | AV10: =RIGHT(Sheet1!AF9,2) -> ra | AW10: =MID(Sheet1!AE9,2,3) -> riy | AX10: =LEN(Sheet1!AE9) -> 5 | AY10: =UPPER(Sheet1!AE9) -> PRIYA | AZ10: =LOWER(Sheet1!AE9) -> priya | BA10: =PROPER(Sheet1!AE9) -> Priya | BB10: =_xlfn.CONCAT(Sheet1!AE9," ",Sheet1!AF9) -> Priya Malhotra | BL10: Laptop
A11: Watch | B11: =SUMIFS(Sheet1!$N$2:$N$1001,Sheet1!$J$2:$J$1001,A11) -> 321750 | D11: Rohit | E11: =SUMIFS(Sheet1!$N$2:$N$1001,Sheet1!$T$2:$T$1001,D11) -> 3031592.5 | G11: July | H11: =SUMIFS(Sheet1!$N$2:$N$1001,Sheet1!$U$2:$U$1001,G11) -> 3495020 | V11: =Sheet1!J11 -> Table | W11: =Sheet1!I11 -> Furniture | X11: =Sheet1!L11 -> 4000 | Z11: Table | AA11: =VLOOKUP(Z11,$V$2:$X$11,2,FALSE) -> Furniture | AB11: =VLOOKUP(Z11,$V$2:$X$11,3,FALSE) -> 4000 | AN11: =Sheet1!B10 -> 45300 | AO11: =IFERROR(DAY(AN11),VALUE(LEFT(AN11,2))) -> 9 | AP11: =IFERROR(MONTH(AN11),VALUE(MID(AN11,4,2))) -> 1 | AQ11: =IFERROR(YEAR(AN11),VALUE(RIGHT(AN11,4))) -> 2024 | AR11: =IF(ISNUMBER(AN11),TEXT(AN11,"mmm-yyyy"),TEXT(DATE(VALUE(RIGHT(AN11,4)),VALUE(MID(AN11,4,2)),VALUE(LEFT(AN11,2))),"mmm-yyyy")) -> Jan-2024 | AS11: =DATE(AQ11,AP11,AO11) -> 45300 | AT11: =TODAY()-AS11 -> 978 | AU11: =LEFT(Sheet1!AE10,3) -> Sim | AV11: =RIGHT(Sheet1!AF10,2) -> av | AW11: =MID(Sheet1!AE10,2,3) -> imr | AX11: =LEN(Sheet1!AE10) -> 6 | AY11: =UPPER(Sheet1!AE10) -> SIMRAN | AZ11: =LOWER(Sheet1!AE10) -> simran | BA11: =PROPER(Sheet1!AE10) -> Simran | BB11: =_xlfn.CONCAT(Sheet1!AE10," ",Sheet1!AF10) -> Simran Yadav | BL11: Tablet
A12: Printer Paper | B12: =SUMIFS(Sheet1!$N$2:$N$1001,Sheet1!$J$2:$J$1001,A12) -> 82737.5 | G12: August | H12: =SUMIFS(Sheet1!$N$2:$N$1001,Sheet1!$U$2:$U$1001,G12) -> 2480745 | AN12: =Sheet1!B11 -> 45301 | AO12: =IFERROR(DAY(AN12),VALUE(LEFT(AN12,2))) -> 10 | AP12: =IFERROR(MONTH(AN12),VALUE(MID(AN12,4,2))) -> 1 | AQ12: =IFERROR(YEAR(AN12),VALUE(RIGHT(AN12,4))) -> 2024 | AR12: =IF(ISNUMBER(AN12),TEXT(AN12,"mmm-yyyy"),TEXT(DATE(VALUE(RIGHT(AN12,4)),VALUE(MID(AN12,4,2)),VALUE(LEFT(AN12,2))),"mmm-yyyy")) -> Jan-2024 | AS12: =DATE(AQ12,AP12,AO12) -> 45301 | AT12: =TODAY()-AS12 -> 977 | AU12: =LEFT(Sheet1!AE11,3) -> Nis | AV12: =RIGHT(Sheet1!AF11,2) -> av | AW12: =MID(Sheet1!AE11,2,3) -> ish | AX12: =LEN(Sheet1!AE11) -> 5 | AY12: =UPPER(Sheet1!AE11) -> NISHA | AZ12: =LOWER(Sheet1!AE11) -> nisha | BA12: =PROPER(Sheet1!AE11) -> Nisha | BB12: =_xlfn.CONCAT(Sheet1!AE11," ",Sheet1!AF11) -> Nisha Yadav | BL12: Smartphone
A13: Backpack | B13: =SUMIFS(Sheet1!$N$2:$N$1001,Sheet1!$J$2:$J$1001,A13) -> 381040 | G13: November | H13: =SUMIFS(Sheet1!$N$2:$N$1001,Sheet1!$U$2:$U$1001,G13) -> 2076795 | AN13: =Sheet1!B12 -> 45301 | AO13: =IFERROR(DAY(AN13),VALUE(LEFT(AN13,2))) -> 10 | AP13: =IFERROR(MONTH(AN13),VALUE(MID(AN13,4,2))) -> 1 | AQ13: =IFERROR(YEAR(AN13),VALUE(RIGHT(AN13,4))) -> 2024 | AR13: =IF(ISNUMBER(AN13),TEXT(AN13,"mmm-yyyy"),TEXT(DATE(VALUE(RIGHT(AN13,4)),VALUE(MID(AN13,4,2)),VALUE(LEFT(AN13,2))),"mmm-yyyy")) -> Jan-2024 | AS13: =DATE(AQ13,AP13,AO13) -> 45301 | AT13: =TODAY()-AS13 -> 977 | AU13: =LEFT(Sheet1!AE12,3) -> Vik | AV13: =RIGHT(Sheet1!AF12,2) -> ma | AW13: =MID(Sheet1!AE12,2,3) -> ikr | AX13: =LEN(Sheet1!AE12) -> 6 | AY13: =UPPER(Sheet1!AE12) -> VIKRAM | AZ13: =LOWER(Sheet1!AE12) -> vikram | BA13: =PROPER(Sheet1!AE12) -> Vikram | BB13: =_xlfn.CONCAT(Sheet1!AE12," ",Sheet1!AF12) -> Vikram Sharma | BL13: Monitor
A14: Monitor | B14: =SUMIFS(Sheet1!$N$2:$N$1001,Sheet1!$J$2:$J$1001,A14) -> 4066900 | AN14: =Sheet1!B13 -> 45303 | AO14: =IFERROR(DAY(AN14),VALUE(LEFT(AN14,2))) -> 12 | AP14: =IFERROR(MONTH(AN14),VALUE(MID(AN14,4,2))) -> 1 | AQ14: =IFERROR(YEAR(AN14),VALUE(RIGHT(AN14,4))) -> 2024 | AR14: =IF(ISNUMBER(AN14),TEXT(AN14,"mmm-yyyy"),TEXT(DATE(VALUE(RIGHT(AN14,4)),VALUE(MID(AN14,4,2)),VALUE(LEFT(AN14,2))),"mmm-yyyy")) -> Jan-2024 | AS14: =DATE(AQ14,AP14,AO14) -> 45303 | AT14: =TODAY()-AS14 -> 975 | AU14: =LEFT(Sheet1!AE13,3) -> Roh | AV14: =RIGHT(Sheet1!AF13,2) -> ra | AW14: =MID(Sheet1!AE13,2,3) -> oha | AX14: =LEN(Sheet1!AE13) -> 5 | AY14: =UPPER(Sheet1!AE13) -> ROHAN | AZ14: =LOWER(Sheet1!AE13) -> rohan | BA14: =PROPER(Sheet1!AE13) -> Rohan | BB14: =_xlfn.CONCAT(Sheet1!AE13," ",Sheet1!AF13) -> Rohan Chopra | BL14: Headphones
A15: Belt | B15: =SUMIFS(Sheet1!$N$2:$N$1001,Sheet1!$J$2:$J$1001,A15) -> 331880 | AN15: =Sheet1!B14 -> 45323 | AO15: =IFERROR(DAY(AN15),VALUE(LEFT(AN15,2))) -> 1 | AP15: =IFERROR(MONTH(AN15),VALUE(MID(AN15,4,2))) -> 2 | AQ15: =IFERROR(YEAR(AN15),VALUE(RIGHT(AN15,4))) -> 2024 | AR15: =IF(ISNUMBER(AN15),TEXT(AN15,"mmm-yyyy"),TEXT(DATE(VALUE(RIGHT(AN15,4)),VALUE(MID(AN15,4,2)),VALUE(LEFT(AN15,2))),"mmm-yyyy")) -> Feb-2024 | AS15: =DATE(AQ15,AP15,AO15) -> 45323 | AT15: =TODAY()-AS15 -> 955 | AU15: =LEFT(Sheet1!AE14,3) -> Poo | AV15: =RIGHT(Sheet1!AF14,2) -> ta | AW15: =MID(Sheet1!AE14,2,3) -> ooj | AX15: =LEN(Sheet1!AE14) -> 5 | AY15: =UPPER(Sheet1!AE14) -> POOJA | AZ15: =LOWER(Sheet1!AE14) -> pooja | BA15: =PROPER(Sheet1!AE14) -> Pooja | BB15: =_xlfn.CONCAT(Sheet1!AE14," ",Sheet1!AF14) -> Pooja Mehta | BL15: Headphones
A16: Shoes | B16: =SUMIFS(Sheet1!$N$2:$N$1001,Sheet1!$J$2:$J$1001,A16) -> 388250 | AN16: =Sheet1!B15 -> 45323 | AO16: =IFERROR(DAY(AN16),VALUE(LEFT(AN16,2))) -> 1 | AP16: =IFERROR(MONTH(AN16),VALUE(MID(AN16,4,2))) -> 2 | AQ16: =IFERROR(YEAR(AN16),VALUE(RIGHT(AN16,4))) -> 2024 | AR16: =IF(ISNUMBER(AN16),TEXT(AN16,"mmm-yyyy"),TEXT(DATE(VALUE(RIGHT(AN16,4)),VALUE(MID(AN16,4,2)),VALUE(LEFT(AN16,2))),"mmm-yyyy")) -> Feb-2024 | AS16: =DATE(AQ16,AP16,AO16) -> 45323 | AT16: =TODAY()-AS16 -> 955 | AU16: =LEFT(Sheet1!AE15,3) -> Pri | AV16: =RIGHT(Sheet1!AF15,2) -> ma | AW16: =MID(Sheet1!AE15,2,3) -> riy | AX16: =LEN(Sheet1!AE15) -> 5 | AY16: =UPPER(Sheet1!AE15) -> PRIYA | AZ16: =LOWER(Sheet1!AE15) -> priya | BA16: =PROPER(Sheet1!AE15) -> Priya | BB16: =_xlfn.CONCAT(Sheet1!AE15," ",Sheet1!AF15) -> Priya Sharma | BL16: Smartphone
A17: Office Chair | B17: =SUMIFS(Sheet1!$N$2:$N$1001,Sheet1!$J$2:$J$1001,A17) -> 1289950 | AN17: =Sheet1!B16 -> 45324 | AO17: =IFERROR(DAY(AN17),VALUE(LEFT(AN17,2))) -> 2 | AP17: =IFERROR(MONTH(AN17),VALUE(MID(AN17,4,2))) -> 2 | AQ17: =IFERROR(YEAR(AN17),VALUE(RIGHT(AN17,4))) -> 2024 | AR17: =IF(ISNUMBER(AN17),TEXT(AN17,"mmm-yyyy"),TEXT(DATE(VALUE(RIGHT(AN17,4)),VALUE(MID(AN17,4,2)),VALUE(LEFT(AN17,2))),"mmm-yyyy")) -> Feb-2024 | AS17: =DATE(AQ17,AP17,AO17) -> 45324 | AT17: =TODAY()-AS17 -> 954 | AU17: =LEFT(Sheet1!AE16,3) -> Ish | AV17: =RIGHT(Sheet1!AF16,2) -> in | AW17: =MID(Sheet1!AE16,2,3) -> shi | AX17: =LEN(Sheet1!AE16) -> 6 | AY17: =UPPER(Sheet1!AE16) -> ISHITA | AZ17: =LOWER(Sheet1!AE16) -> ishita | BA17: =PROPER(Sheet1!AE16) -> Ishita | BB17: =_xlfn.CONCAT(Sheet1!AE16," ",Sheet1!AF16) -> Ishita Jain | BL17: Tablet
A18: Wallet | B18: =SUMIFS(Sheet1!$N$2:$N$1001,Sheet1!$J$2:$J$1001,A18) -> 150115 | AN18: =Sheet1!B17 -> 45324 | AO18: =IFERROR(DAY(AN18),VALUE(LEFT(AN18,2))) -> 2 | AP18: =IFERROR(MONTH(AN18),VALUE(MID(AN18,4,2))) -> 2 | AQ18: =IFERROR(YEAR(AN18),VALUE(RIGHT(AN18,4))) -> 2024 | AR18: =IF(ISNUMBER(AN18),TEXT(AN18,"mmm-yyyy"),TEXT(DATE(VALUE(RIGHT(AN18,4)),VALUE(MID(AN18,4,2)),VALUE(LEFT(AN18,2))),"mmm-yyyy")) -> Feb-2024 | AS18: =DATE(AQ18,AP18,AO18) -> 45324 | AT18: =TODAY()-AS18 -> 954 | AU18: =LEFT(Sheet1!AE17,3) -> Pri | AV18: =RIGHT(Sheet1!AF17,2) -> ma | AW18: =MID(Sheet1!AE17,2,3) -> riy | AX18: =LEN(Sheet1!AE17) -> 5 | AY18: =UPPER(Sheet1!AE17) -> PRIYA | AZ18: =LOWER(Sheet1!AE17) -> priya | BA18: =PROPER(Sheet1!AE17) -> Priya | BB18: =_xlfn.CONCAT(Sheet1!AE17," ",Sheet1!AF17) -> Priya Verma | BL18: Headphones
A19: Pen Set | B19: =SUMIFS(Sheet1!$N$2:$N$1001,Sheet1!$J$2:$J$1001,A19) -> 96982.5 | AN19: =Sheet1!B18 -> 45325 | AO19: =IFERROR(DAY(AN19),VALUE(LEFT(AN19,2))) -> 3 | AP19: =IFERROR(MONTH(AN19),VALUE(MID(AN19,4,2))) -> 2 | AQ19: =IFERROR(YEAR(AN19),VALUE(RIGHT(AN19,4))) -> 2024 | AR19: =IF(ISNUMBER(AN19),TEXT(AN19,"mmm-yyyy"),TEXT(DATE(VALUE(RIGHT(AN19,4)),VALUE(MID(AN19,4,2)),VALUE(LEFT(AN19,2))),"mmm-yyyy")) -> Feb-2024 | AS19: =DATE(AQ19,AP19,AO19) -> 45325 | AT19: =TODAY()-AS19 -> 953 | AU19: =LEFT(Sheet1!AE18,3) -> Sne | AV19: =RIGHT(Sheet1!AF18,2) -> ta | AW19: =MID(Sheet1!AE18,2,3) -> neh | AX19: =LEN(Sheet1!AE18) -> 5 | AY19: =UPPER(Sheet1!AE18) -> SNEHA | AZ19: =LOWER(Sheet1!AE18) -> sneha | BA19: =PROPER(Sheet1!AE18) -> Sneha | BB19: =_xlfn.CONCAT(Sheet1!AE18," ",Sheet1!AF18) -> Sneha Mehta | BL19: Monitor
A20: File Folder | B20: =SUMIFS(Sheet1!$N$2:$N$1001,Sheet1!$J$2:$J$1001,A20) -> 64612.5 | AN20: =Sheet1!B19 -> 45326 | AO20: =IFERROR(DAY(AN20),VALUE(LEFT(AN20,2))) -> 4 | AP20: =IFERROR(MONTH(AN20),VALUE(MID(AN20,4,2))) -> 2 | AQ20: =IFERROR(YEAR(AN20),VALUE(RIGHT(AN20,4))) -> 2024 | AR20: =IF(ISNUMBER(AN20),TEXT(AN20,"mmm-yyyy"),TEXT(DATE(VALUE(RIGHT(AN20,4)),VALUE(MID(AN20,4,2)),VALUE(LEFT(AN20,2))),"mmm-yyyy")) -> Feb-2024 | AS20: =DATE(AQ20,AP20,AO20) -> 45326 | AT20: =TODAY()-AS20 -> 952 | AU20: =LEFT(Sheet1!AE19,3) -> Riy | AV20: =RIGHT(Sheet1!AF19,2) -> ta | AW20: =MID(Sheet1!AE19,2,3) -> iya | AX20: =LEN(Sheet1!AE19) -> 4 | AY20: =UPPER(Sheet1!AE19) -> RIYA | AZ20: =LOWER(Sheet1!AE19) -> riya | BA20: =PROPER(Sheet1!AE19) -> Riya | BB20: =_xlfn.CONCAT(Sheet1!AE19," ",Sheet1!AF19) -> Riya Gupta | BL20: Smartphone
A21: Sunglasses | B21: =SUMIFS(Sheet1!$N$2:$N$1001,Sheet1!$J$2:$J$1001,A21) -> 281960 | AN21: =Sheet1!B20 -> 45326 | AO21: =IFERROR(DAY(AN21),VALUE(LEFT(AN21,2))) -> 4 | AP21: =IFERROR(MONTH(AN21),VALUE(MID(AN21,4,2))) -> 2 | AQ21: =IFERROR(YEAR(AN21),VALUE(RIGHT(AN21,4))) -> 2024 | AR21: =IF(ISNUMBER(AN21),TEXT(AN21,"mmm-yyyy"),TEXT(DATE(VALUE(RIGHT(AN21,4)),VALUE(MID(AN21,4,2)),VALUE(LEFT(AN21,2))),"mmm-yyyy")) -> Feb-2024 | AS21: =DATE(AQ21,AP21,AO21) -> 45326 | AT21: =TODAY()-AS21 -> 952 | AU21: =LEFT(Sheet1!AE20,3) -> Roh | AV21: =RIGHT(Sheet1!AF20,2) -> ta | AW21: =MID(Sheet1!AE20,2,3) -> oha | AX21: =LEN(Sheet1!AE20) -> 5 | AY21: =UPPER(Sheet1!AE20) -> ROHAN | AZ21: =LOWER(Sheet1!AE20) -> rohan | BA21: =PROPER(Sheet1!AE20) -> Rohan | BB21: =_xlfn.CONCAT(Sheet1!AE20," ",Sheet1!AF20) -> Rohan Gupta | BL21: Tablet
A22: T-Shirt | B22: =SUMIFS(Sheet1!$N$2:$N$1001,Sheet1!$J$2:$J$1001,A22) -> 440780 | AN22: =Sheet1!B21 -> 45326 | AO22: =IFERROR(DAY(AN22),VALUE(LEFT(AN22,2))) -> 4 | AP22: =IFERROR(MONTH(AN22),VALUE(MID(AN22,4,2))) -> 2 | AQ22: =IFERROR(YEAR(AN22),VALUE(RIGHT(AN22,4))) -> 2024 | AR22: =IF(ISNUMBER(AN22),TEXT(AN22,"mmm-yyyy"),TEXT(DATE(VALUE(RIGHT(AN22,4)),VALUE(MID(AN22,4,2)),VALUE(LEFT(AN22,2))),"mmm-yyyy")) -> Feb-2024 | AS22: =DATE(AQ22,AP22,AO22) -> 45326 | AT22: =TODAY()-AS22 -> 952 | AU22: =LEFT(Sheet1!AE21,3) -> Adi | AV22: =RIGHT(Sheet1!AF21,2) -> ta | AW22: =MID(Sheet1!AE21,2,3) -> dit | AX22: =LEN(Sheet1!AE21) -> 5 | AY22: =UPPER(Sheet1!AE21) -> ADITI | AZ22: =LOWER(Sheet1!AE21) -> aditi | BA22: =PROPER(Sheet1!AE21) -> Aditi | BB22: =_xlfn.CONCAT(Sheet1!AE21," ",Sheet1!AF21) -> Aditi Gupta | BL22: Laptop
A23: Headphones | B23: =SUMIFS(Sheet1!$N$2:$N$1001,Sheet1!$J$2:$J$1001,A23) -> 2740850 | AN23: =Sheet1!B22 -> 45326 | AO23: =IFERROR(DAY(AN23),VALUE(LEFT(AN23,2))) -> 4 | AP23: =IFERROR(MONTH(AN23),VALUE(MID(AN23,4,2))) -> 2 | AQ23: =IFERROR(YEAR(AN23),VALUE(RIGHT(AN23,4))) -> 2024 | AR23: =IF(ISNUMBER(AN23),TEXT(AN23,"mmm-yyyy"),TEXT(DATE(VALUE(RIGHT(AN23,4)),VALUE(MID(AN23,4,2)),VALUE(LEFT(AN23,2))),"mmm-yyyy")) -> Feb-2024 | AS23: =DATE(AQ23,AP23,AO23) -> 45326 | AT23: =TODAY()-AS23 -> 952 | AU23: =LEFT(Sheet1!AE22,3) -> Sne | AV23: =RIGHT(Sheet1!AF22,2) -> ra | AW23: =MID(Sheet1!AE22,2,3) -> neh | AX23: =LEN(Sheet1!AE22) -> 5 | AY23: =UPPER(Sheet1!AE22) -> SNEHA | AZ23: =LOWER(Sheet1!AE22) -> sneha | BA23: =PROPER(Sheet1!AE22) -> Sneha | BB23: =_xlfn.CONCAT(Sheet1!AE22," ",Sheet1!AF22) -> Sneha Mishra | BL23: Smartphone
A24: Stapler | B24: =SUMIFS(Sheet1!$N$2:$N$1001,Sheet1!$J$2:$J$1001,A24) -> 82717.5 | AN24: =Sheet1!B23 -> 45326 | AO24: =IFERROR(DAY(AN24),VALUE(LEFT(AN24,2))) -> 4 | AP24: =IFERROR(MONTH(AN24),VALUE(MID(AN24,4,2))) -> 2 | AQ24: =IFERROR(YEAR(AN24),VALUE(RIGHT(AN24,4))) -> 2024 | AR24: =IF(ISNUMBER(AN24),TEXT(AN24,"mmm-yyyy"),TEXT(DATE(VALUE(RIGHT(AN24,4)),VALUE(MID(AN24,4,2)),VALUE(LEFT(AN24,2))),"mmm-yyyy")) -> Feb-2024 | AS24: =DATE(AQ24,AP24,AO24) -> 45326 | AT24: =TODAY()-AS24 -> 952 | AU24: =LEFT(Sheet1!AE23,3) -> Rah | AV24: =RIGHT(Sheet1!AF23,2) -> ar | AW24: =MID(Sheet1!AE23,2,3) -> ahu | AX24: =LEN(Sheet1!AE23) -> 5 | AY24: =UPPER(Sheet1!AE23) -> RAHUL | AZ24: =LOWER(Sheet1!AE23) -> rahul | BA24: =PROPER(Sheet1!AE23) -> Rahul | BB24: =_xlfn.CONCAT(Sheet1!AE23," ",Sheet1!AF23) -> Rahul Kumar | BL24: Laptop
A25: Sofa | B25: =SUMIFS(Sheet1!$N$2:$N$1001,Sheet1!$J$2:$J$1001,A25) -> 1204050 | AN25: =Sheet1!B24 -> 45326 | AO25: =IFERROR(DAY(AN25),VALUE(LEFT(AN25,2))) -> 4 | AP25: =IFERROR(MONTH(AN25),VALUE(MID(AN25,4,2))) -> 2 | AQ25: =IFERROR(YEAR(AN25),VALUE(RIGHT(AN25,4))) -> 2024 | AR25: =IF(ISNUMBER(AN25),TEXT(AN25,"mmm-yyyy"),TEXT(DATE(VALUE(RIGHT(AN25,4)),VALUE(MID(AN25,4,2)),VALUE(LEFT(AN25,2))),"mmm-yyyy")) -> Feb-2024 | AS25: =DATE(AQ25,AP25,AO25) -> 45326 | AT25: =TODAY()-AS25 -> 952 | AU25: =LEFT(Sheet1!AE24,3) -> Kar | AV25: =RIGHT(Sheet1!AF24,2) -> gh | AW25: =MID(Sheet1!AE24,2,3) -> ara | AX25: =LEN(Sheet1!AE24) -> 5 | AY25: =UPPER(Sheet1!AE24) -> KARAN | AZ25: =LOWER(Sheet1!AE24) -> karan | BA25: =PROPER(Sheet1!AE24) -> Karan | BB25: =_xlfn.CONCAT(Sheet1!AE24," ",Sheet1!AF24) -> Karan Singh | BL25: Tablet
A26: Bookshelf | B26: =SUMIFS(Sheet1!$N$2:$N$1001,Sheet1!$J$2:$J$1001,A26) -> 1141650 | AN26: =Sheet1!B25 -> 45327 | AO26: =IFERROR(DAY(AN26),VALUE(LEFT(AN26,2))) -> 5 | AP26: =IFERROR(MONTH(AN26),VALUE(MID(AN26,4,2))) -> 2 | AQ26: =IFERROR(YEAR(AN26),VALUE(RIGHT(AN26,4))) -> 2024 | AR26: =IF(ISNUMBER(AN26),TEXT(AN26,"mmm-yyyy"),TEXT(DATE(VALUE(RIGHT(AN26,4)),VALUE(MID(AN26,4,2)),VALUE(LEFT(AN26,2))),"mmm-yyyy")) -> Feb-2024 | AS26: =DATE(AQ26,AP26,AO26) -> 45327 | AT26: =TODAY()-AS26 -> 951 | AU26: =LEFT(Sheet1!AE25,3) -> Nis | AV26: =RIGHT(Sheet1!AF25,2) -> av | AW26: =MID(Sheet1!AE25,2,3) -> ish | AX26: =LEN(Sheet1!AE25) -> 5 | AY26: =UPPER(Sheet1!AE25) -> NISHA | AZ26: =LOWER(Sheet1!AE25) -> nisha | BA26: =PROPER(Sheet1!AE25) -> Nisha | BB26: =_xlfn.CONCAT(Sheet1!AE25," ",Sheet1!AF25) -> Nisha Yadav | BL26: Smartphone
AN27: =Sheet1!B26 -> 45327 | AO27: =IFERROR(DAY(AN27),VALUE(LEFT(AN27,2))) -> 5 | AP27: =IFERROR(MONTH(AN27),VALUE(MID(AN27,4,2))) -> 2 | AQ27: =IFERROR(YEAR(AN27),VALUE(RIGHT(AN27,4))) -> 2024 | AR27: =IF(ISNUMBER(AN27),TEXT(AN27,"mmm-yyyy"),TEXT(DATE(VALUE(RIGHT(AN27,4)),VALUE(MID(AN27,4,2)),VALUE(LEFT(AN27,2))),"mmm-yyyy")) -> Feb-2024 | AS27: =DATE(AQ27,AP27,AO27) -> 45327 | AT27: =TODAY()-AS27 -> 951 | AU27: =LEFT(Sheet1!AE26,3) -> Kav | AV27: =RIGHT(Sheet1!AF26,2) -> al | AW27: =MID(Sheet1!AE26,2,3) -> avy | AX27: =LEN(Sheet1!AE26) -> 5 | AY27: =UPPER(Sheet1!AE26) -> KAVYA | AZ27: =LOWER(Sheet1!AE26) -> kavya | BA27: =PROPER(Sheet1!AE26) -> Kavya | BB27: =_xlfn.CONCAT(Sheet1!AE26," ",Sheet1!AF26) -> Kavya Bansal | BL27: Monitor
AN28: =Sheet1!B27 -> 45328 | AO28: =IFERROR(DAY(AN28),VALUE(LEFT(AN28,2))) -> 6 | AP28: =IFERROR(MONTH(AN28),VALUE(MID(AN28,4,2))) -> 2 | AQ28: =IFERROR(YEAR(AN28),VALUE(RIGHT(AN28,4))) -> 2024 | AR28: =IF(ISNUMBER(AN28),TEXT(AN28,"mmm-yyyy"),TEXT(DATE(VALUE(RIGHT(AN28,4)),VALUE(MID(AN28,4,2)),VALUE(LEFT(AN28,2))),"mmm-yyyy")) -> Feb-2024 | AS28: =DATE(AQ28,AP28,AO28) -> 45328 | AT28: =TODAY()-AS28 -> 950 | AU28: =LEFT(Sheet1!AE27,3) -> Pri | AV28: =RIGHT(Sheet1!AF27,2) -> av | AW28: =MID(Sheet1!AE27,2,3) -> riy | AX28: =LEN(Sheet1!AE27) -> 5 | AY28: =UPPER(Sheet1!AE27) -> PRIYA | AZ28: =LOWER(Sheet1!AE27) -> priya | BA28: =PROPER(Sheet1!AE27) -> Priya | BB28: =_xlfn.CONCAT(Sheet1!AE27," ",Sheet1!AF27) -> Priya Yadav | BL28: Smartphone
AN29: =Sheet1!B28 -> 45329 | AO29: =IFERROR(DAY(AN29),VALUE(LEFT(AN29,2))) -> 7 | AP29: =IFERROR(MONTH(AN29),VALUE(MID(AN29,4,2))) -> 2 | AQ29: =IFERROR(YEAR(AN29),VALUE(RIGHT(AN29,4))) -> 2024 | AR29: =IF(ISNUMBER(AN29),TEXT(AN29,"mmm-yyyy"),TEXT(DATE(VALUE(RIGHT(AN29,4)),VALUE(MID(AN29,4,2)),VALUE(LEFT(AN29,2))),"mmm-yyyy")) -> Feb-2024 | AS29: =DATE(AQ29,AP29,AO29) -> 45329 | AT29: =TODAY()-AS29 -> 949 | AU29: =LEFT(Sheet1!AE28,3) -> Adi | AV29: =RIGHT(Sheet1!AF28,2) -> na | AW29: =MID(Sheet1!AE28,2,3) -> dit | AX29: =LEN(Sheet1!AE28) -> 6 | AY29: =UPPER(Sheet1!AE28) -> ADITYA | AZ29: =LOWER(Sheet1!AE28) -> aditya | BA29: =PROPER(Sheet1!AE28) -> Aditya | BB29: =_xlfn.CONCAT(Sheet1!AE28," ",Sheet1!AF28) -> Aditya Saxena | BL29: Smartphone
AN30: =Sheet1!B29 -> 45329 | AO30: =IFERROR(DAY(AN30),VALUE(LEFT(AN30,2))) -> 7 | AP30: =IFERROR(MONTH(AN30),VALUE(MID(AN30,4,2))) -> 2 | AQ30: =IFERROR(YEAR(AN30),VALUE(RIGHT(AN30,4))) -> 2024 | AR30: =IF(ISNUMBER(AN30),TEXT(AN30,"mmm-yyyy"),TEXT(DATE(VALUE(RIGHT(AN30,4)),VALUE(MID(AN30,4,2)),VALUE(LEFT(AN30,2))),"mmm-yyyy")) -> Feb-2024 | AS30: =DATE(AQ30,AP30,AO30) -> 45329 | AT30: =TODAY()-AS30 -> 949 | AU30: =LEFT(Sheet1!AE29,3) -> Pri | AV30: =RIGHT(Sheet1!AF29,2) -> al | AW30: =MID(Sheet1!AE29,2,3) -> riy | AX30: =LEN(Sheet1!AE29) -> 5 | AY30: =UPPER(Sheet1!AE29) -> PRIYA | AZ30: =LOWER(Sheet1!AE29) -> priya | BA30: =PROPER(Sheet1!AE29) -> Priya | BB30: =_xlfn.CONCAT(Sheet1!AE29," ",Sheet1!AF29) -> Priya Bansal | BL30: Tablet
AN31: =Sheet1!B30 -> 45329 | AO31: =IFERROR(DAY(AN31),VALUE(LEFT(AN31,2))) -> 7 | AP31: =IFERROR(MONTH(AN31),VALUE(MID(AN31,4,2))) -> 2 | AQ31: =IFERROR(YEAR(AN31),VALUE(RIGHT(AN31,4))) -> 2024 | AR31: =IF(ISNUMBER(AN31),TEXT(AN31,"mmm-yyyy"),TEXT(DATE(VALUE(RIGHT(AN31,4)),VALUE(MID(AN31,4,2)),VALUE(LEFT(AN31,2))),"mmm-yyyy")) -> Feb-2024 | AS31: =DATE(AQ31,AP31,AO31) -> 45329 | AT31: =TODAY()-AS31 -> 949 | AU31: =LEFT(Sheet1!AE30,3) -> Neh | AV31: =RIGHT(Sheet1!AF30,2) -> ar | AW31: =MID(Sheet1!AE30,2,3) -> eha | AX31: =LEN(Sheet1!AE30) -> 4 | AY31: =UPPER(Sheet1!AE30) -> NEHA | AZ31: =LOWER(Sheet1!AE30) -> neha | BA31: =PROPER(Sheet1!AE30) -> Neha | BB31: =_xlfn.CONCAT(Sheet1!AE30," ",Sheet1!AF30) -> Neha Kumar | BL31: Laptop
AN32: =Sheet1!B31 -> 45330 | AO32: =IFERROR(DAY(AN32),VALUE(LEFT(AN32,2))) -> 8 | AP32: =IFERROR(MONTH(AN32),VALUE(MID(AN32,4,2))) -> 2 | AQ32: =IFERROR(YEAR(AN32),VALUE(RIGHT(AN32,4))) -> 2024 | AR32: =IF(ISNUMBER(AN32),TEXT(AN32,"mmm-yyyy"),TEXT(DATE(VALUE(RIGHT(AN32,4)),VALUE(MID(AN32,4,2)),VALUE(LEFT(AN32,2))),"mmm-yyyy")) -> Feb-2024 | AS32: =DATE(AQ32,AP32,AO32) -> 45330 | AT32: =TODAY()-AS32 -> 948 | AU32: =LEFT(Sheet1!AE31,3) -> Aar | AV32: =RIGHT(Sheet1!AF31,2) -> ma | AW32: =MID(Sheet1!AE31,2,3) -> ara | AX32: =LEN(Sheet1!AE31) -> 5 | AY32: =UPPER(Sheet1!AE31) -> AARAV | AZ32: =LOWER(Sheet1!AE31) -> aarav | BA32: =PROPER(Sheet1!AE31) -> Aarav | BB32: =_xlfn.CONCAT(Sheet1!AE31," ",Sheet1!AF31) -> Aarav Sharma | BL32: Tablet
AN33: =Sheet1!B32 -> 45331 | AO33: =IFERROR(DAY(AN33),VALUE(LEFT(AN33,2))) -> 9 | AP33: =IFERROR(MONTH(AN33),VALUE(MID(AN33,4,2))) -> 2 | AQ33: =IFERROR(YEAR(AN33),VALUE(RIGHT(AN33,4))) -> 2024 | AR33: =IF(ISNUMBER(AN33),TEXT(AN33,"mmm-yyyy"),TEXT(DATE(VALUE(RIGHT(AN33,4)),VALUE(MID(AN33,4,2)),VALUE(LEFT(AN33,2))),"mmm-yyyy")) -> Feb-2024 | AS33: =DATE(AQ33,AP33,AO33) -> 45331 | AT33: =TODAY()-AS33 -> 947 | AU33: =LEFT(Sheet1!AE32,3) -> Adi | AV33: =RIGHT(Sheet1!AF32,2) -> av | AW33: =MID(Sheet1!AE32,2,3) -> dit | AX33: =LEN(Sheet1!AE32) -> 6 | AY33: =UPPER(Sheet1!AE32) -> ADITYA | AZ33: =LOWER(Sheet1!AE32) -> aditya | BA33: =PROPER(Sheet1!AE32) -> Aditya | BB33: =_xlfn.CONCAT(Sheet1!AE32," ",Sheet1!AF32) -> Aditya Yadav | BL33: Headphones
AN34: =Sheet1!B33 -> 45332 | AO34: =IFERROR(DAY(AN34),VALUE(LEFT(AN34,2))) -> 10 | AP34: =IFERROR(MONTH(AN34),VALUE(MID(AN34,4,2))) -> 2 | AQ34: =IFERROR(YEAR(AN34),VALUE(RIGHT(AN34,4))) -> 2024 | AR34: =IF(ISNUMBER(AN34),TEXT(AN34,"mmm-yyyy"),TEXT(DATE(VALUE(RIGHT(AN34,4)),VALUE(MID(AN34,4,2)),VALUE(LEFT(AN34,2))),"mmm-yyyy")) -> Feb-2024 | AS34: =DATE(AQ34,AP34,AO34) -> 45332 | AT34: =TODAY()-AS34 -> 946 | AU34: =LEFT(Sheet1!AE33,3) -> Rah | AV34: =RIGHT(Sheet1!AF33,2) -> ra | AW34: =MID(Sheet1!AE33,2,3) -> ahu | AX34: =LEN(Sheet1!AE33) -> 5 | AY34: =UPPER(Sheet1!AE33) -> RAHUL | AZ34: =LOWER(Sheet1!AE33) -> rahul | BA34: =PROPER(Sheet1!AE33) -> Rahul | BB34: =_xlfn.CONCAT(Sheet1!AE33," ",Sheet1!AF33) -> Rahul Malhotra | BL34: Monitor
AN35: =Sheet1!B34 -> 45332 | AO35: =IFERROR(DAY(AN35),VALUE(LEFT(AN35,2))) -> 10 | AP35: =IFERROR(MONTH(AN35),VALUE(MID(AN35,4,2))) -> 2 | AQ35: =IFERROR(YEAR(AN35),VALUE(RIGHT(AN35,4))) -> 2024 | AR35: =IF(ISNUMBER(AN35),TEXT(AN35,"mmm-yyyy"),TEXT(DATE(VALUE(RIGHT(AN35,4)),VALUE(MID(AN35,4,2)),VALUE(LEFT(AN35,2))),"mmm-yyyy")) -> Feb-2024 | AS35: =DATE(AQ35,AP35,AO35) -> 45332 | AT35: =TODAY()-AS35 -> 946 | AU35: =LEFT(Sheet1!AE34,3) -> Mee | AV35: =RIGHT(Sheet1!AF34,2) -> ta | AW35: =MID(Sheet1!AE34,2,3) -> eer | AX35: =LEN(Sheet1!AE34) -> 5 | AY35: =UPPER(Sheet1!AE34) -> MEERA | AZ35: =LOWER(Sheet1!AE34) -> meera | BA35: =PROPER(Sheet1!AE34) -> Meera | BB35: =_xlfn.CONCAT(Sheet1!AE34," ",Sheet1!AF34) -> Meera Gupta | BL35: Monitor
AN36: =Sheet1!B35 -> 45332 | AO36: =IFERROR(DAY(AN36),VALUE(LEFT(AN36,2))) -> 10 | AP36: =IFERROR(MONTH(AN36),VALUE(MID(AN36,4,2))) -> 2 | AQ36: =IFERROR(YEAR(AN36),VALUE(RIGHT(AN36,4))) -> 2024 | AR36: =IF(ISNUMBER(AN36),TEXT(AN36,"mmm-yyyy"),TEXT(DATE(VALUE(RIGHT(AN36,4)),VALUE(MID(AN36,4,2)),VALUE(LEFT(AN36,2))),"mmm-yyyy")) -> Feb-2024 | AS36: =DATE(AQ36,AP36,AO36) -> 45332 | AT36: =TODAY()-AS36 -> 946 | AU36: =LEFT(Sheet1!AE35,3) -> Viv | AV36: =RIGHT(Sheet1!AF35,2) -> in | AW36: =MID(Sheet1!AE35,2,3) -> iva | AX36: =LEN(Sheet1!AE35) -> 6 | AY36: =UPPER(Sheet1!AE35) -> VIVAAN | AZ36: =LOWER(Sheet1!AE35) -> vivaan | BA36: =PROPER(Sheet1!AE35) -> Vivaan | BB36: =_xlfn.CONCAT(Sheet1!AE35," ",Sheet1!AF35) -> Vivaan Jain | BL36: Headphones
AN37: =Sheet1!B36 -> 45334 | AO37: =IFERROR(DAY(AN37),VALUE(LEFT(AN37,2))) -> 12 | AP37: =IFERROR(MONTH(AN37),VALUE(MID(AN37,4,2))) -> 2 | AQ37: =IFERROR(YEAR(AN37),VALUE(RIGHT(AN37,4))) -> 2024 | AR37: =IF(ISNUMBER(AN37),TEXT(AN37,"mmm-yyyy"),TEXT(DATE(VALUE(RIGHT(AN37,4)),VALUE(MID(AN37,4,2)),VALUE(LEFT(AN37,2))),"mmm-yyyy")) -> Feb-2024 | AS37: =DATE(AQ37,AP37,AO37) -> 45334 | AT37: =TODAY()-AS37 -> 944 | AU37: =LEFT(Sheet1!AE36,3) -> Vik | AV37: =RIGHT(Sheet1!AF36,2) -> or | AW37: =MID(Sheet1!AE36,2,3) -> ikr | AX37: =LEN(Sheet1!AE36) -> 6 | AY37: =UPPER(Sheet1!AE36) -> VIKRAM | AZ37: =LOWER(Sheet1!AE36) -> vikram | BA37: =PROPER(Sheet1!AE36) -> Vikram | BB37: =_xlfn.CONCAT(Sheet1!AE36," ",Sheet1!AF36) -> Vikram Kapoor | BL37: Smartphone
AN38: =Sheet1!B37 -> 45352 | AO38: =IFERROR(DAY(AN38),VALUE(LEFT(AN38,2))) -> 1 | AP38: =IFERROR(MONTH(AN38),VALUE(MID(AN38,4,2))) -> 3 | AQ38: =IFERROR(YEAR(AN38),VALUE(RIGHT(AN38,4))) -> 2024 | AR38: =IF(ISNUMBER(AN38),TEXT(AN38,"mmm-yyyy"),TEXT(DATE(VALUE(RIGHT(AN38,4)),VALUE(MID(AN38,4,2)),VALUE(LEFT(AN38,2))),"mmm-yyyy")) -> Mar-2024 | AS38: =DATE(AQ38,AP38,AO38) -> 45352 | AT38: =TODAY()-AS38 -> 926 | AU38: =LEFT(Sheet1!AE37,3) -> Ish | AV38: =RIGHT(Sheet1!AF37,2) -> ra | AW38: =MID(Sheet1!AE37,2,3) -> shi | AX38: =LEN(Sheet1!AE37) -> 6 | AY38: =UPPER(Sheet1!AE37) -> ISHITA | AZ38: =LOWER(Sheet1!AE37) -> ishita | BA38: =PROPER(Sheet1!AE37) -> Ishita | BB38: =_xlfn.CONCAT(Sheet1!AE37," ",Sheet1!AF37) -> Ishita Chopra | BL38: Monitor
... AN49: =Sheet1!B48 -> 45359 | AO49: =IFERROR(DAY(AN49),VALUE(LEFT(AN49,2))) -> 8 | AP49: =IFERROR(MONTH(AN49),VALUE(MID(AN49,4,2))) -> 3 | AQ49: =IFERROR(YEAR(AN49),VALUE(RIGHT(AN49,4))) -> 2024 | AR49: =IF(ISNUMBER(AN49),TEXT(AN49,"mmm-yyyy"),TEXT(DATE(VALUE(RIGHT(AN49,4)),VALUE(MID(AN49,4,2)),VALUE(LEFT(AN49,2))),"mmm-yyyy")) -> Mar-2024 | AS49: =DATE(AQ49,AP49,AO49) -> 45359 | AT49: =TODAY()-AS49 -> 919 | AU49: =LEFT(Sheet1!AE48,3) -> Neh | AV49: =RIGHT(Sheet1!AF48,2) -> ra | AW49: =MID(Sheet1!AE48,2,3) -> eha | AX49: =LEN(Sheet1!AE48) -> 4 | AY49: =UPPER(Sheet1!AE48) -> NEHA | AZ49: =LOWER(Sheet1!AE48) -> neha | BA49: =PROPER(Sheet1!AE48) -> Neha | BB49: =_xlfn.CONCAT(Sheet1!AE48," ",Sheet1!AF48) -> Neha Chopra | BL49: Monitor
